Workbook

Sheet Resumo Executivo
B2: Análise Comparativa de 3 Concorrentes — SIENO, BAGATELLE e AUMA
B3: Catálogos completos anunciados no Mercado Livre · gerado a partir dos 3 arquivos enviados
B5: Indicador | C5: SIENO | D5: BAGATELLE | E5: AUMA | F5: Total (3 concorrentes)
B6: Receita (R$) | C6: =SUMIF('Dados Brutos'!$T:$T,C$5,'Dados Brutos'!$C:$C) -> 8228730 | D6: =SUMIF('Dados Brutos'!$T:$T,D$5,'Dados Brutos'!$C:$C) -> 3808650 | E6: =SUMIF('Dados Brutos'!$T:$T,E$5,'Dados Brutos'!$C:$C) -> 9294080 | F6: =SUM(C6:E6) -> 21331460
B7: Unidades vendidas | C7: =SUMIF('Dados Brutos'!$T:$T,C$5,'Dados Brutos'!$D:$D) -> 79159 | D7: =SUMIF('Dados Brutos'!$T:$T,D$5,'Dados Brutos'!$D:$D) -> 6513 | E7: =SUMIF('Dados Brutos'!$T:$T,E$5,'Dados Brutos'!$D:$D) -> 18578 | F7: =SUM(C7:E7) -> 104250
B8: Anúncios (SKUs) | C8: =COUNTIF('Dados Brutos'!$T:$T,C$5) -> 893 | D8: =COUNTIF('Dados Brutos'!$T:$T,D$5) -> 1089 | E8: =COUNTIF('Dados Brutos'!$T:$T,E$5) -> 2006 | F8: =SUM(C8:E8) -> 3988
B9: Marcas distintas | C9: =SUMIFS('Dados Brutos'!$W:$W,'Dados Brutos'!$T:$T,C$5) -> 187 | D9: =SUMIFS('Dados Brutos'!$W:$W,'Dados Brutos'!$T:$T,D$5) -> 70 | E9: =SUMIFS('Dados Brutos'!$W:$W,'Dados Brutos'!$T:$T,E$5) -> 89 | F9: 275
B11: Marcas vendidas pelos 3 concorrentes | C11: =COUNTIF('Comparativo de Marcas'!K2:K276,"Sim") -> 19
B12: Marcas sinalizadas como oportunidade* | C12: =COUNTIF('Comparativo de Marcas'!L2:L276,"Sim") -> 64
B13: Marca líder em receita combinada | C13: ='Comparativo de Marcas'!A2 -> CAROLINA HERRERA
B15: * Critério de oportunidade (heurística do Bruno)
B16: Marca com ticket médio combinado >= R$100 (faixa em que a concorrência costuma ser menor) e demanda validada (>= 100 unidades vendidas somando os 3 catálogos). É um filtro de partida — cruzar sempre com margem, fornecedor e exclusividade de marca antes de decidir.
B18: Como usar este relatório
B19: • | C19: Aba "Oportunidades": só as marcas que passam no seu critério (ticket/volume), já filtradas — sem depender de cor —, e logo abaixo os anúncios individuais dessas marcas nos 3 concorrentes, ordenados por receita.
B20: • | C20: Aba "Comparativo de Marcas": a visão completa — todas as marcas dos 3 concorrentes lado a lado, com a receita em cada um, quantos concorrentes vendem cada marca e o sinalizador de oportunidade (linhas amarelas = vendida pelos 3; linhas verdes = passa no critério).
B21: • | C21: Aba "Por Categoria": mesma base, agrupada por categoria de produto (a SIENO vende outras coisas além de perfume; BAGATELLE e AUMA são quase 100% perfumaria).
B22: • | C22: Aba "Produtos por GTIN": junta os anúncios que são o mesmo produto (mesmo código de barras), já recuperando o tamanho certo ao cruzar as variações de título — e mostra, lado a lado, o preço de cada concorrente quando o mesmo GTIN aparece em mais de um.
B23: • | C23: Aba "Dados Brutos": os 3.988 anúncios originais dos 3 concorrentes, com a coluna "Categoria" classificada automaticamente. Corrigir uma linha aqui recalcula "Comparativo de Marcas", "Por Categoria" e a lista de marcas em "Oportunidades" — a lista de produtos em "Oportunidades" é fixa e precisa ser regenerada se os dados mudarem.
B25: Limitações e observações importantes
B26: • | C26: Os títulos dos anúncios vêm truncados em 40 caracteres na exportação de origem — a classificação por categoria usa apenas esse trecho, então uma parcela cai em "Outros/Diversos" por não bater com nenhuma palavra-chave.
B27: • | C27: SIENO tem um catálogo multi-categoria (perfumaria é ~29% da receita dela); BAGATELLE e AUMA são especializadas em perfumaria — a comparação de receita entre marcas é mais direta para as marcas de perfumaria presentes nos 3.
B28: • | C28: Isso mostra o que cada concorrente vende e fatura — não a margem deles, nem se há espaço real (exclusividade de marca, nº de outros vendedores, MSRP) pra você entrar. Ponto de partida pro garimpo, não decisão final.
B29: • | C29: Os números refletem o período coberto por cada exportação enviada (não informado nos arquivos, e pode não ser o mesmo período nos 3) — comparação pontual, não uma série histórica sincronizada.

Sheet Oportunidades
A1: Marcas oportunidade (64) — ticket médio combinado ≥ R$100 e ≥100 unidades vendidas (critério do Bruno)
A2: Marca | B2: Categoria | C2: Receita SIENO (R$) | D2: Receita BAGATELLE (R$) | E2: Receita AUMA (R$) | F2: Receita Total (R$) | G2: Unidades Total | H2: Ticket Médio (R$)
A3: =IFERROR(INDEX('Comparativo de Marcas'!$A:$A,MATCH(1,'Comparativo de Marcas'!$M:$M,0)),"") -> CAROLINA HERRERA | B3: =IFERROR(INDEX('Comparativo de Marcas'!$B:$B,MATCH(1,'Comparativo de Marcas'!$M:$M,0)),"") -> Perfumaria/Colonia | C3: =IFERROR(INDEX('Comparativo de Marcas'!$C:$C,MATCH(1,'Comparativo de Marcas'!$M:$M,0)),"") -> 0 | D3: =IFERROR(INDEX('Comparativo de Marcas'!$D:$D,MATCH(1,'Comparativo de Marcas'!$M:$M,0)),"") -> 1332020 | E3: =IFERROR(INDEX('Comparativo de Marcas'!$E:$E,MATCH(1,'Comparativo de Marcas'!$M:$M,0)),"") -> 2191200 | F3: =IFERROR(INDEX('Comparativo de Marcas'!$F:$F,MATCH(1,'Comparativo de Marcas'!$M:$M,0)),"") -> 3523220 | G3: =IFERROR(INDEX('Comparativo de Marcas'!$G:$G,MATCH(1,'Comparativo de Marcas'!$M:$M,0)),"") -> 5687 | H3: =IFERROR(INDEX('Comparativo de Marcas'!$I:$I,MATCH(1,'Comparativo de Marcas'!$M:$M,0)),"") -> 619.52172
A4: =IFERROR(INDEX('Comparativo de Marcas'!$A:$A,MATCH(2,'Comparativo de Marcas'!$M:$M,0)),"") -> RABANNE | B4: =IFERROR(INDEX('Comparativo de Marcas'!$B:$B,MATCH(2,'Comparativo de Marcas'!$M:$M,0)),"") -> Perfumaria/Colonia | C4: =IFERROR(INDEX('Comparativo de Marcas'!$C:$C,MATCH(2,'Comparativo de Marcas'!$M:$M,0)),"") -> 0 | D4: =IFERROR(INDEX('Comparativo de Marcas'!$D:$D,MATCH(2,'Comparativo de Marcas'!$M:$M,0)),"") -> 921250 | E4: =IFERROR(INDEX('Comparativo de Marcas'!$E:$E,MATCH(2,'Comparativo de Marcas'!$M:$M,0)),"") -> 1517680 | F4: =IFERROR(INDEX('Comparativo de Marcas'!$F:$F,MATCH(2,'Comparativo de Marcas'!$M:$M,0)),"") -> 2438930 | G4: =IFERROR(INDEX('Comparativo de Marcas'!$G:$G,MATCH(2,'Comparativo de Marcas'!$M:$M,0)),"") -> 3685 | H4: =IFERROR(INDEX('Comparativo de Marcas'!$I:$I,MATCH(2,'Comparativo de Marcas'!$M:$M,0)),"") -> 661.85346
A5: =IFERROR(INDEX('Comparativo de Marcas'!$A:$A,MATCH(3,'Comparativo de Marcas'!$M:$M,0)),"") -> JEAN PAUL GAULTIER | B5: =IFERROR(INDEX('Comparativo de Marcas'!$B:$B,MATCH(3,'Comparativo de Marcas'!$M:$M,0)),"") -> Perfumaria/Colonia | C5: =IFERROR(INDEX('Comparativo de Marcas'!$C:$C,MATCH(3,'Comparativo de Marcas'!$M:$M,0)),"") -> 0 | D5: =IFERROR(INDEX('Comparativo de Marcas'!$D:$D,MATCH(3,'Comparativo de Marcas'!$M:$M,0)),"") -> 387830 | E5: =IFERROR(INDEX('Comparativo de Marcas'!$E:$E,MATCH(3,'Comparativo de Marcas'!$M:$M,0)),"") -> 1397570 | F5: =IFERROR(INDEX('Comparativo de Marcas'!$F:$F,MATCH(3,'Comparativo de Marcas'!$M:$M,0)),"") -> 1785400 | G5: =IFERROR(INDEX('Comparativo de Marcas'!$G:$G,MATCH(3,'Comparativo de Marcas'!$M:$M,0)),"") -> 2595 | H5: =IFERROR(INDEX('Comparativo de Marcas'!$I:$I,MATCH(3,'Comparativo de Marcas'!$M:$M,0)),"") -> 688.01541
A6: =IFERROR(INDEX('Comparativo de Marcas'!$A:$A,MATCH(4,'Comparativo de Marcas'!$M:$M,0)),"") -> YVES SAINT LAURENT | B6: =IFERROR(INDEX('Comparativo de Marcas'!$B:$B,MATCH(4,'Comparativo de Marcas'!$M:$M,0)),"") -> Perfumaria/Colonia | C6: =IFERROR(INDEX('Comparativo de Marcas'!$C:$C,MATCH(4,'Comparativo de Marcas'!$M:$M,0)),"") -> 253760 | D6: =IFERROR(INDEX('Comparativo de Marcas'!$D:$D,MATCH(4,'Comparativo de Marcas'!$M:$M,0)),"") -> 17620 | E6: =IFERROR(INDEX('Comparativo de Marcas'!$E:$E,MATCH(4,'Comparativo de Marcas'!$M:$M,0)),"") -> 521750 | F6: =IFERROR(INDEX('Comparativo de Marcas'!$F:$F,MATCH(4,'Comparativo de Marcas'!$M:$M,0)),"") -> 793130 | G6: =IFERROR(INDEX('Comparativo de Marcas'!$G:$G,MATCH(4,'Comparativo de Marcas'!$M:$M,0)),"") -> 1123 | H6: =IFERROR(INDEX('Comparativo de Marcas'!$I:$I,MATCH(4,'Comparativo de Marcas'!$M:$M,0)),"") -> 706.26002
A7: =IFERROR(INDEX('Comparativo de Marcas'!$A:$A,MATCH(5,'Comparativo de Marcas'!$M:$M,0)),"") -> DOLCE & GABBANA | B7: =IFERROR(INDEX('Comparativo de Marcas'!$B:$B,MATCH(5,'Comparativo de Marcas'!$M:$M,0)),"") -> Perfumaria/Colonia | C7: =IFERROR(INDEX('Comparativo de Marcas'!$C:$C,MATCH(5,'Comparativo de Marcas'!$M:$M,0)),"") -> 178890 | D7: =IFERROR(INDEX('Comparativo de Marcas'!$D:$D,MATCH(5,'Comparativo de Marcas'!$M:$M,0)),"") -> 99900 | E7: =IFERROR(INDEX('Comparativo de Marcas'!$E:$E,MATCH(5,'Comparativo de Marcas'!$M:$M,0)),"") -> 170460 | F7: =IFERROR(INDEX('Comparativo de Marcas'!$F:$F,MATCH(5,'Comparativo de Marcas'!$M:$M,0)),"") -> 449250 | G7: =IFERROR(INDEX('Comparativo de Marcas'!$G:$G,MATCH(5,'Comparativo de Marcas'!$M:$M,0)),"") -> 670 | H7: =IFERROR(INDEX('Comparativo de Marcas'!$I:$I,MATCH(5,'Comparativo de Marcas'!$M:$M,0)),"") -> 670.52239
A8: =IFERROR(INDEX('Comparativo de Marcas'!$A:$A,MATCH(6,'Comparativo de Marcas'!$M:$M,0)),"") -> SHISEIDO | B8: =IFERROR(INDEX('Comparativo de Marcas'!$B:$B,MATCH(6,'Comparativo de Marcas'!$M:$M,0)),"") -> Perfumaria/Colonia | C8: =IFERROR(INDEX('Comparativo de Marcas'!$C:$C,MATCH(6,'Comparativo de Marcas'!$M:$M,0)),"") -> 0 | D8: =IFERROR(INDEX('Comparativo de Marcas'!$D:$D,MATCH(6,'Comparativo de Marcas'!$M:$M,0)),"") -> 0 | E8: =IFERROR(INDEX('Comparativo de Marcas'!$E:$E,MATCH(6,'Comparativo de Marcas'!$M:$M,0)),"") -> 447230 | F8: =IFERROR(INDEX('Comparativo de Marcas'!$F:$F,MATCH(6,'Comparativo de Marcas'!$M:$M,0)),"") -> 447230 | G8: =IFERROR(INDEX('Comparativo de Marcas'!$G:$G,MATCH(6,'Comparativo de Marcas'!$M:$M,0)),"") -> 1310 | H8: =IFERROR(INDEX('Comparativo de Marcas'!$I:$I,MATCH(6,'Comparativo de Marcas'!$M:$M,0)),"") -> 341.39695
A9: =IFERROR(INDEX('Comparativo de Marcas'!$A:$A,MATCH(7,'Comparativo de Marcas'!$M:$M,0)),"") -> LANCÔME | B9: =IFERROR(INDEX('Comparativo de Marcas'!$B:$B,MATCH(7,'Comparativo de Marcas'!$M:$M,0)),"") -> Perfumaria/Colonia | C9: =IFERROR(INDEX('Comparativo de Marcas'!$C:$C,MATCH(7,'Comparativo de Marcas'!$M:$M,0)),"") -> 0 | D9: =IFERROR(INDEX('Comparativo de Marcas'!$D:$D,MATCH(7,'Comparativo de Marcas'!$M:$M,0)),"") -> 0 | E9: =IFERROR(INDEX('Comparativo de Marcas'!$E:$E,MATCH(7,'Comparativo de Marcas'!$M:$M,0)),"") -> 443410 | F9: =IFERROR(INDEX('Comparativo de Marcas'!$F:$F,MATCH(7,'Comparativo de Marcas'!$M:$M,0)),"") -> 443410 | G9: =IFERROR(INDEX('Comparativo de Marcas'!$G:$G,MATCH(7,'Comparativo de Marcas'!$M:$M,0)),"") -> 774 | H9: =IFERROR(INDEX('Comparativo de Marcas'!$I:$I,MATCH(7,'Comparativo de Marcas'!$M:$M,0)),"") -> 572.88114
A10: =IFERROR(INDEX('Comparativo de Marcas'!$A:$A,MATCH(8,'Comparativo de Marcas'!$M:$M,0)),"") -> PRADA | B10: =IFERROR(INDEX('Comparativo de Marcas'!$B:$B,MATCH(8,'Comparativo de Marcas'!$M:$M,0)),"") -> Perfumaria/Colonia | C10: =IFERROR(INDEX('Comparativo de Marcas'!$C:$C,MATCH(8,'Comparativo de Marcas'!$M:$M,0)),"") -> 33000 | D10: =IFERROR(INDEX('Comparativo de Marcas'!$D:$D,MATCH(8,'Comparativo de Marcas'!$M:$M,0)),"") -> 940 | E10: =IFERROR(INDEX('Comparativo de Marcas'!$E:$E,MATCH(8,'Comparativo de Marcas'!$M:$M,0)),"") -> 372630 | F10: =IFERROR(INDEX('Comparativo de Marcas'!$F:$F,MATCH(8,'Comparativo de Marcas'!$M:$M,0)),"") -> 406570 | G10: =IFERROR(INDEX('Comparativo de Marcas'!$G:$G,MATCH(8,'Comparativo de Marcas'!$M:$M,0)),"") -> 519 | H10: =IFERROR(INDEX('Comparativo de Marcas'!$I:$I,MATCH(8,'Comparativo de Marcas'!$M:$M,0)),"") -> 783.37187
A11: =IFERROR(INDEX('Comparativo de Marcas'!$A:$A,MATCH(9,'Comparativo de Marcas'!$M:$M,0)),"") -> ARMANI BEAUTY | B11: =IFERROR(INDEX('Comparativo de Marcas'!$B:$B,MATCH(9,'Comparativo de Marcas'!$M:$M,0)),"") -> Perfumaria/Colonia | C11: =IFERROR(INDEX('Comparativo de Marcas'!$C:$C,MATCH(9,'Comparativo de Marcas'!$M:$M,0)),"") -> 0 | D11: =IFERROR(INDEX('Comparativo de Marcas'!$D:$D,MATCH(9,'Comparativo de Marcas'!$M:$M,0)),"") -> 0 | E11: =IFERROR(INDEX('Comparativo de Marcas'!$E:$E,MATCH(9,'Comparativo de Marcas'!$M:$M,0)),"") -> 402220 | F11: =IFERROR(INDEX('Comparativo de Marcas'!$F:$F,MATCH(9,'Comparativo de Marcas'!$M:$M,0)),"") -> 402220 | G11: =IFERROR(INDEX('Comparativo de Marcas'!$G:$G,MATCH(9,'Comparativo de Marcas'!$M:$M,0)),"") -> 540 | H11: =IFERROR(INDEX('Comparativo de Marcas'!$I:$I,MATCH(9,'Comparativo de Marcas'!$M:$M,0)),"") -> 744.85185
A12: =IFERROR(INDEX('Comparativo de Marcas'!$A:$A,MATCH(10,'Comparativo de Marcas'!$M:$M,0)),"") -> MARURI | B12: =IFERROR(INDEX('Comparativo de Marcas'!$B:$B,MATCH(10,'Comparativo de Marcas'!$M:$M,0)),"") -> Pesca/Nautica | C12: =IFERROR(INDEX('Comparativo de Marcas'!$C:$C,MATCH(10,'Comparativo de Marcas'!$M:$M,0)),"") -> 344600 | D12: =IFERROR(INDEX('Comparativo de Marcas'!$D:$D,MATCH(10,'Comparativo de Marcas'!$M:$M,0)),"") -> 0 | E12: =IFERROR(INDEX('Comparativo de Marcas'!$E:$E,MATCH(10,'Comparativo de Marcas'!$M:$M,0)),"") -> 0 | F12: =IFERROR(INDEX('Comparativo de Marcas'!$F:$F,MATCH(10,'Comparativo de Marcas'!$M:$M,0)),"") -> 344600 | G12: =IFERROR(INDEX('Comparativo de Marcas'!$G:$G,MATCH(10,'Comparativo de Marcas'!$M:$M,0)),"") -> 1042 | H12: =IFERROR(INDEX('Comparativo de Marcas'!$I:$I,MATCH(10,'Comparativo de Marcas'!$M:$M,0)),"") -> 330.71017
A13: =IFERROR(INDEX('Comparativo de Marcas'!$A:$A,MATCH(11,'Comparativo de Marcas'!$M:$M,0)),"") -> SHIMANO | B13: =IFERROR(INDEX('Comparativo de Marcas'!$B:$B,MATCH(11,'Comparativo de Marcas'!$M:$M,0)),"") -> Pesca/Nautica | C13: =IFERROR(INDEX('Comparativo de Marcas'!$C:$C,MATCH(11,'Comparativo de Marcas'!$M:$M,0)),"") -> 314200 | D13: =IFERROR(INDEX('Comparativo de Marcas'!$D:$D,MATCH(11,'Comparativo de Marcas'!$M:$M,0)),"") -> 0 | E13: =IFERROR(INDEX('Comparativo de Marcas'!$E:$E,MATCH(11,'Comparativo de Marcas'!$M:$M,0)),"") -> 0 | F13: =IFERROR(INDEX('Comparativo de Marcas'!$F:$F,MATCH(11,'Comparativo de Marcas'!$M:$M,0)),"") -> 314200 | G13: =IFERROR(INDEX('Comparativo de Marcas'!$G:$G,MATCH(11,'Comparativo de Marcas'!$M:$M,0)),"") -> 1307 | H13: =IFERROR(INDEX('Comparativo de Marcas'!$I:$I,MATCH(11,'Comparativo de Marcas'!$M:$M,0)),"") -> 240.39786
A14: =IFERROR(INDEX('Comparativo de Marcas'!$A:$A,MATCH(12,'Comparativo de Marcas'!$M:$M,0)),"") -> VERSACE | B14: =IFERROR(INDEX('Comparativo de Marcas'!$B:$B,MATCH(12,'Comparativo de Marcas'!$M:$M,0)),"") -> Perfumaria/Colonia | C14: =IFERROR(INDEX('Comparativo de Marcas'!$C:$C,MATCH(12,'Comparativo de Marcas'!$M:$M,0)),"") -> 0 | D14: =IFERROR(INDEX('Comparativo de Marcas'!$D:$D,MATCH(12,'Comparativo de Marcas'!$M:$M,0)),"") -> 77180 | E14: =IFERROR(INDEX('Comparativo de Marcas'!$E:$E,MATCH(12,'Comparativo de Marcas'!$M:$M,0)),"") -> 235620 | F14: =IFERROR(INDEX('Comparativo de Marcas'!$F:$F,MATCH(12,'Comparativo de Marcas'!$M:$M,0)),"") -> 312800 | G14: =IFERROR(INDEX('Comparativo de Marcas'!$G:$G,MATCH(12,'Comparativo de Marcas'!$M:$M,0)),"") -> 534 | H14: =IFERROR(INDEX('Comparativo de Marcas'!$I:$I,MATCH(12,'Comparativo de Marcas'!$M:$M,0)),"") -> 585.76779
A15: =IFERROR(INDEX('Comparativo de Marcas'!$A:$A,MATCH(13,'Comparativo de Marcas'!$M:$M,0)),"") -> WELLA | B15: =IFERROR(INDEX('Comparativo de Marcas'!$B:$B,MATCH(13,'Comparativo de Marcas'!$M:$M,0)),"") -> Perfumaria/Colonia | C15: =IFERROR(INDEX('Comparativo de Marcas'!$C:$C,MATCH(13,'Comparativo de Marcas'!$M:$M,0)),"") -> 0 | D15: =IFERROR(INDEX('Comparativo de Marcas'!$D:$D,MATCH(13,'Comparativo de Marcas'!$M:$M,0)),"") -> 0 | E15: =IFERROR(INDEX('Comparativo de Marcas'!$E:$E,MATCH(13,'Comparativo de Marcas'!$M:$M,0)),"") -> 233560 | F15: =IFERROR(INDEX('Comparativo de Marcas'!$F:$F,MATCH(13,'Comparativo de Marcas'!$M:$M,0)),"") -> 233560 | G15: =IFERROR(INDEX('Comparativo de Marcas'!$G:$G,MATCH(13,'Comparativo de Marcas'!$M:$M,0)),"") -> 1501 | H15: =IFERROR(INDEX('Comparativo de Marcas'!$I:$I,MATCH(13,'Comparativo de Marcas'!$M:$M,0)),"") -> 155.60293
A16: =IFERROR(INDEX('Comparativo de Marcas'!$A:$A,MATCH(14,'Comparativo de Marcas'!$M:$M,0)),"") -> HUGO BOSS | B16: =IFERROR(INDEX('Comparativo de Marcas'!$B:$B,MATCH(14,'Comparativo de Marcas'!$M:$M,0)),"") -> Perfumaria/Colonia | C16: =IFERROR(INDEX('Comparativo de Marcas'!$C:$C,MATCH(14,'Comparativo de Marcas'!$M:$M,0)),"") -> 85500 | D16: =IFERROR(INDEX('Comparativo de Marcas'!$D:$D,MATCH(14,'Comparativo de Marcas'!$M:$M,0)),"") -> 49190 | E16: =IFERROR(INDEX('Comparativo de Marcas'!$E:$E,MATCH(14,'Comparativo de Marcas'!$M:$M,0)),"") -> 76360 | F16: =IFERROR(INDEX('Comparativo de Marcas'!$F:$F,MATCH(14,'Comparativo de Marcas'!$M:$M,0)),"") -> 211050 | G16: =IFERROR(INDEX('Comparativo de Marcas'!$G:$G,MATCH(14,'Comparativo de Marcas'!$M:$M,0)),"") -> 426 | H16: =IFERROR(INDEX('Comparativo de Marcas'!$I:$I,MATCH(14,'Comparativo de Marcas'!$M:$M,0)),"") -> 495.42254
A17: =IFERROR(INDEX('Comparativo de Marcas'!$A:$A,MATCH(15,'Comparativo de Marcas'!$M:$M,0)),"") -> MARINE SPORTS | B17: =IFERROR(INDEX('Comparativo de Marcas'!$B:$B,MATCH(15,'Comparativo de Marcas'!$M:$M,0)),"") -> Pesca/Nautica | C17: =IFERROR(INDEX('Comparativo de Marcas'!$C:$C,MATCH(15,'Comparativo de Marcas'!$M:$M,0)),"") -> 207870 | D17: =IFERROR(INDEX('Comparativo de Marcas'!$D:$D,MATCH(15,'Comparativo de Marcas'!$M:$M,0)),"") -> 0 | E17: =IFERROR(INDEX('Comparativo de Marcas'!$E:$E,MATCH(15,'Comparativo de Marcas'!$M:$M,0)),"") -> 0 | F17: =IFERROR(INDEX('Comparativo de Marcas'!$F:$F,MATCH(15,'Comparativo de Marcas'!$M:$M,0)),"") -> 207870 | G17: =IFERROR(INDEX('Comparativo de Marcas'!$G:$G,MATCH(15,'Comparativo de Marcas'!$M:$M,0)),"") -> 1351 | H17: =IFERROR(INDEX('Comparativo de Marcas'!$I:$I,MATCH(15,'Comparativo de Marcas'!$M:$M,0)),"") -> 153.8638
A18: =IFERROR(INDEX('Comparativo de Marcas'!$A:$A,MATCH(16,'Comparativo de Marcas'!$M:$M,0)),"") -> INVICTUS | B18: =IFERROR(INDEX('Comparativo de Marcas'!$B:$B,MATCH(16,'Comparativo de Marcas'!$M:$M,0)),"") -> Tatico/Outdoor | C18: =IFERROR(INDEX('Comparativo de Marcas'!$C:$C,MATCH(16,'Comparativo de Marcas'!$M:$M,0)),"") -> 202830 | D18: =IFERROR(INDEX('Comparativo de Marcas'!$D:$D,MATCH(16,'Comparativo de Marcas'!$M:$M,0)),"") -> 0 | E18: =IFERROR(INDEX('Comparativo de Marcas'!$E:$E,MATCH(16,'Comparativo de Marcas'!$M:$M,0)),"") -> 0 | F18: =IFERROR(INDEX('Comparativo de Marcas'!$F:$F,MATCH(16,'Comparativo de Marcas'!$M:$M,0)),"") -> 202830 | G18: =IFERROR(INDEX('Comparativo de Marcas'!$G:$G,MATCH(16,'Comparativo de Marcas'!$M:$M,0)),"") -> 1208 | H18: =IFERROR(INDEX('Comparativo de Marcas'!$I:$I,MATCH(16,'Comparativo de Marcas'!$M:$M,0)),"") -> 167.90563
A19: =IFERROR(INDEX('Comparativo de Marcas'!$A:$A,MATCH(17,'Comparativo de Marcas'!$M:$M,0)),"") -> CALVIN KLEIN | B19: =IFERROR(INDEX('Comparativo de Marcas'!$B:$B,MATCH(17,'Comparativo de Marcas'!$M:$M,0)),"") -> Perfumaria/Colonia | C19: =IFERROR(INDEX('Comparativo de Marcas'!$C:$C,MATCH(17,'Comparativo de Marcas'!$M:$M,0)),"") -> 65700 | D19: =IFERROR(INDEX('Comparativo de Marcas'!$D:$D,MATCH(17,'Comparativo de Marcas'!$M:$M,0)),"") -> 128030 | E19: =IFERROR(INDEX('Comparativo de Marcas'!$E:$E,MATCH(17,'Comparativo de Marcas'!$M:$M,0)),"") -> 5280 | F19: =IFERROR(INDEX('Comparativo de Marcas'!$F:$F,MATCH(17,'Comparativo de Marcas'!$M:$M,0)),"") -> 199010 | G19: =IFERROR(INDEX('Comparativo de Marcas'!$G:$G,MATCH(17,'Comparativo de Marcas'!$M:$M,0)),"") -> 507 | H19: =IFERROR(INDEX('Comparativo de Marcas'!$I:$I,MATCH(17,'Comparativo de Marcas'!$M:$M,0)),"") -> 392.52465
A20: =IFERROR(INDEX('Comparativo de Marcas'!$A:$A,MATCH(18,'Comparativo de Marcas'!$M:$M,0)),"") -> BESTFER | B20: =IFERROR(INDEX('Comparativo de Marcas'!$B:$B,MATCH(18,'Comparativo de Marcas'!$M:$M,0)),"") -> Outros/Diversos | C20: =IFERROR(INDEX('Comparativo de Marcas'!$C:$C,MATCH(18,'Comparativo de Marcas'!$M:$M,0)),"") -> 196270 | D20: =IFERROR(INDEX('Comparativo de Marcas'!$D:$D,MATCH(18,'Comparativo de Marcas'!$M:$M,0)),"") -> 0 | E20: =IFERROR(INDEX('Comparativo de Marcas'!$E:$E,MATCH(18,'Comparativo de Marcas'!$M:$M,0)),"") -> 0 | F20: =IFERROR(INDEX('Comparativo de Marcas'!$F:$F,MATCH(18,'Comparativo de Marcas'!$M:$M,0)),"") -> 196270 | G20: =IFERROR(INDEX('Comparativo de Marcas'!$G:$G,MATCH(18,'Comparativo de Marcas'!$M:$M,0)),"") -> 1905 | H20: =IFERROR(INDEX('Comparativo de Marcas'!$I:$I,MATCH(18,'Comparativo de Marcas'!$M:$M,0)),"") -> 103.02887
A21: =IFERROR(INDEX('Comparativo de Marcas'!$A:$A,MATCH(19,'Comparativo de Marcas'!$M:$M,0)),"") -> GIORGIO ARMANI | B21: =IFERROR(INDEX('Comparativo de Marcas'!$B:$B,MATCH(19,'Comparativo de Marcas'!$M:$M,0)),"") -> Perfumaria/Colonia | C21: =IFERROR(INDEX('Comparativo de Marcas'!$C:$C,MATCH(19,'Comparativo de Marcas'!$M:$M,0)),"") -> 0 | D21: =IFERROR(INDEX('Comparativo de Marcas'!$D:$D,MATCH(19,'Comparativo de Marcas'!$M:$M,0)),"") -> 0 | E21: =IFERROR(INDEX('Comparativo de Marcas'!$E:$E,MATCH(19,'Comparativo de Marcas'!$M:$M,0)),"") -> 193570 | F21: =IFERROR(INDEX('Comparativo de Marcas'!$F:$F,MATCH(19,'Comparativo de Marcas'!$M:$M,0)),"") -> 193570 | G21: =IFERROR(INDEX('Comparativo de Marcas'!$G:$G,MATCH(19,'Comparativo de Marcas'!$M:$M,0)),"") -> 270 | H21: =IFERROR(INDEX('Comparativo de Marcas'!$I:$I,MATCH(19,'Comparativo de Marcas'!$M:$M,0)),"") -> 716.92593
A22: =IFERROR(INDEX('Comparativo de Marcas'!$A:$A,MATCH(20,'Comparativo de Marcas'!$M:$M,0)),"") -> JACQUES BOGART | B22: =IFERROR(INDEX('Comparativo de Marcas'!$B:$B,MATCH(20,'Comparativo de Marcas'!$M:$M,0)),"") -> Perfumaria/Colonia | C22: =IFERROR(INDEX('Comparativo de Marcas'!$C:$C,MATCH(20,'Comparativo de Marcas'!$M:$M,0)),"") -> 64100 | D22: =IFERROR(INDEX('Comparativo de Marcas'!$D:$D,MATCH(20,'Comparativo de Marcas'!$M:$M,0)),"") -> 128360 | E22: =IFERROR(INDEX('Comparativo de Marcas'!$E:$E,MATCH(20,'Comparativo de Marcas'!$M:$M,0)),"") -> 0 | F22: =IFERROR(INDEX('Comparativo de Marcas'!$F:$F,MATCH(20,'Comparativo de Marcas'!$M:$M,0)),"") -> 192460 | G22: =IFERROR(INDEX('Comparativo de Marcas'!$G:$G,MATCH(20,'Comparativo de Marcas'!$M:$M,0)),"") -> 635 | H22: =IFERROR(INDEX('Comparativo de Marcas'!$I:$I,MATCH(20,'Comparativo de Marcas'!$M:$M,0)),"") -> 303.08661
A23: =IFERROR(INDEX('Comparativo de Marcas'!$A:$A,MATCH(21,'Comparativo de Marcas'!$M:$M,0)),"") -> DEWALT | B23: =IFERROR(INDEX('Comparativo de Marcas'!$B:$B,MATCH(21,'Comparativo de Marcas'!$M:$M,0)),"") -> Ferramentas | C23: =IFERROR(INDEX('Comparativo de Marcas'!$C:$C,MATCH(21,'Comparativo de Marcas'!$M:$M,0)),"") -> 190000 | D23: =IFERROR(INDEX('Comparativo de Marcas'!$D:$D,MATCH(21,'Comparativo de Marcas'!$M:$M,0)),"") -> 0 | E23: =IFERROR(INDEX('Comparativo de Marcas'!$E:$E,MATCH(21,'Comparativo de Marcas'!$M:$M,0)),"") -> 0 | F23: =IFERROR(INDEX('Comparativo de Marcas'!$F:$F,MATCH(21,'Comparativo de Marcas'!$M:$M,0)),"") -> 190000 | G23: =IFERROR(INDEX('Comparativo de Marcas'!$G:$G,MATCH(21,'Comparativo de Marcas'!$M:$M,0)),"") -> 218 | H23: =IFERROR(INDEX('Comparativo de Marcas'!$I:$I,MATCH(21,'Comparativo de Marcas'!$M:$M,0)),"") -> 871.55963
A24: =IFERROR(INDEX('Comparativo de Marcas'!$A:$A,MATCH(22,'Comparativo de Marcas'!$M:$M,0)),"") -> CHLOÉ | B24: =IFERROR(INDEX('Comparativo de Marcas'!$B:$B,MATCH(22,'Comparativo de Marcas'!$M:$M,0)),"") -> Perfumaria/Colonia | C24: =IFERROR(INDEX('Comparativo de Marcas'!$C:$C,MATCH(22,'Comparativo de Marcas'!$M:$M,0)),"") -> 22240 | D24: =IFERROR(INDEX('Comparativo de Marcas'!$D:$D,MATCH(22,'Comparativo de Marcas'!$M:$M,0)),"") -> 86960 | E24: =IFERROR(INDEX('Comparativo de Marcas'!$E:$E,MATCH(22,'Comparativo de Marcas'!$M:$M,0)),"") -> 60830 | F24: =IFERROR(INDEX('Comparativo de Marcas'!$F:$F,MATCH(22,'Comparativo de Marcas'!$M:$M,0)),"") -> 170030 | G24: =IFERROR(INDEX('Comparativo de Marcas'!$G:$G,MATCH(22,'Comparativo de Marcas'!$M:$M,0)),"") -> 267 | H24: =IFERROR(INDEX('Comparativo de Marcas'!$I:$I,MATCH(22,'Comparativo de Marcas'!$M:$M,0)),"") -> 636.81648
A25: =IFERROR(INDEX('Comparativo de Marcas'!$A:$A,MATCH(23,'Comparativo de Marcas'!$M:$M,0)),"") -> BURBERRY | B25: =IFERROR(INDEX('Comparativo de Marcas'!$B:$B,MATCH(23,'Comparativo de Marcas'!$M:$M,0)),"") -> Perfumaria/Colonia | C25: =IFERROR(INDEX('Comparativo de Marcas'!$C:$C,MATCH(23,'Comparativo de Marcas'!$M:$M,0)),"") -> 33700 | D25: =IFERROR(INDEX('Comparativo de Marcas'!$D:$D,MATCH(23,'Comparativo de Marcas'!$M:$M,0)),"") -> 5390 | E25: =IFERROR(INDEX('Comparativo de Marcas'!$E:$E,MATCH(23,'Comparativo de Marcas'!$M:$M,0)),"") -> 100410 | F25: =IFERROR(INDEX('Comparativo de Marcas'!$F:$F,MATCH(23,'Comparativo de Marcas'!$M:$M,0)),"") -> 139500 | G25: =IFERROR(INDEX('Comparativo de Marcas'!$G:$G,MATCH(23,'Comparativo de Marcas'!$M:$M,0)),"") -> 238 | H25: =IFERROR(INDEX('Comparativo de Marcas'!$I:$I,MATCH(23,'Comparativo de Marcas'!$M:$M,0)),"") -> 586.13445
A26: =IFERROR(INDEX('Comparativo de Marcas'!$A:$A,MATCH(24,'Comparativo de Marcas'!$M:$M,0)),"") -> BANDERAS | B26: =IFERROR(INDEX('Comparativo de Marcas'!$B:$B,MATCH(24,'Comparativo de Marcas'!$M:$M,0)),"") -> Perfumaria/Colonia | C26: =IFERROR(INDEX('Comparativo de Marcas'!$C:$C,MATCH(24,'Comparativo de Marcas'!$M:$M,0)),"") -> 0 | D26: =IFERROR(INDEX('Comparativo de Marcas'!$D:$D,MATCH(24,'Comparativo de Marcas'!$M:$M,0)),"") -> 17780 | E26: =IFERROR(INDEX('Comparativo de Marcas'!$E:$E,MATCH(24,'Comparativo de Marcas'!$M:$M,0)),"") -> 113580 | F26: =IFERROR(INDEX('Comparativo de Marcas'!$F:$F,MATCH(24,'Comparativo de Marcas'!$M:$M,0)),"") -> 131360 | G26: =IFERROR(INDEX('Comparativo de Marcas'!$G:$G,MATCH(24,'Comparativo de Marcas'!$M:$M,0)),"") -> 653 | H26: =IFERROR(INDEX('Comparativo de Marcas'!$I:$I,MATCH(24,'Comparativo de Marcas'!$M:$M,0)),"") -> 201.16386
A27: =IFERROR(INDEX('Comparativo de Marcas'!$A:$A,MATCH(25,'Comparativo de Marcas'!$M:$M,0)),"") -> NAUTICA | B27: =IFERROR(INDEX('Comparativo de Marcas'!$B:$B,MATCH(25,'Comparativo de Marcas'!$M:$M,0)),"") -> Perfumaria/Colonia | C27: =IFERROR(INDEX('Comparativo de Marcas'!$C:$C,MATCH(25,'Comparativo de Marcas'!$M:$M,0)),"") -> 114510 | D27: =IFERROR(INDEX('Comparativo de Marcas'!$D:$D,MATCH(25,'Comparativo de Marcas'!$M:$M,0)),"") -> 7270 | E27: =IFERROR(INDEX('Comparativo de Marcas'!$E:$E,MATCH(25,'Comparativo de Marcas'!$M:$M,0)),"") -> 7260 | F27: =IFERROR(INDEX('Comparativo de Marcas'!$F:$F,MATCH(25,'Comparativo de Marcas'!$M:$M,0)),"") -> 129040 | G27: =IFERROR(INDEX('Comparativo de Marcas'!$G:$G,MATCH(25,'Comparativo de Marcas'!$M:$M,0)),"") -> 1224 | H27: =IFERROR(INDEX('Comparativo de Marcas'!$I:$I,MATCH(25,'Comparativo de Marcas'!$M:$M,0)),"") -> 105.42484
A28: =IFERROR(INDEX('Comparativo de Marcas'!$A:$A,MATCH(26,'Comparativo de Marcas'!$M:$M,0)),"") -> MAHOGANY | B28: =IFERROR(INDEX('Comparativo de Marcas'!$B:$B,MATCH(26,'Comparativo de Marcas'!$M:$M,0)),"") -> Perfumaria/Colonia | C28: =IFERROR(INDEX('Comparativo de Marcas'!$C:$C,MATCH(26,'Comparativo de Marcas'!$M:$M,0)),"") -> 0 | D28: =IFERROR(INDEX('Comparativo de Marcas'!$D:$D,MATCH(26,'Comparativo de Marcas'!$M:$M,0)),"") -> 0 | E28: =IFERROR(INDEX('Comparativo de Marcas'!$E:$E,MATCH(26,'Comparativo de Marcas'!$M:$M,0)),"") -> 114270 | F28: =IFERROR(INDEX('Comparativo de Marcas'!$F:$F,MATCH(26,'Comparativo de Marcas'!$M:$M,0)),"") -> 114270 | G28: =IFERROR(INDEX('Comparativo de Marcas'!$G:$G,MATCH(26,'Comparativo de Marcas'!$M:$M,0)),"") -> 807 | H28: =IFERROR(INDEX('Comparativo de Marcas'!$I:$I,MATCH(26,'Comparativo de Marcas'!$M:$M,0)),"") -> 141.59851
A29: =IFERROR(INDEX('Comparativo de Marcas'!$A:$A,MATCH(27,'Comparativo de Marcas'!$M:$M,0)),"") -> GUCCI | B29: =IFERROR(INDEX('Comparativo de Marcas'!$B:$B,MATCH(27,'Comparativo de Marcas'!$M:$M,0)),"") -> Perfumaria/Colonia | C29: =IFERROR(INDEX('Comparativo de Marcas'!$C:$C,MATCH(27,'Comparativo de Marcas'!$M:$M,0)),"") -> 0 | D29: =IFERROR(INDEX('Comparativo de Marcas'!$D:$D,MATCH(27,'Comparativo de Marcas'!$M:$M,0)),"") -> 29140 | E29: =IFERROR(INDEX('Comparativo de Marcas'!$E:$E,MATCH(27,'Comparativo de Marcas'!$M:$M,0)),"") -> 85100 | F29: =IFERROR(INDEX('Comparativo de Marcas'!$F:$F,MATCH(27,'Comparativo de Marcas'!$M:$M,0)),"") -> 114240 | G29: =IFERROR(INDEX('Comparativo de Marcas'!$G:$G,MATCH(27,'Comparativo de Marcas'!$M:$M,0)),"") -> 144 | H29: =IFERROR(INDEX('Comparativo de Marcas'!$I:$I,MATCH(27,'Comparativo de Marcas'!$M:$M,0)),"") -> 793.33333
A30: =IFERROR(INDEX('Comparativo de Marcas'!$A:$A,MATCH(28,'Comparativo de Marcas'!$M:$M,0)),"") -> AZZARO | B30: =IFERROR(INDEX('Comparativo de Marcas'!$B:$B,MATCH(28,'Comparativo de Marcas'!$M:$M,0)),"") -> Perfumaria/Colonia | C30: =IFERROR(INDEX('Comparativo de Marcas'!$C:$C,MATCH(28,'Comparativo de Marcas'!$M:$M,0)),"") -> 67300 | D30: =IFERROR(INDEX('Comparativo de Marcas'!$D:$D,MATCH(28,'Comparativo de Marcas'!$M:$M,0)),"") -> 0 | E30: =IFERROR(INDEX('Comparativo de Marcas'!$E:$E,MATCH(28,'Comparativo de Marcas'!$M:$M,0)),"") -> 46690 | F30: =IFERROR(INDEX('Comparativo de Marcas'!$F:$F,MATCH(28,'Comparativo de Marcas'!$M:$M,0)),"") -> 113990 | G30: =IFERROR(INDEX('Comparativo de Marcas'!$G:$G,MATCH(28,'Comparativo de Marcas'!$M:$M,0)),"") -> 297 | H30: =IFERROR(INDEX('Comparativo de Marcas'!$I:$I,MATCH(28,'Comparativo de Marcas'!$M:$M,0)),"") -> 383.80471
A31: =IFERROR(INDEX('Comparativo de Marcas'!$A:$A,MATCH(29,'Comparativo de Marcas'!$M:$M,0)),"") -> MAIS - GTECH | B31: =IFERROR(INDEX('Comparativo de Marcas'!$B:$B,MATCH(29,'Comparativo de Marcas'!$M:$M,0)),"") -> Saude/Bem-estar | C31: =IFERROR(INDEX('Comparativo de Marcas'!$C:$C,MATCH(29,'Comparativo de Marcas'!$M:$M,0)),"") -> 110000 | D31: =IFERROR(INDEX('Comparativo de Marcas'!$D:$D,MATCH(29,'Comparativo de Marcas'!$M:$M,0)),"") -> 0 | E31: =IFERROR(INDEX('Comparativo de Marcas'!$E:$E,MATCH(29,'Comparativo de Marcas'!$M:$M,0)),"") -> 0 | F31: =IFERROR(INDEX('Comparativo de Marcas'!$F:$F,MATCH(29,'Comparativo de Marcas'!$M:$M,0)),"") -> 110000 | G31: =IFERROR(INDEX('Comparativo de Marcas'!$G:$G,MATCH(29,'Comparativo de Marcas'!$M:$M,0)),"") -> 820 | H31: =IFERROR(INDEX('Comparativo de Marcas'!$I:$I,MATCH(29,'Comparativo de Marcas'!$M:$M,0)),"") -> 134.14634
A32: =IFERROR(INDEX('Comparativo de Marcas'!$A:$A,MATCH(30,'Comparativo de Marcas'!$M:$M,0)),"") -> MERCEDES-BENZ | B32: =IFERROR(INDEX('Comparativo de Marcas'!$B:$B,MATCH(30,'Comparativo de Marcas'!$M:$M,0)),"") -> Perfumaria/Colonia | C32: =IFERROR(INDEX('Comparativo de Marcas'!$C:$C,MATCH(30,'Comparativo de Marcas'!$M:$M,0)),"") -> 98400 | D32: =IFERROR(INDEX('Comparativo de Marcas'!$D:$D,MATCH(30,'Comparativo de Marcas'!$M:$M,0)),"") -> 10310 | E32: =IFERROR(INDEX('Comparativo de Marcas'!$E:$E,MATCH(30,'Comparativo de Marcas'!$M:$M,0)),"") -> 0 | F32: =IFERROR(INDEX('Comparativo de Marcas'!$F:$F,MATCH(30,'Comparativo de Marcas'!$M:$M,0)),"") -> 108710 | G32: =IFERROR(INDEX('Comparativo de Marcas'!$G:$G,MATCH(30,'Comparativo de Marcas'!$M:$M,0)),"") -> 340 | H32: =IFERROR(INDEX('Comparativo de Marcas'!$I:$I,MATCH(30,'Comparativo de Marcas'!$M:$M,0)),"") -> 319.73529
A33: =IFERROR(INDEX('Comparativo de Marcas'!$A:$A,MATCH(31,'Comparativo de Marcas'!$M:$M,0)),"") -> ADA TINA ITALY | B33: =IFERROR(INDEX('Comparativo de Marcas'!$B:$B,MATCH(31,'Comparativo de Marcas'!$M:$M,0)),"") -> Cosmeticos/Skincare | C33: =IFERROR(INDEX('Comparativo de Marcas'!$C:$C,MATCH(31,'Comparativo de Marcas'!$M:$M,0)),"") -> 102490 | D33: =IFERROR(INDEX('Comparativo de Marcas'!$D:$D,MATCH(31,'Comparativo de Marcas'!$M:$M,0)),"") -> 0 | E33: =IFERROR(INDEX('Comparativo de Marcas'!$E:$E,MATCH(31,'Comparativo de Marcas'!$M:$M,0)),"") -> 0 | F33: =IFERROR(INDEX('Comparativo de Marcas'!$F:$F,MATCH(31,'Comparativo de Marcas'!$M:$M,0)),"") -> 102490 | G33: =IFERROR(INDEX('Comparativo de Marcas'!$G:$G,MATCH(31,'Comparativo de Marcas'!$M:$M,0)),"") -> 859 | H33: =IFERROR(INDEX('Comparativo de Marcas'!$I:$I,MATCH(31,'Comparativo de Marcas'!$M:$M,0)),"") -> 119.31315
A34: =IFERROR(INDEX('Comparativo de Marcas'!$A:$A,MATCH(32,'Comparativo de Marcas'!$M:$M,0)),"") -> BRITNEY SPEARS | B34: =IFERROR(INDEX('Comparativo de Marcas'!$B:$B,MATCH(32,'Comparativo de Marcas'!$M:$M,0)),"") -> Perfumaria/Colonia | C34: =IFERROR(INDEX('Comparativo de Marcas'!$C:$C,MATCH(32,'Comparativo de Marcas'!$M:$M,0)),"") -> 97000 | D34: =IFERROR(INDEX('Comparativo de Marcas'!$D:$D,MATCH(32,'Comparativo de Marcas'!$M:$M,0)),"") -> 2880 | E34: =IFERROR(INDEX('Comparativo de Marcas'!$E:$E,MATCH(32,'Comparativo de Marcas'!$M:$M,0)),"") -> 570 | F34: =IFERROR(INDEX('Comparativo de Marcas'!$F:$F,MATCH(32,'Comparativo de Marcas'!$M:$M,0)),"") -> 100450 | G34: =IFERROR(INDEX('Comparativo de Marcas'!$G:$G,MATCH(32,'Comparativo de Marcas'!$M:$M,0)),"") -> 514 | H34: =IFERROR(INDEX('Comparativo de Marcas'!$I:$I,MATCH(32,'Comparativo de Marcas'!$M:$M,0)),"") -> 195.42802
A35: =IFERROR(INDEX('Comparativo de Marcas'!$A:$A,MATCH(33,'Comparativo de Marcas'!$M:$M,0)),"") -> KOMECO | B35: =IFERROR(INDEX('Comparativo de Marcas'!$B:$B,MATCH(33,'Comparativo de Marcas'!$M:$M,0)),"") -> Casa/Eletrodomesticos | C35: =IFERROR(INDEX('Comparativo de Marcas'!$C:$C,MATCH(33,'Comparativo de Marcas'!$M:$M,0)),"") -> 98500 | D35: =IFERROR(INDEX('Comparativo de Marcas'!$D:$D,MATCH(33,'Comparativo de Marcas'!$M:$M,0)),"") -> 0 | E35: =IFERROR(INDEX('Comparativo de Marcas'!$E:$E,MATCH(33,'Comparativo de Marcas'!$M:$M,0)),"") -> 0 | F35: =IFERROR(INDEX('Comparativo de Marcas'!$F:$F,MATCH(33,'Comparativo de Marcas'!$M:$M,0)),"") -> 98500 | G35: =IFERROR(INDEX('Comparativo de Marcas'!$G:$G,MATCH(33,'Comparativo de Marcas'!$M:$M,0)),"") -> 186 | H35: =IFERROR(INDEX('Comparativo de Marcas'!$I:$I,MATCH(33,'Comparativo de Marcas'!$M:$M,0)),"") -> 529.56989
A36: =IFERROR(INDEX('Comparativo de Marcas'!$A:$A,MATCH(34,'Comparativo de Marcas'!$M:$M,0)),"") -> RALPH LAUREN | B36: =IFERROR(INDEX('Comparativo de Marcas'!$B:$B,MATCH(34,'Comparativo de Marcas'!$M:$M,0)),"") -> Perfumaria/Colonia | C36: =IFERROR(INDEX('Comparativo de Marcas'!$C:$C,MATCH(34,'Comparativo de Marcas'!$M:$M,0)),"") -> 0 | D36: =IFERROR(INDEX('Comparativo de Marcas'!$D:$D,MATCH(34,'Comparativo de Marcas'!$M:$M,0)),"") -> 0 | E36: =IFERROR(INDEX('Comparativo de Marcas'!$E:$E,MATCH(34,'Comparativo de Marcas'!$M:$M,0)),"") -> 88440 | F36: =IFERROR(INDEX('Comparativo de Marcas'!$F:$F,MATCH(34,'Comparativo de Marcas'!$M:$M,0)),"") -> 88440 | G36: =IFERROR(INDEX('Comparativo de Marcas'!$G:$G,MATCH(34,'Comparativo de Marcas'!$M:$M,0)),"") -> 125 | H36: =IFERROR(INDEX('Comparativo de Marcas'!$I:$I,MATCH(34,'Comparativo de Marcas'!$M:$M,0)),"") -> 707.52
A37: =IFERROR(INDEX('Comparativo de Marcas'!$A:$A,MATCH(35,'Comparativo de Marcas'!$M:$M,0)),"") -> SOFT99 | B37: =IFERROR(INDEX('Comparativo de Marcas'!$B:$B,MATCH(35,'Comparativo de Marcas'!$M:$M,0)),"") -> Automotivo | C37: =IFERROR(INDEX('Comparativo de Marcas'!$C:$C,MATCH(35,'Comparativo de Marcas'!$M:$M,0)),"") -> 86100 | D37: =IFERROR(INDEX('Comparativo de Marcas'!$D:$D,MATCH(35,'Comparativo de Marcas'!$M:$M,0)),"") -> 0 | E37: =IFERROR(INDEX('Comparativo de Marcas'!$E:$E,MATCH(35,'Comparativo de Marcas'!$M:$M,0)),"") -> 0 | F37: =IFERROR(INDEX('Comparativo de Marcas'!$F:$F,MATCH(35,'Comparativo de Marcas'!$M:$M,0)),"") -> 86100 | G37: =IFERROR(INDEX('Comparativo de Marcas'!$G:$G,MATCH(35,'Comparativo de Marcas'!$M:$M,0)),"") -> 816 | H37: =IFERROR(INDEX('Comparativo de Marcas'!$I:$I,MATCH(35,'Comparativo de Marcas'!$M:$M,0)),"") -> 105.51471
A38: =IFERROR(INDEX('Comparativo de Marcas'!$A:$A,MATCH(36,'Comparativo de Marcas'!$M:$M,0)),"") -> MAVALA | B38: =IFERROR(INDEX('Comparativo de Marcas'!$B:$B,MATCH(36,'Comparativo de Marcas'!$M:$M,0)),"") -> Outros/Diversos | C38: =IFERROR(INDEX('Comparativo de Marcas'!$C:$C,MATCH(36,'Comparativo de Marcas'!$M:$M,0)),"") -> 74560 | D38: =IFERROR(INDEX('Comparativo de Marcas'!$D:$D,MATCH(36,'Comparativo de Marcas'!$M:$M,0)),"") -> 0 | E38: =IFERROR(INDEX('Comparativo de Marcas'!$E:$E,MATCH(36,'Comparativo de Marcas'!$M:$M,0)),"") -> 0 | F38: =IFERROR(INDEX('Comparativo de Marcas'!$F:$F,MATCH(36,'Comparativo de Marcas'!$M:$M,0)),"") -> 74560 | G38: =IFERROR(INDEX('Comparativo de Marcas'!$G:$G,MATCH(36,'Comparativo de Marcas'!$M:$M,0)),"") -> 662 | H38: =IFERROR(INDEX('Comparativo de Marcas'!$I:$I,MATCH(36,'Comparativo de Marcas'!$M:$M,0)),"") -> 112.6284
A39: =IFERROR(INDEX('Comparativo de Marcas'!$A:$A,MATCH(37,'Comparativo de Marcas'!$M:$M,0)),"") -> MONTBLANC | B39: =IFERROR(INDEX('Comparativo de Marcas'!$B:$B,MATCH(37,'Comparativo de Marcas'!$M:$M,0)),"") -> Perfumaria/Colonia | C39: =IFERROR(INDEX('Comparativo de Marcas'!$C:$C,MATCH(37,'Comparativo de Marcas'!$M:$M,0)),"") -> 3000 | D39: =IFERROR(INDEX('Comparativo de Marcas'!$D:$D,MATCH(37,'Comparativo de Marcas'!$M:$M,0)),"") -> 45370 | E39: =IFERROR(INDEX('Comparativo de Marcas'!$E:$E,MATCH(37,'Comparativo de Marcas'!$M:$M,0)),"") -> 24380 | F39: =IFERROR(INDEX('Comparativo de Marcas'!$F:$F,MATCH(37,'Comparativo de Marcas'!$M:$M,0)),"") -> 72750 | G39: =IFERROR(INDEX('Comparativo de Marcas'!$G:$G,MATCH(37,'Comparativo de Marcas'!$M:$M,0)),"") -> 131 | H39: =IFERROR(INDEX('Comparativo de Marcas'!$I:$I,MATCH(37,'Comparativo de Marcas'!$M:$M,0)),"") -> 555.34351
A40: =IFERROR(INDEX('Comparativo de Marcas'!$A:$A,MATCH(38,'Comparativo de Marcas'!$M:$M,0)),"") -> BLACK & DECKER | B40: =IFERROR(INDEX('Comparativo de Marcas'!$B:$B,MATCH(38,'Comparativo de Marcas'!$M:$M,0)),"") -> Ferramentas | C40: =IFERROR(INDEX('Comparativo de Marcas'!$C:$C,MATCH(38,'Comparativo de Marcas'!$M:$M,0)),"") -> 71620 | D40: =IFERROR(INDEX('Comparativo de Marcas'!$D:$D,MATCH(38,'Comparativo de Marcas'!$M:$M,0)),"") -> 0 | E40: =IFERROR(INDEX('Comparativo de Marcas'!$E:$E,MATCH(38,'Comparativo de Marcas'!$M:$M,0)),"") -> 0 | F40: =IFERROR(INDEX('Comparativo de Marcas'!$F:$F,MATCH(38,'Comparativo de Marcas'!$M:$M,0)),"") -> 71620 | G40: =IFERROR(INDEX('Comparativo de Marcas'!$G:$G,MATCH(38,'Comparativo de Marcas'!$M:$M,0)),"") -> 563 | H40: =IFERROR(INDEX('Comparativo de Marcas'!$I:$I,MATCH(38,'Comparativo de Marcas'!$M:$M,0)),"") -> 127.21137
A41: =IFERROR(INDEX('Comparativo de Marcas'!$A:$A,MATCH(39,'Comparativo de Marcas'!$M:$M,0)),"") -> ANIMALE | B41: =IFERROR(INDEX('Comparativo de Marcas'!$B:$B,MATCH(39,'Comparativo de Marcas'!$M:$M,0)),"") -> Perfumaria/Colonia | C41: =IFERROR(INDEX('Comparativo de Marcas'!$C:$C,MATCH(39,'Comparativo de Marcas'!$M:$M,0)),"") -> 42900 | D41: =IFERROR(INDEX('Comparativo de Marcas'!$D:$D,MATCH(39,'Comparativo de Marcas'!$M:$M,0)),"") -> 28130 | E41: =IFERROR(INDEX('Comparativo de Marcas'!$E:$E,MATCH(39,'Comparativo de Marcas'!$M:$M,0)),"") -> 0 | F41: =IFERROR(INDEX('Comparativo de Marcas'!$F:$F,MATCH(39,'Comparativo de Marcas'!$M:$M,0)),"") -> 71030 | G41: =IFERROR(INDEX('Comparativo de Marcas'!$G:$G,MATCH(39,'Comparativo de Marcas'!$M:$M,0)),"") -> 256 | H41: =IFERROR(INDEX('Comparativo de Marcas'!$I:$I,MATCH(39,'Comparativo de Marcas'!$M:$M,0)),"") -> 277.46094
A42: =IFERROR(INDEX('Comparativo de Marcas'!$A:$A,MATCH(40,'Comparativo de Marcas'!$M:$M,0)),"") -> GIVENCHY | B42: =IFERROR(INDEX('Comparativo de Marcas'!$B:$B,MATCH(40,'Comparativo de Marcas'!$M:$M,0)),"") -> Perfumaria/Colonia | C42: =IFERROR(INDEX('Comparativo de Marcas'!$C:$C,MATCH(40,'Comparativo de Marcas'!$M:$M,0)),"") -> 60550 | D42: =IFERROR(INDEX('Comparativo de Marcas'!$D:$D,MATCH(40,'Comparativo de Marcas'!$M:$M,0)),"") -> 7660 | E42: =IFERROR(INDEX('Comparativo de Marcas'!$E:$E,MATCH(40,'Comparativo de Marcas'!$M:$M,0)),"") -> 1980 | F42: =IFERROR(INDEX('Comparativo de Marcas'!$F:$F,MATCH(40,'Comparativo de Marcas'!$M:$M,0)),"") -> 70190 | G42: =IFERROR(INDEX('Comparativo de Marcas'!$G:$G,MATCH(40,'Comparativo de Marcas'!$M:$M,0)),"") -> 130 | H42: =IFERROR(INDEX('Comparativo de Marcas'!$I:$I,MATCH(40,'Comparativo de Marcas'!$M:$M,0)),"") -> 539.92308
A43: =IFERROR(INDEX('Comparativo de Marcas'!$A:$A,MATCH(41,'Comparativo de Marcas'!$M:$M,0)),"") -> NINA RICCI | B43: =IFERROR(INDEX('Comparativo de Marcas'!$B:$B,MATCH(41,'Comparativo de Marcas'!$M:$M,0)),"") -> Perfumaria/Colonia | C43: =IFERROR(INDEX('Comparativo de Marcas'!$C:$C,MATCH(41,'Comparativo de Marcas'!$M:$M,0)),"") -> 0 | D43: =IFERROR(INDEX('Comparativo de Marcas'!$D:$D,MATCH(41,'Comparativo de Marcas'!$M:$M,0)),"") -> 23210 | E43: =IFERROR(INDEX('Comparativo de Marcas'!$E:$E,MATCH(41,'Comparativo de Marcas'!$M:$M,0)),"") -> 44890 | F43: =IFERROR(INDEX('Comparativo de Marcas'!$F:$F,MATCH(41,'Comparativo de Marcas'!$M:$M,0)),"") -> 68100 | G43: =IFERROR(INDEX('Comparativo de Marcas'!$G:$G,MATCH(41,'Comparativo de Marcas'!$M:$M,0)),"") -> 149 | H43: =IFERROR(INDEX('Comparativo de Marcas'!$I:$I,MATCH(41,'Comparativo de Marcas'!$M:$M,0)),"") -> 457.04698
A44: =IFERROR(INDEX('Comparativo de Marcas'!$A:$A,MATCH(42,'Comparativo de Marcas'!$M:$M,0)),"") -> CENTRAL NUTRITION | B44: =IFERROR(INDEX('Comparativo de Marcas'!$B:$B,MATCH(42,'Comparativo de Marcas'!$M:$M,0)),"") -> Suplementos/Nutricao | C44: =IFERROR(INDEX('Comparativo de Marcas'!$C:$C,MATCH(42,'Comparativo de Marcas'!$M:$M,0)),"") -> 65400 | D44: =IFERROR(INDEX('Comparativo de Marcas'!$D:$D,MATCH(42,'Comparativo de Marcas'!$M:$M,0)),"") -> 0 | E44: =IFERROR(INDEX('Comparativo de Marcas'!$E:$E,MATCH(42,'Comparativo de Marcas'!$M:$M,0)),"") -> 0 | F44: =IFERROR(INDEX('Comparativo de Marcas'!$F:$F,MATCH(42,'Comparativo de Marcas'!$M:$M,0)),"") -> 65400 | G44: =IFERROR(INDEX('Comparativo de Marcas'!$G:$G,MATCH(42,'Comparativo de Marcas'!$M:$M,0)),"") -> 300 | H44: =IFERROR(INDEX('Comparativo de Marcas'!$I:$I,MATCH(42,'Comparativo de Marcas'!$M:$M,0)),"") -> 218
A45: =IFERROR(INDEX('Comparativo de Marcas'!$A:$A,MATCH(43,'Comparativo de Marcas'!$M:$M,0)),"") -> DAVIDOFF | B45: =IFERROR(INDEX('Comparativo de Marcas'!$B:$B,MATCH(43,'Comparativo de Marcas'!$M:$M,0)),"") -> Perfumaria/Colonia | C45: =IFERROR(INDEX('Comparativo de Marcas'!$C:$C,MATCH(43,'Comparativo de Marcas'!$M:$M,0)),"") -> 30800 | D45: =IFERROR(INDEX('Comparativo de Marcas'!$D:$D,MATCH(43,'Comparativo de Marcas'!$M:$M,0)),"") -> 28790 | E45: =IFERROR(INDEX('Comparativo de Marcas'!$E:$E,MATCH(43,'Comparativo de Marcas'!$M:$M,0)),"") -> 3160 | F45: =IFERROR(INDEX('Comparativo de Marcas'!$F:$F,MATCH(43,'Comparativo de Marcas'!$M:$M,0)),"") -> 62750 | G45: =IFERROR(INDEX('Comparativo de Marcas'!$G:$G,MATCH(43,'Comparativo de Marcas'!$M:$M,0)),"") -> 281 | H45: =IFERROR(INDEX('Comparativo de Marcas'!$I:$I,MATCH(43,'Comparativo de Marcas'!$M:$M,0)),"") -> 223.30961
A46: =IFERROR(INDEX('Comparativo de Marcas'!$A:$A,MATCH(44,'Comparativo de Marcas'!$M:$M,0)),"") -> ARMAF | B46: =IFERROR(INDEX('Comparativo de Marcas'!$B:$B,MATCH(44,'Comparativo de Marcas'!$M:$M,0)),"") -> Perfumaria/Colonia | C46: =IFERROR(INDEX('Comparativo de Marcas'!$C:$C,MATCH(44,'Comparativo de Marcas'!$M:$M,0)),"") -> 1810 | D46: =IFERROR(INDEX('Comparativo de Marcas'!$D:$D,MATCH(44,'Comparativo de Marcas'!$M:$M,0)),"") -> 46710 | E46: =IFERROR(INDEX('Comparativo de Marcas'!$E:$E,MATCH(44,'Comparativo de Marcas'!$M:$M,0)),"") -> 7670 | F46: =IFERROR(INDEX('Comparativo de Marcas'!$F:$F,MATCH(44,'Comparativo de Marcas'!$M:$M,0)),"") -> 56190 | G46: =IFERROR(INDEX('Comparativo de Marcas'!$G:$G,MATCH(44,'Comparativo de Marcas'!$M:$M,0)),"") -> 161 | H46: =IFERROR(INDEX('Comparativo de Marcas'!$I:$I,MATCH(44,'Comparativo de Marcas'!$M:$M,0)),"") -> 349.00621
A47: =IFERROR(INDEX('Comparativo de Marcas'!$A:$A,MATCH(45,'Comparativo de Marcas'!$M:$M,0)),"") -> MARINE | B47: =IFERROR(INDEX('Comparativo de Marcas'!$B:$B,MATCH(45,'Comparativo de Marcas'!$M:$M,0)),"") -> Pesca/Nautica | C47: =IFERROR(INDEX('Comparativo de Marcas'!$C:$C,MATCH(45,'Comparativo de Marcas'!$M:$M,0)),"") -> 52600 | D47: =IFERROR(INDEX('Comparativo de Marcas'!$D:$D,MATCH(45,'Comparativo de Marcas'!$M:$M,0)),"") -> 0 | E47: =IFERROR(INDEX('Comparativo de Marcas'!$E:$E,MATCH(45,'Comparativo de Marcas'!$M:$M,0)),"") -> 0 | F47: =IFERROR(INDEX('Comparativo de Marcas'!$F:$F,MATCH(45,'Comparativo de Marcas'!$M:$M,0)),"") -> 52600 | G47: =IFERROR(INDEX('Comparativo de Marcas'!$G:$G,MATCH(45,'Comparativo de Marcas'!$M:$M,0)),"") -> 150 | H47: =IFERROR(INDEX('Comparativo de Marcas'!$I:$I,MATCH(45,'Comparativo de Marcas'!$M:$M,0)),"") -> 350.66667
A48: =IFERROR(INDEX('Comparativo de Marcas'!$A:$A,MATCH(46,'Comparativo de Marcas'!$M:$M,0)),"") -> GABRIELA SABATINI | B48: =IFERROR(INDEX('Comparativo de Marcas'!$B:$B,MATCH(46,'Comparativo de Marcas'!$M:$M,0)),"") -> Perfumaria/Colonia | C48: =IFERROR(INDEX('Comparativo de Marcas'!$C:$C,MATCH(46,'Comparativo de Marcas'!$M:$M,0)),"") -> 45700 | D48: =IFERROR(INDEX('Comparativo de Marcas'!$D:$D,MATCH(46,'Comparativo de Marcas'!$M:$M,0)),"") -> 5710 | E48: =IFERROR(INDEX('Comparativo de Marcas'!$E:$E,MATCH(46,'Comparativo de Marcas'!$M:$M,0)),"") -> 680 | F48: =IFERROR(INDEX('Comparativo de Marcas'!$F:$F,MATCH(46,'Comparativo de Marcas'!$M:$M,0)),"") -> 52090 | G48: =IFERROR(INDEX('Comparativo de Marcas'!$G:$G,MATCH(46,'Comparativo de Marcas'!$M:$M,0)),"") -> 520 | H48: =IFERROR(INDEX('Comparativo de Marcas'!$I:$I,MATCH(46,'Comparativo de Marcas'!$M:$M,0)),"") -> 100.17308
A49: =IFERROR(INDEX('Comparativo de Marcas'!$A:$A,MATCH(47,'Comparativo de Marcas'!$M:$M,0)),"") -> JOOP! | B49: =IFERROR(INDEX('Comparativo de Marcas'!$B:$B,MATCH(47,'Comparativo de Marcas'!$M:$M,0)),"") -> Perfumaria/Colonia | C49: =IFERROR(INDEX('Comparativo de Marcas'!$C:$C,MATCH(47,'Comparativo de Marcas'!$M:$M,0)),"") -> 41400 | D49: =IFERROR(INDEX('Comparativo de Marcas'!$D:$D,MATCH(47,'Comparativo de Marcas'!$M:$M,0)),"") -> 10000 | E49: =IFERROR(INDEX('Comparativo de Marcas'!$E:$E,MATCH(47,'Comparativo de Marcas'!$M:$M,0)),"") -> 510 | F49: =IFERROR(INDEX('Comparativo de Marcas'!$F:$F,MATCH(47,'Comparativo de Marcas'!$M:$M,0)),"") -> 51910 | G49: =IFERROR(INDEX('Comparativo de Marcas'!$G:$G,MATCH(47,'Comparativo de Marcas'!$M:$M,0)),"") -> 235 | H49: =IFERROR(INDEX('Comparativo de Marcas'!$I:$I,MATCH(47,'Comparativo de Marcas'!$M:$M,0)),"") -> 220.89362
A50: =IFERROR(INDEX('Comparativo de Marcas'!$A:$A,MATCH(48,'Comparativo de Marcas'!$M:$M,0)),"") -> WESCO | B50: =IFERROR(INDEX('Comparativo de Marcas'!$B:$B,MATCH(48,'Comparativo de Marcas'!$M:$M,0)),"") -> Ferramentas | C50: =IFERROR(INDEX('Comparativo de Marcas'!$C:$C,MATCH(48,'Comparativo de Marcas'!$M:$M,0)),"") -> 49300 | D50: =IFERROR(INDEX('Comparativo de Marcas'!$D:$D,MATCH(48,'Comparativo de Marcas'!$M:$M,0)),"") -> 0 | E50: =IFERROR(INDEX('Comparativo de Marcas'!$E:$E,MATCH(48,'Comparativo de Marcas'!$M:$M,0)),"") -> 0 | F50: =IFERROR(INDEX('Comparativo de Marcas'!$F:$F,MATCH(48,'Comparativo de Marcas'!$M:$M,0)),"") -> 49300 | G50: =IFERROR(INDEX('Comparativo de Marcas'!$G:$G,MATCH(48,'Comparativo de Marcas'!$M:$M,0)),"") -> 267 | H50: =IFERROR(INDEX('Comparativo de Marcas'!$I:$I,MATCH(48,'Comparativo de Marcas'!$M:$M,0)),"") -> 184.64419
A51: =IFERROR(INDEX('Comparativo de Marcas'!$A:$A,MATCH(49,'Comparativo de Marcas'!$M:$M,0)),"") -> TOMMY HILFIGER | B51: =IFERROR(INDEX('Comparativo de Marcas'!$B:$B,MATCH(49,'Comparativo de Marcas'!$M:$M,0)),"") -> Perfumaria/Colonia | C51: =IFERROR(INDEX('Comparativo de Marcas'!$C:$C,MATCH(49,'Comparativo de Marcas'!$M:$M,0)),"") -> 26220 | D51: =IFERROR(INDEX('Comparativo de Marcas'!$D:$D,MATCH(49,'Comparativo de Marcas'!$M:$M,0)),"") -> 22580 | E51: =IFERROR(INDEX('Comparativo de Marcas'!$E:$E,MATCH(49,'Comparativo de Marcas'!$M:$M,0)),"") -> 0 | F51: =IFERROR(INDEX('Comparativo de Marcas'!$F:$F,MATCH(49,'Comparativo de Marcas'!$M:$M,0)),"") -> 48800 | G51: =IFERROR(INDEX('Comparativo de Marcas'!$G:$G,MATCH(49,'Comparativo de Marcas'!$M:$M,0)),"") -> 119 | H51: =IFERROR(INDEX('Comparativo de Marcas'!$I:$I,MATCH(49,'Comparativo de Marcas'!$M:$M,0)),"") -> 410.08403
A52: =IFERROR(INDEX('Comparativo de Marcas'!$A:$A,MATCH(50,'Comparativo de Marcas'!$M:$M,0)),"") -> MOSCHINO | B52: =IFERROR(INDEX('Comparativo de Marcas'!$B:$B,MATCH(50,'Comparativo de Marcas'!$M:$M,0)),"") -> Perfumaria/Colonia | C52: =IFERROR(INDEX('Comparativo de Marcas'!$C:$C,MATCH(50,'Comparativo de Marcas'!$M:$M,0)),"") -> 6540 | D52: =IFERROR(INDEX('Comparativo de Marcas'!$D:$D,MATCH(50,'Comparativo de Marcas'!$M:$M,0)),"") -> 9470 | E52: =IFERROR(INDEX('Comparativo de Marcas'!$E:$E,MATCH(50,'Comparativo de Marcas'!$M:$M,0)),"") -> 29510 | F52: =IFERROR(INDEX('Comparativo de Marcas'!$F:$F,MATCH(50,'Comparativo de Marcas'!$M:$M,0)),"") -> 45520 | G52: =IFERROR(INDEX('Comparativo de Marcas'!$G:$G,MATCH(50,'Comparativo de Marcas'!$M:$M,0)),"") -> 125 | H52: =IFERROR(INDEX('Comparativo de Marcas'!$I:$I,MATCH(50,'Comparativo de Marcas'!$M:$M,0)),"") -> 364.16
A53: =IFERROR(INDEX('Comparativo de Marcas'!$A:$A,MATCH(51,'Comparativo de Marcas'!$M:$M,0)),"") -> LORENZETTI | B53: =IFERROR(INDEX('Comparativo de Marcas'!$B:$B,MATCH(51,'Comparativo de Marcas'!$M:$M,0)),"") -> Casa/Eletrodomesticos | C53: =IFERROR(INDEX('Comparativo de Marcas'!$C:$C,MATCH(51,'Comparativo de Marcas'!$M:$M,0)),"") -> 45270 | D53: =IFERROR(INDEX('Comparativo de Marcas'!$D:$D,MATCH(51,'Comparativo de Marcas'!$M:$M,0)),"") -> 0 | E53: =IFERROR(INDEX('Comparativo de Marcas'!$E:$E,MATCH(51,'Comparativo de Marcas'!$M:$M,0)),"") -> 0 | F53: =IFERROR(INDEX('Comparativo de Marcas'!$F:$F,MATCH(51,'Comparativo de Marcas'!$M:$M,0)),"") -> 45270 | G53: =IFERROR(INDEX('Comparativo de Marcas'!$G:$G,MATCH(51,'Comparativo de Marcas'!$M:$M,0)),"") -> 175 | H53: =IFERROR(INDEX('Comparativo de Marcas'!$I:$I,MATCH(51,'Comparativo de Marcas'!$M:$M,0)),"") -> 258.68571
A54: =IFERROR(INDEX('Comparativo de Marcas'!$A:$A,MATCH(52,'Comparativo de Marcas'!$M:$M,0)),"") -> PLAYSTATION | B54: =IFERROR(INDEX('Comparativo de Marcas'!$B:$B,MATCH(52,'Comparativo de Marcas'!$M:$M,0)),"") -> Eletronicos/Games | C54: =IFERROR(INDEX('Comparativo de Marcas'!$C:$C,MATCH(52,'Comparativo de Marcas'!$M:$M,0)),"") -> 42000 | D54: =IFERROR(INDEX('Comparativo de Marcas'!$D:$D,MATCH(52,'Comparativo de Marcas'!$M:$M,0)),"") -> 0 | E54: =IFERROR(INDEX('Comparativo de Marcas'!$E:$E,MATCH(52,'Comparativo de Marcas'!$M:$M,0)),"") -> 0 | F54: =IFERROR(INDEX('Comparativo de Marcas'!$F:$F,MATCH(52,'Comparativo de Marcas'!$M:$M,0)),"") -> 42000 | G54: =IFERROR(INDEX('Comparativo de Marcas'!$G:$G,MATCH(52,'Comparativo de Marcas'!$M:$M,0)),"") -> 103 | H54: =IFERROR(INDEX('Comparativo de Marcas'!$I:$I,MATCH(52,'Comparativo de Marcas'!$M:$M,0)),"") -> 407.76699
A55: =IFERROR(INDEX('Comparativo de Marcas'!$A:$A,MATCH(53,'Comparativo de Marcas'!$M:$M,0)),"") -> AL WATANIAH | B55: =IFERROR(INDEX('Comparativo de Marcas'!$B:$B,MATCH(53,'Comparativo de Marcas'!$M:$M,0)),"") -> Perfumaria/Colonia | C55: =IFERROR(INDEX('Comparativo de Marcas'!$C:$C,MATCH(53,'Comparativo de Marcas'!$M:$M,0)),"") -> 23250 | D55: =IFERROR(INDEX('Comparativo de Marcas'!$D:$D,MATCH(53,'Comparativo de Marcas'!$M:$M,0)),"") -> 9230 | E55: =IFERROR(INDEX('Comparativo de Marcas'!$E:$E,MATCH(53,'Comparativo de Marcas'!$M:$M,0)),"") -> 0 | F55: =IFERROR(INDEX('Comparativo de Marcas'!$F:$F,MATCH(53,'Comparativo de Marcas'!$M:$M,0)),"") -> 32480 | G55: =IFERROR(INDEX('Comparativo de Marcas'!$G:$G,MATCH(53,'Comparativo de Marcas'!$M:$M,0)),"") -> 184 | H55: =IFERROR(INDEX('Comparativo de Marcas'!$I:$I,MATCH(53,'Comparativo de Marcas'!$M:$M,0)),"") -> 176.52174
A56: =IFERROR(INDEX('Comparativo de Marcas'!$A:$A,MATCH(54,'Comparativo de Marcas'!$M:$M,0)),"") -> ELIZABETH ARDEN | B56: =IFERROR(INDEX('Comparativo de Marcas'!$B:$B,MATCH(54,'Comparativo de Marcas'!$M:$M,0)),"") -> Perfumaria/Colonia | C56: =IFERROR(INDEX('Comparativo de Marcas'!$C:$C,MATCH(54,'Comparativo de Marcas'!$M:$M,0)),"") -> 23300 | D56: =IFERROR(INDEX('Comparativo de Marcas'!$D:$D,MATCH(54,'Comparativo de Marcas'!$M:$M,0)),"") -> 8390 | E56: =IFERROR(INDEX('Comparativo de Marcas'!$E:$E,MATCH(54,'Comparativo de Marcas'!$M:$M,0)),"") -> 0 | F56: =IFERROR(INDEX('Comparativo de Marcas'!$F:$F,MATCH(54,'Comparativo de Marcas'!$M:$M,0)),"") -> 31690 | G56: =IFERROR(INDEX('Comparativo de Marcas'!$G:$G,MATCH(54,'Comparativo de Marcas'!$M:$M,0)),"") -> 191 | H56: =IFERROR(INDEX('Comparativo de Marcas'!$I:$I,MATCH(54,'Comparativo de Marcas'!$M:$M,0)),"") -> 165.91623
A57: =IFERROR(INDEX('Comparativo de Marcas'!$A:$A,MATCH(55,'Comparativo de Marcas'!$M:$M,0)),"") -> GILLES CANTUEL | B57: =IFERROR(INDEX('Comparativo de Marcas'!$B:$B,MATCH(55,'Comparativo de Marcas'!$M:$M,0)),"") -> Perfumaria/Colonia | C57: =IFERROR(INDEX('Comparativo de Marcas'!$C:$C,MATCH(55,'Comparativo de Marcas'!$M:$M,0)),"") -> 17410 | D57: =IFERROR(INDEX('Comparativo de Marcas'!$D:$D,MATCH(55,'Comparativo de Marcas'!$M:$M,0)),"") -> 11930 | E57: =IFERROR(INDEX('Comparativo de Marcas'!$E:$E,MATCH(55,'Comparativo de Marcas'!$M:$M,0)),"") -> 300 | F57: =IFERROR(INDEX('Comparativo de Marcas'!$F:$F,MATCH(55,'Comparativo de Marcas'!$M:$M,0)),"") -> 29640 | G57: =IFERROR(INDEX('Comparativo de Marcas'!$G:$G,MATCH(55,'Comparativo de Marcas'!$M:$M,0)),"") -> 158 | H57: =IFERROR(INDEX('Comparativo de Marcas'!$I:$I,MATCH(55,'Comparativo de Marcas'!$M:$M,0)),"") -> 187.59494
A58: =IFERROR(INDEX('Comparativo de Marcas'!$A:$A,MATCH(56,'Comparativo de Marcas'!$M:$M,0)),"") -> CHAOYANG | B58: =IFERROR(INDEX('Comparativo de Marcas'!$B:$B,MATCH(56,'Comparativo de Marcas'!$M:$M,0)),"") -> Bike/Ciclismo | C58: =IFERROR(INDEX('Comparativo de Marcas'!$C:$C,MATCH(56,'Comparativo de Marcas'!$M:$M,0)),"") -> 29440 | D58: =IFERROR(INDEX('Comparativo de Marcas'!$D:$D,MATCH(56,'Comparativo de Marcas'!$M:$M,0)),"") -> 0 | E58: =IFERROR(INDEX('Comparativo de Marcas'!$E:$E,MATCH(56,'Comparativo de Marcas'!$M:$M,0)),"") -> 0 | F58: =IFERROR(INDEX('Comparativo de Marcas'!$F:$F,MATCH(56,'Comparativo de Marcas'!$M:$M,0)),"") -> 29440 | G58: =IFERROR(INDEX('Comparativo de Marcas'!$G:$G,MATCH(56,'Comparativo de Marcas'!$M:$M,0)),"") -> 211 | H58: =IFERROR(INDEX('Comparativo de Marcas'!$I:$I,MATCH(56,'Comparativo de Marcas'!$M:$M,0)),"") -> 139.52607
A59: =IFERROR(INDEX('Comparativo de Marcas'!$A:$A,MATCH(57,'Comparativo de Marcas'!$M:$M,0)),"") -> BENETTON | B59: =IFERROR(INDEX('Comparativo de Marcas'!$B:$B,MATCH(57,'Comparativo de Marcas'!$M:$M,0)),"") -> Perfumaria/Colonia | C59: =IFERROR(INDEX('Comparativo de Marcas'!$C:$C,MATCH(57,'Comparativo de Marcas'!$M:$M,0)),"") -> 0 | D59: =IFERROR(INDEX('Comparativo de Marcas'!$D:$D,MATCH(57,'Comparativo de Marcas'!$M:$M,0)),"") -> 10060 | E59: =IFERROR(INDEX('Comparativo de Marcas'!$E:$E,MATCH(57,'Comparativo de Marcas'!$M:$M,0)),"") -> 17330 | F59: =IFERROR(INDEX('Comparativo de Marcas'!$F:$F,MATCH(57,'Comparativo de Marcas'!$M:$M,0)),"") -> 27390 | G59: =IFERROR(INDEX('Comparativo de Marcas'!$G:$G,MATCH(57,'Comparativo de Marcas'!$M:$M,0)),"") -> 127 | H59: =IFERROR(INDEX('Comparativo de Marcas'!$I:$I,MATCH(57,'Comparativo de Marcas'!$M:$M,0)),"") -> 215.66929
A60: =IFERROR(INDEX('Comparativo de Marcas'!$A:$A,MATCH(58,'Comparativo de Marcas'!$M:$M,0)),"") -> LATTAFA | B60: =IFERROR(INDEX('Comparativo de Marcas'!$B:$B,MATCH(58,'Comparativo de Marcas'!$M:$M,0)),"") -> Perfumaria/Colonia | C60: =IFERROR(INDEX('Comparativo de Marcas'!$C:$C,MATCH(58,'Comparativo de Marcas'!$M:$M,0)),"") -> 22610 | D60: =IFERROR(INDEX('Comparativo de Marcas'!$D:$D,MATCH(58,'Comparativo de Marcas'!$M:$M,0)),"") -> 2370 | E60: =IFERROR(INDEX('Comparativo de Marcas'!$E:$E,MATCH(58,'Comparativo de Marcas'!$M:$M,0)),"") -> 1730 | F60: =IFERROR(INDEX('Comparativo de Marcas'!$F:$F,MATCH(58,'Comparativo de Marcas'!$M:$M,0)),"") -> 26710 | G60: =IFERROR(INDEX('Comparativo de Marcas'!$G:$G,MATCH(58,'Comparativo de Marcas'!$M:$M,0)),"") -> 100 | H60: =IFERROR(INDEX('Comparativo de Marcas'!$I:$I,MATCH(58,'Comparativo de Marcas'!$M:$M,0)),"") -> 267.1
A61: =IFERROR(INDEX('Comparativo de Marcas'!$A:$A,MATCH(59,'Comparativo de Marcas'!$M:$M,0)),"") -> PHILIPS | B61: =IFERROR(INDEX('Comparativo de Marcas'!$B:$B,MATCH(59,'Comparativo de Marcas'!$M:$M,0)),"") -> Outros/Diversos | C61: =IFERROR(INDEX('Comparativo de Marcas'!$C:$C,MATCH(59,'Comparativo de Marcas'!$M:$M,0)),"") -> 24400 | D61: =IFERROR(INDEX('Comparativo de Marcas'!$D:$D,MATCH(59,'Comparativo de Marcas'!$M:$M,0)),"") -> 0 | E61: =IFERROR(INDEX('Comparativo de Marcas'!$E:$E,MATCH(59,'Comparativo de Marcas'!$M:$M,0)),"") -> 0 | F61: =IFERROR(INDEX('Comparativo de Marcas'!$F:$F,MATCH(59,'Comparativo de Marcas'!$M:$M,0)),"") -> 24400 | G61: =IFERROR(INDEX('Comparativo de Marcas'!$G:$G,MATCH(59,'Comparativo de Marcas'!$M:$M,0)),"") -> 226 | H61: =IFERROR(INDEX('Comparativo de Marcas'!$I:$I,MATCH(59,'Comparativo de Marcas'!$M:$M,0)),"") -> 107.9646
A62: =IFERROR(INDEX('Comparativo de Marcas'!$A:$A,MATCH(60,'Comparativo de Marcas'!$M:$M,0)),"") -> TEND SKIN | B62: =IFERROR(INDEX('Comparativo de Marcas'!$B:$B,MATCH(60,'Comparativo de Marcas'!$M:$M,0)),"") -> Outros/Diversos | C62: =IFERROR(INDEX('Comparativo de Marcas'!$C:$C,MATCH(60,'Comparativo de Marcas'!$M:$M,0)),"") -> 22000 | D62: =IFERROR(INDEX('Comparativo de Marcas'!$D:$D,MATCH(60,'Comparativo de Marcas'!$M:$M,0)),"") -> 0 | E62: =IFERROR(INDEX('Comparativo de Marcas'!$E:$E,MATCH(60,'Comparativo de Marcas'!$M:$M,0)),"") -> 0 | F62: =IFERROR(INDEX('Comparativo de Marcas'!$F:$F,MATCH(60,'Comparativo de Marcas'!$M:$M,0)),"") -> 22000 | G62: =IFERROR(INDEX('Comparativo de Marcas'!$G:$G,MATCH(60,'Comparativo de Marcas'!$M:$M,0)),"") -> 100 | H62: =IFERROR(INDEX('Comparativo de Marcas'!$I:$I,MATCH(60,'Comparativo de Marcas'!$M:$M,0)),"") -> 220
A63: =IFERROR(INDEX('Comparativo de Marcas'!$A:$A,MATCH(61,'Comparativo de Marcas'!$M:$M,0)),"") -> ESTRELA | B63: =IFERROR(INDEX('Comparativo de Marcas'!$B:$B,MATCH(61,'Comparativo de Marcas'!$M:$M,0)),"") -> Outros/Diversos | C63: =IFERROR(INDEX('Comparativo de Marcas'!$C:$C,MATCH(61,'Comparativo de Marcas'!$M:$M,0)),"") -> 21700 | D63: =IFERROR(INDEX('Comparativo de Marcas'!$D:$D,MATCH(61,'Comparativo de Marcas'!$M:$M,0)),"") -> 0 | E63: =IFERROR(INDEX('Comparativo de Marcas'!$E:$E,MATCH(61,'Comparativo de Marcas'!$M:$M,0)),"") -> 0 | F63: =IFERROR(INDEX('Comparativo de Marcas'!$F:$F,MATCH(61,'Comparativo de Marcas'!$M:$M,0)),"") -> 21700 | G63: =IFERROR(INDEX('Comparativo de Marcas'!$G:$G,MATCH(61,'Comparativo de Marcas'!$M:$M,0)),"") -> 110 | H63: =IFERROR(INDEX('Comparativo de Marcas'!$I:$I,MATCH(61,'Comparativo de Marcas'!$M:$M,0)),"") -> 197.27273
A64: =IFERROR(INDEX('Comparativo de Marcas'!$A:$A,MATCH(62,'Comparativo de Marcas'!$M:$M,0)),"") -> MIKATOS | B64: =IFERROR(INDEX('Comparativo de Marcas'!$B:$B,MATCH(62,'Comparativo de Marcas'!$M:$M,0)),"") -> Saude/Bem-estar | C64: =IFERROR(INDEX('Comparativo de Marcas'!$C:$C,MATCH(62,'Comparativo de Marcas'!$M:$M,0)),"") -> 21000 | D64: =IFERROR(INDEX('Comparativo de Marcas'!$D:$D,MATCH(62,'Comparativo de Marcas'!$M:$M,0)),"") -> 0 | E64: =IFERROR(INDEX('Comparativo de Marcas'!$E:$E,MATCH(62,'Comparativo de Marcas'!$M:$M,0)),"") -> 0 | F64: =IFERROR(INDEX('Comparativo de Marcas'!$F:$F,MATCH(62,'Comparativo de Marcas'!$M:$M,0)),"") -> 21000 | G64: =IFERROR(INDEX('Comparativo de Marcas'!$G:$G,MATCH(62,'Comparativo de Marcas'!$M:$M,0)),"") -> 101 | H64: =IFERROR(INDEX('Comparativo de Marcas'!$I:$I,MATCH(62,'Comparativo de Marcas'!$M:$M,0)),"") -> 207.92079
A65: =IFERROR(INDEX('Comparativo de Marcas'!$A:$A,MATCH(63,'Comparativo de Marcas'!$M:$M,0)),"") -> 4711 | B65: =IFERROR(INDEX('Comparativo de Marcas'!$B:$B,MATCH(63,'Comparativo de Marcas'!$M:$M,0)),"") -> Perfumaria/Colonia | C65: =IFERROR(INDEX('Comparativo de Marcas'!$C:$C,MATCH(63,'Comparativo de Marcas'!$M:$M,0)),"") -> 11200 | D65: =IFERROR(INDEX('Comparativo de Marcas'!$D:$D,MATCH(63,'Comparativo de Marcas'!$M:$M,0)),"") -> 9260 | E65: =IFERROR(INDEX('Comparativo de Marcas'!$E:$E,MATCH(63,'Comparativo de Marcas'!$M:$M,0)),"") -> 0 | F65: =IFERROR(INDEX('Comparativo de Marcas'!$F:$F,MATCH(63,'Comparativo de Marcas'!$M:$M,0)),"") -> 20460 | G65: =IFERROR(INDEX('Comparativo de Marcas'!$G:$G,MATCH(63,'Comparativo de Marcas'!$M:$M,0)),"") -> 135 | H65: =IFERROR(INDEX('Comparativo de Marcas'!$I:$I,MATCH(63,'Comparativo de Marcas'!$M:$M,0)),"") -> 151.55556
A66: =IFERROR(INDEX('Comparativo de Marcas'!$A:$A,MATCH(64,'Comparativo de Marcas'!$M:$M,0)),"") -> LANSINOH | B66: =IFERROR(INDEX('Comparativo de Marcas'!$B:$B,MATCH(64,'Comparativo de Marcas'!$M:$M,0)),"") -> Outros/Diversos | C66: =IFERROR(INDEX('Comparativo de Marcas'!$C:$C,MATCH(64,'Comparativo de Marcas'!$M:$M,0)),"") -> 19360 | D66: =IFERROR(INDEX('Comparativo de Marcas'!$D:$D,MATCH(64,'Comparativo de Marcas'!$M:$M,0)),"") -> 0 | E66: =IFERROR(INDEX('Comparativo de Marcas'!$E:$E,MATCH(64,'Comparativo de Marcas'!$M:$M,0)),"") -> 0 | F66: =IFERROR(INDEX('Comparativo de Marcas'!$F:$F,MATCH(64,'Comparativo de Marcas'!$M:$M,0)),"") -> 19360 | G66: =IFERROR(INDEX('Comparativo de Marcas'!$G:$G,MATCH(64,'Comparativo de Marcas'!$M:$M,0)),"") -> 175 | H66: =IFERROR(INDEX('Comparativo de Marcas'!$I:$I,MATCH(64,'Comparativo de Marcas'!$M:$M,0)),"") -> 110.62857
A67: =IFERROR(INDEX('Comparativo de Marcas'!$A:$A,MATCH(65,'Comparativo de Marcas'!$M:$M,0)),"") | B67: =IFERROR(INDEX('Comparativo de Marcas'!$B:$B,MATCH(65,'Comparativo de Marcas'!$M:$M,0)),"") | C67: =IFERROR(INDEX('Comparativo de Marcas'!$C:$C,MATCH(65,'Comparativo de Marcas'!$M:$M,0)),"") | D67: =IFERROR(INDEX('Comparativo de Marcas'!$D:$D,MATCH(65,'Comparativo de Marcas'!$M:$M,0)),"") | E67: =IFERROR(INDEX('Comparativo de Marcas'!$E:$E,MATCH(65,'Comparativo de Marcas'!$M:$M,0)),"") | F67: =IFERROR(INDEX('Comparativo de Marcas'!$F:$F,MATCH(65,'Comparativo de Marcas'!$M:$M,0)),"") | G67: =IFERROR(INDEX('Comparativo de Marcas'!$G:$G,MATCH(65,'Comparativo de Marcas'!$M:$M,0)),"") | H67: =IFERROR(INDEX('Comparativo de Marcas'!$I:$I,MATCH(65,'Comparativo de Marcas'!$M:$M,0)),"")
A68: =IFERROR(INDEX('Comparativo de Marcas'!$A:$A,MATCH(66,'Comparativo de Marcas'!$M:$M,0)),"") | B68: =IFERROR(INDEX('Comparativo de Marcas'!$B:$B,MATCH(66,'Comparativo de Marcas'!$M:$M,0)),"") | C68: =IFERROR(INDEX('Comparativo de Marcas'!$C:$C,MATCH(66,'Comparativo de Marcas'!$M:$M,0)),"") | D68: =IFERROR(INDEX('Comparativo de Marcas'!$D:$D,MATCH(66,'Comparativo de Marcas'!$M:$M,0)),"") | E68: =IFERROR(INDEX('Comparativo de Marcas'!$E:$E,MATCH(66,'Comparativo de Marcas'!$M:$M,0)),"") | F68: =IFERROR(INDEX('Comparativo de Marcas'!$F:$F,MATCH(66,'Comparativo de Marcas'!$M:$M,0)),"") | G68: =IFERROR(INDEX('Comparativo de Marcas'!$G:$G,MATCH(66,'Comparativo de Marcas'!$M:$M,0)),"") | H68: =IFERROR(INDEX('Comparativo de Marcas'!$I:$I,MATCH(66,'Comparativo de Marcas'!$M:$M,0)),"")
A69: =IFERROR(INDEX('Comparativo de Marcas'!$A:$A,MATCH(67,'Comparativo de Marcas'!$M:$M,0)),"") | B69: =IFERROR(INDEX('Comparativo de Marcas'!$B:$B,MATCH(67,'Comparativo de Marcas'!$M:$M,0)),"") | C69: =IFERROR(INDEX('Comparativo de Marcas'!$C:$C,MATCH(67,'Comparativo de Marcas'!$M:$M,0)),"") | D69: =IFERROR(INDEX('Comparativo de Marcas'!$D:$D,MATCH(67,'Comparativo de Marcas'!$M:$M,0)),"") | E69: =IFERROR(INDEX('Comparativo de Marcas'!$E:$E,MATCH(67,'Comparativo de Marcas'!$M:$M,0)),"") | F69: =IFERROR(INDEX('Comparativo de Marcas'!$F:$F,MATCH(67,'Comparativo de Marcas'!$M:$M,0)),"") | G69: =IFERROR(INDEX('Comparativo de Marcas'!$G:$G,MATCH(67,'Comparativo de Marcas'!$M:$M,0)),"") | H69: =IFERROR(INDEX('Comparativo de Marcas'!$I:$I,MATCH(67,'Comparativo de Marcas'!$M:$M,0)),"")
A70: =IFERROR(INDEX('Comparativo de Marcas'!$A:$A,MATCH(68,'Comparativo de Marcas'!$M:$M,0)),"") | B70: =IFERROR(INDEX('Comparativo de Marcas'!$B:$B,MATCH(68,'Comparativo de Marcas'!$M:$M,0)),"") | C70: =IFERROR(INDEX('Comparativo de Marcas'!$C:$C,MATCH(68,'Comparativo de Marcas'!$M:$M,0)),"") | D70: =IFERROR(INDEX('Comparativo de Marcas'!$D:$D,MATCH(68,'Comparativo de Marcas'!$M:$M,0)),"") | E70: =IFERROR(INDEX('Comparativo de Marcas'!$E:$E,MATCH(68,'Comparativo de Marcas'!$M:$M,0)),"") | F70: =IFERROR(INDEX('Comparativo de Marcas'!$F:$F,MATCH(68,'Comparativo de Marcas'!$M:$M,0)),"") | G70: =IFERROR(INDEX('Comparativo de Marcas'!$G:$G,MATCH(68,'Comparativo de Marcas'!$M:$M,0)),"") | H70: =IFERROR(INDEX('Comparativo de Marcas'!$I:$I,MATCH(68,'Comparativo de Marcas'!$M:$M,0)),"")
A71: =IFERROR(INDEX('Comparativo de Marcas'!$A:$A,MATCH(69,'Comparativo de Marcas'!$M:$M,0)),"") | B71: =IFERROR(INDEX('Comparativo de Marcas'!$B:$B,MATCH(69,'Comparativo de Marcas'!$M:$M,0)),"") | C71: =IFERROR(INDEX('Comparativo de Marcas'!$C:$C,MATCH(69,'Comparativo de Marcas'!$M:$M,0)),"") | D71: =IFERROR(INDEX('Comparativo de Marcas'!$D:$D,MATCH(69,'Comparativo de Marcas'!$M:$M,0)),"") | E71: =IFERROR(INDEX('Comparativo de Marcas'!$E:$E,MATCH(69,'Comparativo de Marcas'!$M:$M,0)),"") | F71: =IFERROR(INDEX('Comparativo de Marcas'!$F:$F,MATCH(69,'Comparativo de Marcas'!$M:$M,0)),"") | G71: =IFERROR(INDEX('Comparativo de Marcas'!$G:$G,MATCH(69,'Comparativo de Marcas'!$M:$M,0)),"") | H71: =IFERROR(INDEX('Comparativo de Marcas'!$I:$I,MATCH(69,'Comparativo de Marcas'!$M:$M,0)),"")
A72: =IFERROR(INDEX('Comparativo de Marcas'!$A:$A,MATCH(70,'Comparativo de Marcas'!$M:$M,0)),"") | B72: =IFERROR(INDEX('Comparativo de Marcas'!$B:$B,MATCH(70,'Comparativo de Marcas'!$M:$M,0)),"") | C72: =IFERROR(INDEX('Comparativo de Marcas'!$C:$C,MATCH(70,'Comparativo de Marcas'!$M:$M,0)),"") | D72: =IFERROR(INDEX('Comparativo de Marcas'!$D:$D,MATCH(70,'Comparativo de Marcas'!$M:$M,0)),"") | E72: =IFERROR(INDEX('Comparativo de Marcas'!$E:$E,MATCH(70,'Comparativo de Marcas'!$M:$M,0)),"") | F72: =IFERROR(INDEX('Comparativo de Marcas'!$F:$F,MATCH(70,'Comparativo de Marcas'!$M:$M,0)),"") | G72: =IFERROR(INDEX('Comparativo de Marcas'!$G:$G,MATCH(70,'Comparativo de Marcas'!$M:$M,0)),"") | H72: =IFERROR(INDEX('Comparativo de Marcas'!$I:$I,MATCH(70,'Comparativo de Marcas'!$M:$M,0)),"")
A73: =IFERROR(INDEX('Comparativo de Marcas'!$A:$A,MATCH(71,'Comparativo de Marcas'!$M:$M,0)),"") | B73: =IFERROR(INDEX('Comparativo de Marcas'!$B:$B,MATCH(71,'Comparativo de Marcas'!$M:$M,0)),"") | C73: =IFERROR(INDEX('Comparativo de Marcas'!$C:$C,MATCH(71,'Comparativo de Marcas'!$M:$M,0)),"") | D73: =IFERROR(INDEX('Comparativo de Marcas'!$D:$D,MATCH(71,'Comparativo de Marcas'!$M:$M,0)),"") | E73: =IFERROR(INDEX('Comparativo de Marcas'!$E:$E,MATCH(71,'Comparativo de Marcas'!$M:$M,0)),"") | F73: =IFERROR(INDEX('Comparativo de Marcas'!$F:$F,MATCH(71,'Comparativo de Marcas'!$M:$M,0)),"") | G73: =IFERROR(INDEX('Comparativo de Marcas'!$G:$G,MATCH(71,'Comparativo de Marcas'!$M:$M,0)),"") | H73: =IFERROR(INDEX('Comparativo de Marcas'!$I:$I,MATCH(71,'Comparativo de Marcas'!$M:$M,0)),"")
A74: =IFERROR(INDEX('Comparativo de Marcas'!$A:$A,MATCH(72,'Comparativo de Marcas'!$M:$M,0)),"") | B74: =IFERROR(INDEX('Comparativo de Marcas'!$B:$B,MATCH(72,'Comparativo de Marcas'!$M:$M,0)),"") | C74: =IFERROR(INDEX('Comparativo de Marcas'!$C:$C,MATCH(72,'Comparativo de Marcas'!$M:$M,0)),"") | D74: =IFERROR(INDEX('Comparativo de Marcas'!$D:$D,MATCH(72,'Comparativo de Marcas'!$M:$M,0)),"") | E74: =IFERROR(INDEX('Comparativo de Marcas'!$E:$E,MATCH(72,'Comparativo de Marcas'!$M:$M,0)),"") | F74: =IFERROR(INDEX('Comparativo de Marcas'!$F:$F,MATCH(72,'Comparativo de Marcas'!$M:$M,0)),"") | G74: =IFERROR(INDEX('Comparativo de Marcas'!$G:$G,MATCH(72,'Comparativo de Marcas'!$M:$M,0)),"") | H74: =IFERROR(INDEX('Comparativo de Marcas'!$I:$I,MATCH(72,'Comparativo de Marcas'!$M:$M,0)),"")
A75: =IFERROR(INDEX('Comparativo de Marcas'!$A:$A,MATCH(73,'Comparativo de Marcas'!$M:$M,0)),"") | B75: =IFERROR(INDEX('Comparativo de Marcas'!$B:$B,MATCH(73,'Comparativo de Marcas'!$M:$M,0)),"") | C75: =IFERROR(INDEX('Comparativo de Marcas'!$C:$C,MATCH(73,'Comparativo de Marcas'!$M:$M,0)),"") | D75: =IFERROR(INDEX('Comparativo de Marcas'!$D:$D,MATCH(73,'Comparativo de Marcas'!$M:$M,0)),"") | E75: =IFERROR(INDEX('Comparativo de Marcas'!$E:$E,MATCH(73,'Comparativo de Marcas'!$M:$M,0)),"") | F75: =IFERROR(INDEX('Comparativo de Marcas'!$F:$F,MATCH(73,'Comparativo de Marcas'!$M:$M,0)),"") | G75: =IFERROR(INDEX('Comparativo de Marcas'!$G:$G,MATCH(73,'Comparativo de Marcas'!$M:$M,0)),"") | H75: =IFERROR(INDEX('Comparativo de Marcas'!$I:$I,MATCH(73,'Comparativo de Marcas'!$M:$M,0)),"")
A76: =IFERROR(INDEX('Comparativo de Marcas'!$A:$A,MATCH(74,'Comparativo de Marcas'!$M:$M,0)),"") | B76: =IFERROR(INDEX('Comparativo de Marcas'!$B:$B,MATCH(74,'Comparativo de Marcas'!$M:$M,0)),"") | C76: =IFERROR(INDEX('Comparativo de Marcas'!$C:$C,MATCH(74,'Comparativo de Marcas'!$M:$M,0)),"") | D76: =IFERROR(INDEX('Comparativo de Marcas'!$D:$D,MATCH(74,'Comparativo de Marcas'!$M:$M,0)),"") | E76: =IFERROR(INDEX('Comparativo de Marcas'!$E:$E,MATCH(74,'Comparativo de Marcas'!$M:$M,0)),"") | F76: =IFERROR(INDEX('Comparativo de Marcas'!$F:$F,MATCH(74,'Comparativo de Marcas'!$M:$M,0)),"") | G76: =IFERROR(INDEX('Comparativo de Marcas'!$G:$G,MATCH(74,'Comparativo de Marcas'!$M:$M,0)),"") | H76: =IFERROR(INDEX('Comparativo de Marcas'!$I:$I,MATCH(74,'Comparativo de Marcas'!$M:$M,0)),"")
A77: =IFERROR(INDEX('Comparativo de Marcas'!$A:$A,MATCH(75,'Comparativo de Marcas'!$M:$M,0)),"") | B77: =IFERROR(INDEX('Comparativo de Marcas'!$B:$B,MATCH(75,'Comparativo de Marcas'!$M:$M,0)),"") | C77: =IFERROR(INDEX('Comparativo de Marcas'!$C:$C,MATCH(75,'Comparativo de Marcas'!$M:$M,0)),"") | D77: =IFERROR(INDEX('Comparativo de Marcas'!$D:$D,MATCH(75,'Comparativo de Marcas'!$M:$M,0)),"") | E77: =IFERROR(INDEX('Comparativo de Marcas'!$E:$E,MATCH(75,'Comparativo de Marcas'!$M:$M,0)),"") | F77: =IFERROR(INDEX('Comparativo de Marcas'!$F:$F,MATCH(75,'Comparativo de Marcas'!$M:$M,0)),"") | G77: =IFERROR(INDEX('Comparativo de Marcas'!$G:$G,MATCH(75,'Comparativo de Marcas'!$M:$M,0)),"") | H77: =IFERROR(INDEX('Comparativo de Marcas'!$I:$I,MATCH(75,'Comparativo de Marcas'!$M:$M,0)),"")
A78: =IFERROR(INDEX('Comparativo de Marcas'!$A:$A,MATCH(76,'Comparativo de Marcas'!$M:$M,0)),"") | B78: =IFERROR(INDEX('Comparativo de Marcas'!$B:$B,MATCH(76,'Comparativo de Marcas'!$M:$M,0)),"") | C78: =IFERROR(INDEX('Comparativo de Marcas'!$C:$C,MATCH(76,'Comparativo de Marcas'!$M:$M,0)),"") | D78: =IFERROR(INDEX('Comparativo de Marcas'!$D:$D,MATCH(76,'Comparativo de Marcas'!$M:$M,0)),"") | E78: =IFERROR(INDEX('Comparativo de Marcas'!$E:$E,MATCH(76,'Comparativo de Marcas'!$M:$M,0)),"") | F78: =IFERROR(INDEX('Comparativo de Marcas'!$F:$F,MATCH(76,'Comparativo de Marcas'!$M:$M,0)),"") | G78: =IFERROR(INDEX('Comparativo de Marcas'!$G:$G,MATCH(76,'Comparativo de Marcas'!$M:$M,0)),"") | H78: =IFERROR(INDEX('Comparativo de Marcas'!$I:$I,MATCH(76,'Comparativo de Marcas'!$M:$M,0)),"")
A79: =IFERROR(INDEX('Comparativo de Marcas'!$A:$A,MATCH(77,'Comparativo de Marcas'!$M:$M,0)),"") | B79: =IFERROR(INDEX('Comparativo de Marcas'!$B:$B,MATCH(77,'Comparativo de Marcas'!$M:$M,0)),"") | C79: =IFERROR(INDEX('Comparativo de Marcas'!$C:$C,MATCH(77,'Comparativo de Marcas'!$M:$M,0)),"") | D79: =IFERROR(INDEX('Comparativo de Marcas'!$D:$D,MATCH(77,'Comparativo de Marcas'!$M:$M,0)),"") | E79: =IFERROR(INDEX('Comparativo de Marcas'!$E:$E,MATCH(77,'Comparativo de Marcas'!$M:$M,0)),"") | F79: =IFERROR(INDEX('Comparativo de Marcas'!$F:$F,MATCH(77,'Comparativo de Marcas'!$M:$M,0)),"") | G79: =IFERROR(INDEX('Comparativo de Marcas'!$G:$G,MATCH(77,'Comparativo de Marcas'!$M:$M,0)),"") | H79: =IFERROR(INDEX('Comparativo de Marcas'!$I:$I,MATCH(77,'Comparativo de Marcas'!$M:$M,0)),"")
A80: =IFERROR(INDEX('Comparativo de Marcas'!$A:$A,MATCH(78,'Comparativo de Marcas'!$M:$M,0)),"") | B80: =IFERROR(INDEX('Comparativo de Marcas'!$B:$B,MATCH(78,'Comparativo de Marcas'!$M:$M,0)),"") | C80: =IFERROR(INDEX('Comparativo de Marcas'!$C:$C,MATCH(78,'Comparativo de Marcas'!$M:$M,0)),"") | D80: =IFERROR(INDEX('Comparativo de Marcas'!$D:$D,MATCH(78,'Comparativo de Marcas'!$M:$M,0)),"") | E80: =IFERROR(INDEX('Comparativo de Marcas'!$E:$E,MATCH(78,'Comparativo de Marcas'!$M:$M,0)),"") | F80: =IFERROR(INDEX('Comparativo de Marcas'!$F:$F,MATCH(78,'Comparativo de Marcas'!$M:$M,0)),"") | G80: =IFERROR(INDEX('Comparativo de Marcas'!$G:$G,MATCH(78,'Comparativo de Marcas'!$M:$M,0)),"") | H80: =IFERROR(INDEX('Comparativo de Marcas'!$I:$I,MATCH(78,'Comparativo de Marcas'!$M:$M,0)),"")
A81: =IFERROR(INDEX('Comparativo de Marcas'!$A:$A,MATCH(79,'Comparativo de Marcas'!$M:$M,0)),"") | B81: =IFERROR(INDEX('Comparativo de Marcas'!$B:$B,MATCH(79,'Comparativo de Marcas'!$M:$M,0)),"") | C81: =IFERROR(INDEX('Comparativo de Marcas'!$C:$C,MATCH(79,'Comparativo de Marcas'!$M:$M,0)),"") | D81: =IFERROR(INDEX('Comparativo de Marcas'!$D:$D,MATCH(79,'Comparativo de Marcas'!$M:$M,0)),"") | E81: =IFERROR(INDEX('Comparativo de Marcas'!$E:$E,MATCH(79,'Comparativo de Marcas'!$M:$M,0)),"") | F81: =IFERROR(INDEX('Comparativo de Marcas'!$F:$F,MATCH(79,'Comparativo de Marcas'!$M:$M,0)),"") | G81: =IFERROR(INDEX('Comparativo de Marcas'!$G:$G,MATCH(79,'Comparativo de Marcas'!$M:$M,0)),"") | H81: =IFERROR(INDEX('Comparativo de Marcas'!$I:$I,MATCH(79,'Comparativo de Marcas'!$M:$M,0)),"")
A84: Produtos (anúncios) das marcas oportunidade — 2908 itens, ordenados por receita · lista fixa gerada nesta versão do relatório (não recalcula sozinha se os Dados Brutos forem editados)
A85: Marca | B85: Categoria | C85: Concorrente | D85: Título do Anúncio | E85: Preço Médio (R$) | F85: Unidades Vendidas | G85: Receita (R$)
A86: CAROLINA HERRERA | B86: Perfumaria/Colonia | C86: AUMA | D86: Perfume Carolina Herrera Good Girl Eau D | E86: 698.99559 | F86: 700 | G86: 489000
A87: JEAN PAUL GAULTIER | B87: Perfumaria/Colonia | C87: AUMA | D87: Perfume Jean Paul Gaultier Le Male Elixi | E87: 660.30198 | F87: 430 | G87: 284000
A88: CAROLINA HERRERA | B88: Perfumaria/Colonia | C88: BAGATELLE | D88: Perfume Carolina Herrera 212 Vip Black E | E88: 585.61688 | F88: 480 | G88: 281000
A89: CAROLINA HERRERA | B89: Perfumaria/Colonia | C89: BAGATELLE | D89: Perfume 212 Vip Rosé Carolina Herrera Ea | E89: 616.12373 | F89: 430 | G89: 267000
A90: JEAN PAUL GAULTIER | B90: Perfumaria/Colonia | C90: AUMA | D90: Perfume Jean Paul Gaultier Le Male Le Pa | E90: 696.45785 | F90: 380 | G90: 265000
A91: CAROLINA HERRERA | B91: Perfumaria/Colonia | C91: AUMA | D91: Perfume Carolina Herrera 212 Vip Black E | E91: 637.72305 | F91: 320 | G91: 201000
A92: RABANNE | B92: Perfumaria/Colonia | C92: AUMA | D92: Perfume Rabanne Invictus Eau De Toilette | E92: 648.20935 | F92: 290 | G92: 191000
A93: RABANNE | B93: Perfumaria/Colonia | C93: BAGATELLE | D93: Perfume Rabanne 1 Million Eau De Toilett | E93: 598.4962 | F93: 300 | G93: 183000
A94: RABANNE | B94: Perfumaria/Colonia | C94: AUMA | D94: Perfume Rabanne 1 Million Eau De Toilett | E94: 638.6427 | F94: 240 | G94: 156000
A95: CAROLINA HERRERA | B95: Perfumaria/Colonia | C95: AUMA | D95: Perfume Carolina Herrera 212 Men Heroes | E95: 582.39535 | F95: 260 | G95: 150000
A96: SHISEIDO | B96: Perfumaria/Colonia | C96: AUMA | D96: Shiseido Bb For Sports Fps 50 Medium Bas | E96: 302.81438 | F96: 480 | G96: 145000
A97: CAROLINA HERRERA | B97: Perfumaria/Colonia | C97: AUMA | D97: Perfume 212 Vip Rosé Carolina Herrera Ea | E97: 641.04302 | F97: 190 | G97: 121000
... A2993: WELLA | B2993: Perfumaria/Colonia | C2993: AUMA | D2993: Wella Welloxon Perfect Oxidante 6% 20v 6 | E2993: 28.26 | F2993: 1 | G2993: 30

Sheet Comparativo de Marcas
A1: Marca | B1: Categoria (predominante) | C1: Receita SIENO (R$) | D1: Receita BAGATELLE (R$) | E1: Receita AUMA (R$) | F1: Receita Total (R$) | G1: Unidades Total | H1: Nº Anúncios Total | I1: Ticket Médio (R$) | J1: Nº Concorrentes que vendem | K1: Vendida pelos 3? | L1: Oportunidade (ticket>=R$100 e >=100 unid.) | M1: Rank Oportunidade (auxiliar)
A2: CAROLINA HERRERA | B2: Perfumaria/Colonia | C2: =SUMIFS('Dados Brutos'!$C:$C,'Dados Brutos'!$B:$B,A2,'Dados Brutos'!$T:$T,"SIENO") -> 0 | D2: =SUMIFS('Dados Brutos'!$C:$C,'Dados Brutos'!$B:$B,A2,'Dados Brutos'!$T:$T,"BAGATELLE") -> 1332020 | E2: =SUMIFS('Dados Brutos'!$C:$C,'Dados Brutos'!$B:$B,A2,'Dados Brutos'!$T:$T,"AUMA") -> 2191200 | F2: =SUM(C2:E2) -> 3523220 | G2: =SUMIF('Dados Brutos'!$B:$B,A2,'Dados Brutos'!$D:$D) -> 5687 | H2: =COUNTIF('Dados Brutos'!$B:$B,A2) -> 354 | I2: =IFERROR(F2/G2,0) -> 619.52172 | J2: =(C2>0)+(D2>0)+(E2>0) -> 2 | K2: =IF(J2=3,"Sim","Não") -> Não | L2: =IF(AND(I2>=100,G2>=100),"Sim","Não") -> Sim | M2: =IF(L2="Sim",SUMPRODUCT(($L$2:L2="Sim")*1),"") -> 1
A3: RABANNE | B3: Perfumaria/Colonia | C3: =SUMIFS('Dados Brutos'!$C:$C,'Dados Brutos'!$B:$B,A3,'Dados Brutos'!$T:$T,"SIENO") -> 0 | D3: =SUMIFS('Dados Brutos'!$C:$C,'Dados Brutos'!$B:$B,A3,'Dados Brutos'!$T:$T,"BAGATELLE") -> 921250 | E3: =SUMIFS('Dados Brutos'!$C:$C,'Dados Brutos'!$B:$B,A3,'Dados Brutos'!$T:$T,"AUMA") -> 1517680 | F3: =SUM(C3:E3) -> 2438930 | G3: =SUMIF('Dados Brutos'!$B:$B,A3,'Dados Brutos'!$D:$D) -> 3685 | H3: =COUNTIF('Dados Brutos'!$B:$B,A3) -> 320 | I3: =IFERROR(F3/G3,0) -> 661.85346 | J3: =(C3>0)+(D3>0)+(E3>0) -> 2 | K3: =IF(J3=3,"Sim","Não") -> Não | L3: =IF(AND(I3>=100,G3>=100),"Sim","Não") -> Sim | M3: =IF(L3="Sim",SUMPRODUCT(($L$2:L3="Sim")*1),"") -> 2
A4: JEAN PAUL GAULTIER | B4: Perfumaria/Colonia | C4: =SUMIFS('Dados Brutos'!$C:$C,'Dados Brutos'!$B:$B,A4,'Dados Brutos'!$T:$T,"SIENO") -> 0 | D4: =SUMIFS('Dados Brutos'!$C:$C,'Dados Brutos'!$B:$B,A4,'Dados Brutos'!$T:$T,"BAGATELLE") -> 387830 | E4: =SUMIFS('Dados Brutos'!$C:$C,'Dados Brutos'!$B:$B,A4,'Dados Brutos'!$T:$T,"AUMA") -> 1397570 | F4: =SUM(C4:E4) -> 1785400 | G4: =SUMIF('Dados Brutos'!$B:$B,A4,'Dados Brutos'!$D:$D) -> 2595 | H4: =COUNTIF('Dados Brutos'!$B:$B,A4) -> 255 | I4: =IFERROR(F4/G4,0) -> 688.01541 | J4: =(C4>0)+(D4>0)+(E4>0) -> 2 | K4: =IF(J4=3,"Sim","Não") -> Não | L4: =IF(AND(I4>=100,G4>=100),"Sim","Não") -> Sim | M4: =IF(L4="Sim",SUMPRODUCT(($L$2:L4="Sim")*1),"") -> 3
A5: G-TECH | B5: Saude/Bem-estar | C5: =SUMIFS('Dados Brutos'!$C:$C,'Dados Brutos'!$B:$B,A5,'Dados Brutos'!$T:$T,"SIENO") -> 1429210 | D5: =SUMIFS('Dados Brutos'!$C:$C,'Dados Brutos'!$B:$B,A5,'Dados Brutos'!$T:$T,"BAGATELLE") -> 0 | E5: =SUMIFS('Dados Brutos'!$C:$C,'Dados Brutos'!$B:$B,A5,'Dados Brutos'!$T:$T,"AUMA") -> 0 | F5: =SUM(C5:E5) -> 1429210 | G5: =SUMIF('Dados Brutos'!$B:$B,A5,'Dados Brutos'!$D:$D) -> 16001 | H5: =COUNTIF('Dados Brutos'!$B:$B,A5) -> 25 | I5: =IFERROR(F5/G5,0) -> 89.320042 | J5: =(C5>0)+(D5>0)+(E5>0) -> 1 | K5: =IF(J5=3,"Sim","Não") -> Não | L5: =IF(AND(I5>=100,G5>=100),"Sim","Não") -> Não | M5: =IF(L5="Sim",SUMPRODUCT(($L$2:L5="Sim")*1),"")
A6: YVES SAINT LAURENT | B6: Perfumaria/Colonia | C6: =SUMIFS('Dados Brutos'!$C:$C,'Dados Brutos'!$B:$B,A6,'Dados Brutos'!$T:$T,"SIENO") -> 253760 | D6: =SUMIFS('Dados Brutos'!$C:$C,'Dados Brutos'!$B:$B,A6,'Dados Brutos'!$T:$T,"BAGATELLE") -> 17620 | E6: =SUMIFS('Dados Brutos'!$C:$C,'Dados Brutos'!$B:$B,A6,'Dados Brutos'!$T:$T,"AUMA") -> 521750 | F6: =SUM(C6:E6) -> 793130 | G6: =SUMIF('Dados Brutos'!$B:$B,A6,'Dados Brutos'!$D:$D) -> 1123 | H6: =COUNTIF('Dados Brutos'!$B:$B,A6) -> 75 | I6: =IFERROR(F6/G6,0) -> 706.26002 | J6: =(C6>0)+(D6>0)+(E6>0) -> 3 | K6: =IF(J6=3,"Sim","Não") -> Sim | L6: =IF(AND(I6>=100,G6>=100),"Sim","Não") -> Sim | M6: =IF(L6="Sim",SUMPRODUCT(($L$2:L6="Sim")*1),"") -> 4
A7: DOLCE & GABBANA | B7: Perfumaria/Colonia | C7: =SUMIFS('Dados Brutos'!$C:$C,'Dados Brutos'!$B:$B,A7,'Dados Brutos'!$T:$T,"SIENO") -> 178890 | D7: =SUMIFS('Dados Brutos'!$C:$C,'Dados Brutos'!$B:$B,A7,'Dados Brutos'!$T:$T,"BAGATELLE") -> 99900 | E7: =SUMIFS('Dados Brutos'!$C:$C,'Dados Brutos'!$B:$B,A7,'Dados Brutos'!$T:$T,"AUMA") -> 170460 | F7: =SUM(C7:E7) -> 449250 | G7: =SUMIF('Dados Brutos'!$B:$B,A7,'Dados Brutos'!$D:$D) -> 670 | H7: =COUNTIF('Dados Brutos'!$B:$B,A7) -> 112 | I7: =IFERROR(F7/G7,0) -> 670.52239 | J7: =(C7>0)+(D7>0)+(E7>0) -> 3 | K7: =IF(J7=3,"Sim","Não") -> Sim | L7: =IF(AND(I7>=100,G7>=100),"Sim","Não") -> Sim | M7: =IF(L7="Sim",SUMPRODUCT(($L$2:L7="Sim")*1),"") -> 5
A8: SHISEIDO | B8: Perfumaria/Colonia | C8: =SUMIFS('Dados Brutos'!$C:$C,'Dados Brutos'!$B:$B,A8,'Dados Brutos'!$T:$T,"SIENO") -> 0 | D8: =SUMIFS('Dados Brutos'!$C:$C,'Dados Brutos'!$B:$B,A8,'Dados Brutos'!$T:$T,"BAGATELLE") -> 0 | E8: =SUMIFS('Dados Brutos'!$C:$C,'Dados Brutos'!$B:$B,A8,'Dados Brutos'!$T:$T,"AUMA") -> 447230 | F8: =SUM(C8:E8) -> 447230 | G8: =SUMIF('Dados Brutos'!$B:$B,A8,'Dados Brutos'!$D:$D) -> 1310 | H8: =COUNTIF('Dados Brutos'!$B:$B,A8) -> 108 | I8: =IFERROR(F8/G8,0) -> 341.39695 | J8: =(C8>0)+(D8>0)+(E8>0) -> 1 | K8: =IF(J8=3,"Sim","Não") -> Não | L8: =IF(AND(I8>=100,G8>=100),"Sim","Não") -> Sim | M8: =IF(L8="Sim",SUMPRODUCT(($L$2:L8="Sim")*1),"") -> 6
A9: LANCÔME | B9: Perfumaria/Colonia | C9: =SUMIFS('Dados Brutos'!$C:$C,'Dados Brutos'!$B:$B,A9,'Dados Brutos'!$T:$T,"SIENO") -> 0 | D9: =SUMIFS('Dados Brutos'!$C:$C,'Dados Brutos'!$B:$B,A9,'Dados Brutos'!$T:$T,"BAGATELLE") -> 0 | E9: =SUMIFS('Dados Brutos'!$C:$C,'Dados Brutos'!$B:$B,A9,'Dados Brutos'!$T:$T,"AUMA") -> 443410 | F9: =SUM(C9:E9) -> 443410 | G9: =SUMIF('Dados Brutos'!$B:$B,A9,'Dados Brutos'!$D:$D) -> 774 | H9: =COUNTIF('Dados Brutos'!$B:$B,A9) -> 124 | I9: =IFERROR(F9/G9,0) -> 572.88114 | J9: =(C9>0)+(D9>0)+(E9>0) -> 1 | K9: =IF(J9=3,"Sim","Não") -> Não | L9: =IF(AND(I9>=100,G9>=100),"Sim","Não") -> Sim | M9: =IF(L9="Sim",SUMPRODUCT(($L$2:L9="Sim")*1),"") -> 7
A10: PRADA | B10: Perfumaria/Colonia | C10: =SUMIFS('Dados Brutos'!$C:$C,'Dados Brutos'!$B:$B,A10,'Dados Brutos'!$T:$T,"SIENO") -> 33000 | D10: =SUMIFS('Dados Brutos'!$C:$C,'Dados Brutos'!$B:$B,A10,'Dados Brutos'!$T:$T,"BAGATELLE") -> 940 | E10: =SUMIFS('Dados Brutos'!$C:$C,'Dados Brutos'!$B:$B,A10,'Dados Brutos'!$T:$T,"AUMA") -> 372630 | F10: =SUM(C10:E10) -> 406570 | G10: =SUMIF('Dados Brutos'!$B:$B,A10,'Dados Brutos'!$D:$D) -> 519 | H10: =COUNTIF('Dados Brutos'!$B:$B,A10) -> 44 | I10: =IFERROR(F10/G10,0) -> 783.37187 | J10: =(C10>0)+(D10>0)+(E10>0) -> 3 | K10: =IF(J10=3,"Sim","Não") -> Sim | L10: =IF(AND(I10>=100,G10>=100),"Sim","Não") -> Sim | M10: =IF(L10="Sim",SUMPRODUCT(($L$2:L10="Sim")*1),"") -> 8
A11: ARMANI BEAUTY | B11: Perfumaria/Colonia | C11: =SUMIFS('Dados Brutos'!$C:$C,'Dados Brutos'!$B:$B,A11,'Dados Brutos'!$T:$T,"SIENO") -> 0 | D11: =SUMIFS('Dados Brutos'!$C:$C,'Dados Brutos'!$B:$B,A11,'Dados Brutos'!$T:$T,"BAGATELLE") -> 0 | E11: =SUMIFS('Dados Brutos'!$C:$C,'Dados Brutos'!$B:$B,A11,'Dados Brutos'!$T:$T,"AUMA") -> 402220 | F11: =SUM(C11:E11) -> 402220 | G11: =SUMIF('Dados Brutos'!$B:$B,A11,'Dados Brutos'!$D:$D) -> 540 | H11: =COUNTIF('Dados Brutos'!$B:$B,A11) -> 83 | I11: =IFERROR(F11/G11,0) -> 744.85185 | J11: =(C11>0)+(D11>0)+(E11>0) -> 1 | K11: =IF(J11=3,"Sim","Não") -> Não | L11: =IF(AND(I11>=100,G11>=100),"Sim","Não") -> Sim | M11: =IF(L11="Sim",SUMPRODUCT(($L$2:L11="Sim")*1),"") -> 9
A12: VITAFOR | B12: Suplementos/Nutricao | C12: =SUMIFS('Dados Brutos'!$C:$C,'Dados Brutos'!$B:$B,A12,'Dados Brutos'!$T:$T,"SIENO") -> 358960 | D12: =SUMIFS('Dados Brutos'!$C:$C,'Dados Brutos'!$B:$B,A12,'Dados Brutos'!$T:$T,"BAGATELLE") -> 0 | E12: =SUMIFS('Dados Brutos'!$C:$C,'Dados Brutos'!$B:$B,A12,'Dados Brutos'!$T:$T,"AUMA") -> 0 | F12: =SUM(C12:E12) -> 358960 | G12: =SUMIF('Dados Brutos'!$B:$B,A12,'Dados Brutos'!$D:$D) -> 4666 | H12: =COUNTIF('Dados Brutos'!$B:$B,A12) -> 40 | I12: =IFERROR(F12/G12,0) -> 76.93099 | J12: =(C12>0)+(D12>0)+(E12>0) -> 1 | K12: =IF(J12=3,"Sim","Não") -> Não | L12: =IF(AND(I12>=100,G12>=100),"Sim","Não") -> Não | M12: =IF(L12="Sim",SUMPRODUCT(($L$2:L12="Sim")*1),"")
A13: MARURI | B13: Pesca/Nautica | C13: =SUMIFS('Dados Brutos'!$C:$C,'Dados Brutos'!$B:$B,A13,'Dados Brutos'!$T:$T,"SIENO") -> 344600 | D13: =SUMIFS('Dados Brutos'!$C:$C,'Dados Brutos'!$B:$B,A13,'Dados Brutos'!$T:$T,"BAGATELLE") -> 0 | E13: =SUMIFS('Dados Brutos'!$C:$C,'Dados Brutos'!$B:$B,A13,'Dados Brutos'!$T:$T,"AUMA") -> 0 | F13: =SUM(C13:E13) -> 344600 | G13: =SUMIF('Dados Brutos'!$B:$B,A13,'Dados Brutos'!$D:$D) -> 1042 | H13: =COUNTIF('Dados Brutos'!$B:$B,A13) -> 16 | I13: =IFERROR(F13/G13,0) -> 330.71017 | J13: =(C13>0)+(D13>0)+(E13>0) -> 1 | K13: =IF(J13=3,"Sim","Não") -> Não | L13: =IF(AND(I13>=100,G13>=100),"Sim","Não") -> Sim | M13: =IF(L13="Sim",SUMPRODUCT(($L$2:L13="Sim")*1),"") -> 10
... A276: A BOTICA BRASIL | B276: Cosmeticos/Skincare | C276: =SUMIFS('Dados Brutos'!$C:$C,'Dados Brutos'!$B:$B,A276,'Dados Brutos'!$T:$T,"SIENO") -> 40 | D276: =SUMIFS('Dados Brutos'!$C:$C,'Dados Brutos'!$B:$B,A276,'Dados Brutos'!$T:$T,"BAGATELLE") -> 0 | E276: =SUMIFS('Dados Brutos'!$C:$C,'Dados Brutos'!$B:$B,A276,'Dados Brutos'!$T:$T,"AUMA") -> 0 | F276: =SUM(C276:E276) -> 40 | G276: =SUMIF('Dados Brutos'!$B:$B,A276,'Dados Brutos'!$D:$D) -> 1 | H276: =COUNTIF('Dados Brutos'!$B:$B,A276) -> 1 | I276: =IFERROR(F276/G276,0) -> 40 | J276: =(C276>0)+(D276>0)+(E276>0) -> 1 | K276: =IF(J276=3,"Sim","Não") -> Não | L276: =IF(AND(I276>=100,G276>=100),"Sim","Não") -> Não | M276: =IF(L276="Sim",SUMPRODUCT(($L$2:L276="Sim")*1),"")
A277: TOTAL | C277: =SUM(C2:C276) -> 8228730 | D277: =SUM(D2:D276) -> 3808650 | E277: =SUM(E2:E276) -> 9294080 | F277: =SUM(F2:F276) -> 21331460 | G277: =SUM(G2:G276) -> 104250 | H277: =SUM(H2:H276) -> 3988 | I277: =IFERROR(F277/G277,0) -> 204.61832

Sheet Por Categoria
A1: Categoria | B1: Nº de Marcas | C1: Receita (R$) | D1: Unidades Vendidas | E1: Nº Anúncios (SKUs) | F1: Ticket Médio (R$) | G1: % da Receita Total
A2: Perfumaria/Colonia | B2: =SUMIFS('Dados Brutos'!$V:$V,'Dados Brutos'!$U:$U,A2) -> 125 | C2: =SUMIF('Dados Brutos'!$U:$U,A2,'Dados Brutos'!$C:$C) -> 15170130 | D2: =SUMIF('Dados Brutos'!$U:$U,A2,'Dados Brutos'!$D:$D) -> 43229 | E2: =COUNTIF('Dados Brutos'!$U:$U,A2) -> 3058 | F2: =IFERROR(C2/D2,0) -> 350.92484 | G2: =IFERROR(C2/$C$15,0) -> 0.71116229
A3: Saude/Bem-estar | B3: =SUMIFS('Dados Brutos'!$V:$V,'Dados Brutos'!$U:$U,A3) -> 13 | C3: =SUMIF('Dados Brutos'!$U:$U,A3,'Dados Brutos'!$C:$C) -> 1946030 | D3: =SUMIF('Dados Brutos'!$U:$U,A3,'Dados Brutos'!$D:$D) -> 23460 | E3: =COUNTIF('Dados Brutos'!$U:$U,A3) -> 45 | F3: =IFERROR(C3/D3,0) -> 82.95098 | G3: =IFERROR(C3/$C$15,0) -> 0.091228167
A4: Outros/Diversos | B4: =SUMIFS('Dados Brutos'!$V:$V,'Dados Brutos'!$U:$U,A4) -> 75 | C4: =SUMIF('Dados Brutos'!$U:$U,A4,'Dados Brutos'!$C:$C) -> 936200 | D4: =SUMIF('Dados Brutos'!$U:$U,A4,'Dados Brutos'!$D:$D) -> 10368 | E4: =COUNTIF('Dados Brutos'!$U:$U,A4) -> 464 | F4: =IFERROR(C4/D4,0) -> 90.297068 | G4: =IFERROR(C4/$C$15,0) -> 0.043888229
A5: Pesca/Nautica | B5: =SUMIFS('Dados Brutos'!$V:$V,'Dados Brutos'!$U:$U,A5) -> 5 | C5: =SUMIF('Dados Brutos'!$U:$U,A5,'Dados Brutos'!$C:$C) -> 846880 | D5: =SUMIF('Dados Brutos'!$U:$U,A5,'Dados Brutos'!$D:$D) -> 2987 | E5: =COUNTIF('Dados Brutos'!$U:$U,A5) -> 44 | F5: =IFERROR(C5/D5,0) -> 283.52193 | G5: =IFERROR(C5/$C$15,0) -> 0.039700986
A6: Suplementos/Nutricao | B6: =SUMIFS('Dados Brutos'!$V:$V,'Dados Brutos'!$U:$U,A6) -> 10 | C6: =SUMIF('Dados Brutos'!$U:$U,A6,'Dados Brutos'!$C:$C) -> 723280 | D6: =SUMIF('Dados Brutos'!$U:$U,A6,'Dados Brutos'!$D:$D) -> 10505 | E6: =COUNTIF('Dados Brutos'!$U:$U,A6) -> 71 | F6: =IFERROR(C6/D6,0) -> 68.851023 | G6: =IFERROR(C6/$C$15,0) -> 0.033906727
A7: Cosmeticos/Skincare | B7: =SUMIFS('Dados Brutos'!$V:$V,'Dados Brutos'!$U:$U,A7) -> 21 | C7: =SUMIF('Dados Brutos'!$U:$U,A7,'Dados Brutos'!$C:$C) -> 501660 | D7: =SUMIF('Dados Brutos'!$U:$U,A7,'Dados Brutos'!$D:$D) -> 4723 | E7: =COUNTIF('Dados Brutos'!$U:$U,A7) -> 181 | F7: =IFERROR(C7/D7,0) -> 106.21639 | G7: =IFERROR(C7/$C$15,0) -> 0.023517378
A8: Ferramentas | B8: =SUMIFS('Dados Brutos'!$V:$V,'Dados Brutos'!$U:$U,A8) -> 8 | C8: =SUMIF('Dados Brutos'!$U:$U,A8,'Dados Brutos'!$C:$C) -> 396480 | D8: =SUMIF('Dados Brutos'!$U:$U,A8,'Dados Brutos'!$D:$D) -> 1926 | E8: =COUNTIF('Dados Brutos'!$U:$U,A8) -> 31 | F8: =IFERROR(C8/D8,0) -> 205.8567 | G8: =IFERROR(C8/$C$15,0) -> 0.018586632
A9: Casa/Eletrodomesticos | B9: =SUMIFS('Dados Brutos'!$V:$V,'Dados Brutos'!$U:$U,A9) -> 6 | C9: =SUMIF('Dados Brutos'!$U:$U,A9,'Dados Brutos'!$C:$C) -> 231670 | D9: =SUMIF('Dados Brutos'!$U:$U,A9,'Dados Brutos'!$D:$D) -> 1566 | E9: =COUNTIF('Dados Brutos'!$U:$U,A9) -> 23 | F9: =IFERROR(C9/D9,0) -> 147.93742 | G9: =IFERROR(C9/$C$15,0) -> 0.010860485
A10: Eletronicos/Games | B10: =SUMIFS('Dados Brutos'!$V:$V,'Dados Brutos'!$U:$U,A10) -> 6 | C10: =SUMIF('Dados Brutos'!$U:$U,A10,'Dados Brutos'!$C:$C) -> 159630 | D10: =SUMIF('Dados Brutos'!$U:$U,A10,'Dados Brutos'!$D:$D) -> 1666 | E10: =COUNTIF('Dados Brutos'!$U:$U,A10) -> 17 | F10: =IFERROR(C10/D10,0) -> 95.816327 | G10: =IFERROR(C10/$C$15,0) -> 0.0074833134
A11: Utensilios Cozinha/Jardim | B11: =SUMIFS('Dados Brutos'!$V:$V,'Dados Brutos'!$U:$U,A11) -> 2 | C11: =SUMIF('Dados Brutos'!$U:$U,A11,'Dados Brutos'!$C:$C) -> 155300 | D11: =SUMIF('Dados Brutos'!$U:$U,A11,'Dados Brutos'!$D:$D) -> 1790 | E11: =COUNTIF('Dados Brutos'!$U:$U,A11) -> 5 | F11: =IFERROR(C11/D11,0) -> 86.759777 | G11: =IFERROR(C11/$C$15,0) -> 0.0072803268
A12: Tatico/Outdoor | B12: =SUMIFS('Dados Brutos'!$V:$V,'Dados Brutos'!$U:$U,A12) -> 1 | C12: =SUMIF('Dados Brutos'!$U:$U,A12,'Dados Brutos'!$C:$C) -> 154520 | D12: =SUMIF('Dados Brutos'!$U:$U,A12,'Dados Brutos'!$D:$D) -> 1033 | E12: =COUNTIF('Dados Brutos'!$U:$U,A12) -> 38 | F12: =IFERROR(C12/D12,0) -> 149.58374 | G12: =IFERROR(C12/$C$15,0) -> 0.0072437611
A13: Automotivo | B13: =SUMIFS('Dados Brutos'!$V:$V,'Dados Brutos'!$U:$U,A13) -> 1 | C13: =SUMIF('Dados Brutos'!$U:$U,A13,'Dados Brutos'!$C:$C) -> 77840 | D13: =SUMIF('Dados Brutos'!$U:$U,A13,'Dados Brutos'!$D:$D) -> 766 | E13: =COUNTIF('Dados Brutos'!$U:$U,A13) -> 8 | F13: =IFERROR(C13/D13,0) -> 101.6188 | G13: =IFERROR(C13/$C$15,0) -> 0.0036490704
A14: Bike/Ciclismo | B14: =SUMIFS('Dados Brutos'!$V:$V,'Dados Brutos'!$U:$U,A14) -> 2 | C14: =SUMIF('Dados Brutos'!$U:$U,A14,'Dados Brutos'!$C:$C) -> 31840 | D14: =SUMIF('Dados Brutos'!$U:$U,A14,'Dados Brutos'!$D:$D) -> 231 | E14: =COUNTIF('Dados Brutos'!$U:$U,A14) -> 3 | F14: =IFERROR(C14/D14,0) -> 137.8355 | G14: =IFERROR(C14/$C$15,0) -> 0.0014926311
A15: TOTAL | B15: =SUM(B2:B14) -> 275 | C15: =SUM(C2:C14) -> 21331460 | D15: =SUM(D2:D14) -> 104250 | E15: =SUM(E2:E14) -> 3988 | F15: =IFERROR(C15/D15,0) -> 204.61832 | G15: =SUM(G2:G14) -> 1

Sheet Produtos por GTIN
A1: Produtos consolidados por GTIN (código de barras) — 2142 produtos únicos, a partir de 3988 anúncios (351 sem GTIN válido no cadastro, não entraram aqui)
A2: 310 desses GTINs aparecem em mais de um concorrente — o mesmo produto físico, permitindo comparar o preço de cada um lado a lado. Tabela fixa gerada nesta versão do relatório (não recalcula sozinha se os Dados Brutos forem editados).
A4: GTIN | B4: Marca | C4: Categoria | D4: Tamanho (detectado) | E4: Título representativo | F4: Nº Concorrentes | G4: Nº Anúncios consolidados | H4: Receita Total (R$) | I4: Unidades Total | J4: Preço Médio Ponderado (R$) | K4: Preço Médio SIENO (R$) | L4: Preço Médio BAGATELLE (R$) | M4: Preço Médio AUMA (R$) | N4: Diferença de Preço entre Concorrentes (%)
A5: 8411061838778 | B5: CAROLINA HERRERA | C5: Perfumaria/Colonia | D5: 125ml | E5: Perfume 212 Vip Rosé Carolina Herrera Ea | F5: 2 | G5: 8 | H5: 522480 | I5: 811 | J5: 644.24168 | L5: 633.96825 | M5: 656.48649 | N5: 0.035519495
A6: 7898639690388 | B6: G-TECH | C6: Saude/Bem-estar | D6: Não identificado no título | E6: Aparelho De Medir Pressão Digital De Bra | F6: 1 | G6: 2 | H6: 409000 | I6: 3800 | J6: 107.63158 | K6: 107.63158
A7: 3349668566372 | B7: RABANNE | C7: Perfumaria/Colonia | D7: 200ml | E7: Perfume Rabanne 1 Million Eau De Toilett | F7: 2 | G7: 8 | H7: 364890 | I7: 565 | J7: 645.82301 | L7: 624.91909 | M7: 671.05469 | N7: 0.073826507
A8: 8435415032360 | B8: JEAN PAUL GAULTIER | C8: Perfumaria/Colonia | D8: Não identificado no título | E8: Perfume Jean Paul Gaultier Le Male Le Pa | F8: 2 | G8: 6 | H8: 327100 | I8: 457 | J8: 715.75492 | L8: 842.30769 | M8: 699.50617 | N8: 0.20414619
A9: 8435415076906 | B9: JEAN PAUL GAULTIER | C9: Perfumaria/Colonia | D9: 200ml | E9: Perfume Jean Paul Gaultier Le Male Elixi | F9: 2 | G9: 6 | H9: 313400 | I9: 471 | J9: 665.39278 | L9: 1071.4286 | M9: 659.26724 | N9: 0.62518096
A10: 7898301059895 | B10: G-TECH | C10: Saude/Bem-estar | D10: Não identificado no título | E10: Oxímetro De Dedo Digital Portátil Pulso | F10: 1 | G10: 2 | H10: 293000 | I10: 3100 | J10: 94.516129 | K10: 94.516129
A11: 8411061120620 | B11: CAROLINA HERRERA | C11: Perfumaria/Colonia | D11: Não identificado no título | E11: Perfume Carolina Herrera 212 Vip Black E | F11: 1 | G11: 3 | H11: 282990 | I11: 483 | J11: 585.90062 | L11: 585.90062
A12: 3349668592388 | B12: RABANNE | C12: Perfumaria/Colonia | D12: Não identificado no título | E12: Perfume Rabanne Invictus Victory Eau De | F12: 2 | G12: 7 | H12: 222200 | I12: 324 | J12: 685.80247 | L12: 797.10145 | M12: 655.68627 | N12: 0.21567506
A13: 3349668589678 | B13: RABANNE | C13: Perfumaria/Colonia | D13: 200ml | E13: Perfume Rabanne Invictus Eau De Toilette | F13: 2 | G13: 3 | H13: 202100 | I13: 302 | J13: 669.2053 | L13: 700 | M13: 669 | N13: 0.046337818
A14: 7898639692924 | B14: G-TECH | C14: Saude/Bem-estar | D14: Não identificado no título | E14: Aparelho Medidor De Pressão Arterial Dig | F14: 1 | G14: 2 | H14: 185800 | I14: 1410 | J14: 131.77305 | K14: 131.77305
A15: 3614273760164 | B15: PRADA | C15: Perfumaria/Colonia | D15: 90ml | E15: Perfume Feminino Prada Paradoxe Eau De | F15: 2 | G15: 6 | H15: 174200 | I15: 227 | J15: 767.40088 | K15: 660 | M15: 797.74011 | N15: 0.20869714
A16: 3349666007921 | B16: RABANNE | C16: Perfumaria/Colonia | D16: 100ml | E16: Perfume Rabanne 1 Million Eau De Toilett | F16: 2 | G16: 7 | H16: 167280 | I16: 346 | J16: 483.46821 | L16: 481.56028 | M16: 491.875 | N16: 0.021419367
A17: 8411061023655 | B17: CAROLINA HERRERA | C17: Perfumaria/Colonia | D17: Não identificado no título | E17: Perfume Carolina Herrera 212 Men Heroes | F17: 1 | G17: 2 | H17: 151200 | I17: 262 | J17: 577.09924 | M17: 577.09924
A18: 729238146587 | B18: SHISEIDO | C18: Perfumaria/Colonia | D18: Não identificado no título | E18: Shiseido Bb For Sports Fps 50 Medium Bas | F18: 1 | G18: 2 | H18: 147500 | I18: 485 | J18: 304.12371 | M18: 304.12371
A19: 3349668614530 | B19: RABANNE | C19: Perfumaria/Colonia | D19: Não identificado no título | E19: Perfume Rabanne Invictus Victory Elixir | F19: 2 | G19: 9 | H19: 147070 | I19: 208 | J19: 707.06731 | L19: 781.66667 | M19: 684.6875 | N19: 0.14164004
A20: 8411061853207 | B20: CAROLINA HERRERA | C20: Perfumaria/Colonia | D20: 200ml | E20: Perfume Carolina Herrera 212 Men Nyc Eau | F20: 2 | G20: 5 | H20: 138040 | I20: 206 | J20: 670.09709 | L20: 651.84211 | M20: 680.76923 | N20: 0.044377504
A21: 7908407005693 | B21: RITUÁRIA | C21: Suplementos/Nutricao | D21: Não identificado no título | E21: Suplemento Fibras Alimentares Prebiótica | F21: 1 | G21: 2 | H21: 137900 | I21: 2300 | J21: 59.956522 | K21: 59.956522
A22: 3349668581948 | B22: RABANNE | C22: Perfumaria/Colonia | D22: 200ml | E22: Perfume Rabanne 1 Million Parfum 200 Ml | F22: 2 | G22: 9 | H22: 137680 | I22: 173 | J22: 795.83815 | L22: 940 | M22: 794.15205 | N22: 0.18365243
A23: 8435415076937 | B23: JEAN PAUL GAULTIER | C23: Perfumaria/Colonia | D23: Não identificado no título | E23: Perfume Jean Paul Gaultier Le Male Elixi | F23: 2 | G23: 7 | H23: 137180 | I23: 288 | J23: 476.31944 | L23: 646.66667 | M23: 474.52632 | N23: 0.3627625
A24: 3614273069557 | B24: YVES SAINT LAURENT | C24: Perfumaria/Colonia | D24: Não identificado no título | E24: Yves Saint Laurent Libre Intense Feminin | F24: 1 | G24: 4 | H24: 123100 | I24: 144 | J24: 854.86111 | M24: 854.86111
A25: 7898301054494 | B25: PREMIUM | C25: Saude/Bem-estar | D25: Não identificado no título | E25: Aparelho De Pressão Arterial Manual Esfi | F25: 1 | G25: 2 | H25: 122270 | I25: 1802 | J25: 67.852386 | K25: 67.852386
A26: 7898639690999 | B26: G-TECH | C26: Saude/Bem-estar | D26: Não identificado no título | E26: Oxímetro Led G-tech Branco/azul | F26: 1 | G26: 1 | H26: 121000 | I26: 1700 | J26: 71.176471 | K26: 71.176471
A27: 3605533286555 | B27: LANCÔME | C27: Perfumaria/Colonia | D27: Não identificado no título | E27: Perfume Feminino L' Eau De Parfum Fragrâ | F27: 1 | G27: 5 | H27: 118880 | I27: 170 | J27: 699.29412 | M27: 699.29412
A28: 729238146570 | B28: SHISEIDO | C28: Perfumaria/Colonia | D28: Não identificado no título | E28: Shiseido Bb For Sports Fps 50 Light - Ba | F28: 1 | G28: 5 | H28: 115890 | I28: 372 | J28: 311.53226 | M28: 311.53226
A29: 7899952324523 | B29: JEQUITI | C29: Perfumaria/Colonia | D29: Não identificado no título | E29: Perfumes Colônia Miniatura Cebolinha Tur | F29: 1 | G29: 2 | H29: 110500 | I29: 4960 | J29: 22.278226 | K29: 22.278226
A30: 3614273852814 | B30: YVES SAINT LAURENT | C30: Perfumaria/Colonia | D30: Não identificado no título | E30: Yves Saint Laurent Myslf Edp - Perfume M | F30: 2 | G30: 3 | H30: 108800 | I30: 152 | J30: 715.78947 | K30: 707.69231 | M30: 763.63636 | N30: 0.079051383
A31: 3349668627547 | B31: RABANNE | C31: Perfumaria/Colonia | D31: 200ml | E31: Perfume Rabanne Invictus Parfum 200ml Ma | F31: 2 | G31: 4 | H31: 103660 | I31: 134 | J31: 773.58209 | L31: 830 | M31: 772.72727 | N31: 0.074117647
A32: 3349668508587 | B32: RABANNE | C32: Perfumaria/Colonia | D32: 80ml | E32: Rabanne Lady Million Edp 80ml Para Femin | F32: 2 | G32: 5 | H32: 101100 | I32: 173 | J32: 584.39306 | L32: 1233.3333 | M32: 572.94118 | N32: 1.1526352
A33: 4710206002185 | B33: MARURI | C33: Pesca/Nautica | D33: Não identificado no título | E33: Carretilha Maruri Black Tamba Bg 11 Rol; | F33: 1 | G33: 1 | H33: 99700 | I33: 260 | J33: 383.46154 | K33: 383.46154
A34: 7898639692849 | B34: G-TECH | C34: Saude/Bem-estar | D34: Não identificado no título | E34: Termômetro Infravermelho Ultracompacto D | F34: 1 | G34: 1 | H34: 92800 | I34: 1900 | J34: 48.842105 | K34: 48.842105
A35: 7898919865567 | B35: VITAFOR | C35: Suplementos/Nutricao | D35: Não identificado no título | E35: Suplemento Alimentar Em Pó Glutamax Sem | F35: 1 | G35: 1 | H35: 91100 | I35: 1200 | J35: 75.916667 | K35: 75.916667
A36: 8411061786161 | B36: CAROLINA HERRERA | C36: Perfumaria/Colonia | D36: Não identificado no título | E36: Perfume Carolina Herrera Ch Men Eau De T | F36: 2 | G36: 6 | H36: 90690 | I36: 133 | J36: 681.8797 | L36: 809.35484 | M36: 643.13725 | N36: 0.25844807
A37: 7898953272826 | B37: HADALABO | C37: Cosmeticos/Skincare | D37: Não identificado no título | E37: Demaquilante Hada Labo Gokujyun Oil Clea | F37: 1 | G37: 2 | H37: 87400 | I37: 1420 | J37: 61.549296 | K37: 61.549296
A38: 7899206170791 | B38: BESTFER | C38: Utensilios Cozinha/Jardim | D38: Não identificado no título | E38: Cilindro P/ Massas Aço Inox Massa Caseir | F38: 1 | G38: 1 | H38: 84100 | I38: 750 | J38: 112.13333 | K38: 112.13333
A39: 3616302038633 | B39: CHLOÉ | C39: Perfumaria/Colonia | D39: 100ml | E39: Perfume Chloé Eau De Parfum ( Edp ) 100m | F39: 3 | G39: 5 | H39: 82100 | I39: 113 | J39: 726.54867 | K39: 800 | L39: 737.80488 | M39: 647.61905 | N39: 0.23529412
A40: 7898639691279 | B40: G-TECH | C40: Saude/Bem-estar | D40: Não identificado no título | E40: Oxímetro Pediátrico G-tech Verde E Cinza | F40: 1 | G40: 1 | H40: 80800 | I40: 780 | J40: 103.58974 | K40: 103.58974
A41: 3614272648425 | B41: YVES SAINT LAURENT | C41: Perfumaria/Colonia | D41: 90ml | E41: Yves Saint Laurent Libre Eau De Parfum R | F41: 2 | G41: 6 | H41: 77620 | I41: 98 | J41: 792.04082 | K41: 660 | M41: 929.58333 | N41: 0.4084596
A42: 7899206169504 | B42: BESTFER | C42: Outros/Diversos | D42: Não identificado no título | E42: Moedor Carne Bestfer Fazer Hambúrguer Ma | F42: 1 | G42: 1 | H42: 74700 | I42: 720 | J42: 103.75 | K42: 103.75
A43: 7898301056412 | B43: PREMIUM | C43: Saude/Bem-estar | D43: Não identificado no título | E43: Esfigmomanômetro Premium Aneróide Azul + | F43: 1 | G43: 2 | H43: 74370 | I43: 955 | J43: 77.874346 | K43: 77.874346
A44: 8411061105016 | B44: CAROLINA HERRERA | C44: Perfumaria/Colonia | D44: Não identificado no título | E44: Perfume Carolina Herrera 212 Vip Black E | F44: 2 | G44: 6 | H44: 73380 | I44: 98 | J44: 748.77551 | L44: 757.27273 | M44: 731.25 | N44: 0.035586636
A45: 7898639690630 | B45: G-TECH | C45: Saude/Bem-estar | D45: Não identificado no título | E45: G-tech Eletroestimulador Massageador Ten | F45: 1 | G45: 2 | H45: 73300 | I45: 490 | J45: 149.59184 | K45: 149.59184
A46: 8411061782347 | B46: CAROLINA HERRERA | C46: Perfumaria/Colonia | D46: 200ml | E46: Perfume Carolina Herrera 212 Vip Men Eau | F46: 2 | G46: 6 | H46: 72580 | I46: 97 | J46: 748.24742 | L46: 853.07692 | M46: 709.85915 | N46: 0.20175519
A47: 8435415059060 | B47: JEAN PAUL GAULTIER | C47: Perfumaria/Colonia | D47: Não identificado no título | E47: Perfume Jean Paul Gaultier Scandal Eau D | F47: 2 | G47: 8 | H47: 71200 | I47: 85 | J47: 837.64706 | L47: 1085.7143 | M47: 788.73239 | N47: 0.37653061
A48: 751320866073 | B48: LIKLUC | C48: Saude/Bem-estar | D48: Não identificado no título | E48: Xô Febre Compressa Refrescante - Baixar | F48: 1 | G48: 1 | H48: 67000 | I48: 1900 | J48: 35.263158 | K48: 35.263158
A49: 3349668596348 | B49: RABANNE | C49: Perfumaria/Colonia | D49: Não identificado no título | E49: Perfume Rabanne Phantom Eau De Toilette | F49: 2 | G49: 6 | H49: 66540 | I49: 78 | J49: 853.07692 | L49: 1246.25 | M49: 751.6129 | N49: 0.65810086
A50: 8435415012690 | B50: JEAN PAUL GAULTIER | C50: Perfumaria/Colonia | D50: Não identificado no título | E50: Perfume Jean Paul Gaultier Le Male Eau D | F50: 1 | G50: 3 | H50: 64590 | I50: 91 | J50: 709.78022 | M50: 709.78022
A51: 3614274172997 | B51: PRADA | C51: Perfumaria/Colonia | D51: Não identificado no título | E51: Prada Paradigme Eau De Parfum Perfume Ma | F51: 1 | G51: 5 | H51: 62170 | I51: 86 | J51: 722.90698 | M51: 722.90698
A52: 4710206002192 | B52: MARURI | C52: Outros/Diversos | D52: Não identificado no título | E52: Carretilha Pesca Black Tamba Bg 12kg Dra | F52: 1 | G52: 2 | H52: 60700 | I52: 150 | J52: 404.66667 | K52: 404.66667
A53: 3355991004672 | B53: JACQUES BOGART | C53: Perfumaria/Colonia | D53: Não identificado no título | E53: Jacques Bogart Silver Scent Intense Edt | F53: 2 | G53: 4 | H53: 59900 | I53: 180 | J53: 332.77778 | K53: 300 | L53: 378.66667 | N53: 0.26222222
A54: 3349668515660 | B54: RABANNE | C54: Perfumaria/Colonia | D54: Não identificado no título | E54: Invictus De Rabanne Eau De Toilette 100 | F54: 2 | G54: 5 | H54: 58890 | I54: 117 | J54: 503.33333 | L54: 501.03448 | M54: 770 | N54: 0.53682037
A55: 8411061041673 | B55: CAROLINA HERRERA | C55: Perfumaria/Colonia | D55: Não identificado no título | E55: Perfume Carolina Herrera Good Girl Eau D | F55: 2 | G55: 5 | H55: 58560 | I55: 128 | J55: 457.5 | L55: 536.92308 | M55: 437.2549 | N55: 0.22794067
A56: 7794290370754 | B56: SHIMANO | C56: Pesca/Nautica | D56: Não identificado no título | E56: Molinete Shimano Ix 4000r Traseiro Cor P | F56: 1 | G56: 1 | H56: 57600 | I56: 440 | J56: 130.90909 | K56: 130.90909
A57: 3349668644940 | B57: RABANNE | C57: Perfumaria/Colonia | D57: Não identificado no título | E57: Perfume Rabanne Million Gold Elixir Parf | F57: 2 | G57: 4 | H57: 56660 | I57: 58 | J57: 976.89655 | L57: 1310 | M57: 938.46154 | N57: 0.39590164
A58: 3614272648401 | B58: YVES SAINT LAURENT | C58: Perfumaria/Colonia | D58: Não identificado no título | E58: Yves Saint Laurent Libre Feminino Eau De | F58: 2 | G58: 7 | H58: 55750 | I58: 108 | J58: 516.2037 | K58: 514.28571 | M58: 517.12329 | N58: 0.0055175038
A59: 3614273321891 | B59: YVES SAINT LAURENT | C59: Perfumaria/Colonia | D59: Não identificado no título | E59: Yves Saint Laurent Libre Eau De Toilette | F59: 2 | G59: 2 | H59: 55600 | I59: 65 | J59: 855.38462 | K59: 1500 | M59: 801.66667 | N59: 0.87110187
A60: 7898665435397 | B60: VITAFOR | C60: Suplementos/Nutricao | D60: Não identificado no título | E60: Suplemento Alimentar Colagentek Tipo Ii | F60: 1 | G60: 1 | H60: 54900 | I60: 330 | J60: 166.36364 | K60: 166.36364
A61: 3614273069533 | B61: YVES SAINT LAURENT | C61: Perfumaria/Colonia | D61: Não identificado no título | E61: Libre Intense Yves Saint Laurent Fem Edp | F61: 1 | G61: 5 | H61: 54870 | I61: 119 | J61: 461.09244 | M61: 461.09244
A62: 7898639692948 | B62: G-TECH | C62: Saude/Bem-estar | D62: Não identificado no título | E62: Aparelho De Pressão Digital G-tech Gp400 | F62: 1 | G62: 2 | H62: 54600 | I62: 670 | J62: 81.492537 | K62: 81.492537
A63: 4710206002208 | B63: MARURI | C63: Pesca/Nautica | D63: Não identificado no título | E63: Carretilha Maruri Black Tamba Pro 11 Rol | F63: 1 | G63: 1 | H63: 53500 | I63: 190 | J63: 281.57895 | K63: 281.57895
A64: 7896235353690 | B64: WELLA | C64: Perfumaria/Colonia | D64: 1000ml | E64: Condicionador Wella Invigo Nutri-enrich | F64: 1 | G64: 4 | H64: 52490 | I64: 323 | J64: 162.50774 | M64: 162.50774
A65: 3614273953672 | B65: ARMANI BEAUTY | C65: Perfumaria/Colonia | D65: Não identificado no título | E65: Armani Beauty, Perfume Masculino, Acqua | F65: 1 | G65: 2 | H65: 52400 | I65: 60 | J65: 873.33333 | M65: 873.33333
A66: 737052351100 | B66: HUGO BOSS | C66: Perfumaria/Colonia | D66: 100ml | E66: Perfume Masculino Boss Bottled Eau De To | F66: 3 | G66: 4 | H66: 52380 | I66: 144 | J66: 363.75 | K66: 357.14286 | L66: 630 | M66: 490 | N66: 0.764
A67: 8005610325507 | B67: GABRIELA SABATINI | C67: Perfumaria/Colonia | D67: Não identificado no título | E67: Perfume Gabriela Sabatini Feminino Edt 6 | F67: 2 | G67: 6 | H67: 51410 | I67: 513 | J67: 100.21442 | K67: 97.234043 | L67: 132.7907 | N67: 0.36568114
A68: 3614274114645 | B68: YVES SAINT LAURENT | C68: Perfumaria/Colonia | D68: Não identificado no título | E68: Perfume Yves Saint Laurent Myslf Le Parf | F68: 2 | G68: 3 | H68: 51300 | I68: 50 | J68: 1026 | L68: 1960 | M68: 922.22222 | N68: 1.1253012
A69: 7898936769473 | B69: CICLO | C69: Perfumaria/Colonia | D69: Não identificado no título | E69: Ciclo Hello Hello! Lata Eau De Cologne F | F69: 1 | G69: 1 | H69: 51200 | I69: 770 | J69: 66.493506 | K69: 66.493506
A70: 3349668600298 | B70: RABANNE | C70: Perfumaria/Colonia | D70: 200ml | E70: Perfume One 1 Million Elixir Parfum Inte | F70: 2 | G70: 5 | H70: 50380 | I70: 58 | J70: 868.62069 | L70: 815.29412 | M70: 1257.1429 | N70: 0.54195011
A71: 8411061077160 | B71: CAROLINA HERRERA | C71: Perfumaria/Colonia | D71: Não identificado no título | E71: Perfume Carolina Herrera La Bomba Eau De | F71: 2 | G71: 6 | H71: 50030 | I71: 54 | J71: 926.48148 | L71: 1453.75 | M71: 834.78261 | N71: 0.74147135
A72: 7898639693594 | B72: G-TECH | C72: Saude/Bem-estar | D72: Não identificado no título | E72: Tiras Reagentes G-tech Vita Para Monitor | F72: 1 | G72: 1 | H72: 49100 | I72: 1200 | J72: 40.916667 | K72: 40.916667
A73: 8411061088173 | B73: CAROLINA HERRERA | C73: Perfumaria/Colonia | D73: Não identificado no título | E73: Carolina Herrera 212 Sexy Eau De Parfum | F73: 1 | G73: 4 | H73: 48400 | I73: 72 | J73: 672.22222 | L73: 672.22222
A74: 3616302020652 | B74: BURBERRY | C74: Perfumaria/Colonia | D74: Não identificado no título | E74: Burberry Goddess Perfume Feminino Edp 10 | F74: 2 | G74: 5 | H74: 47980 | I74: 82 | J74: 585.12195 | K74: 532 | M74: 668.125 | N74: 0.25587406
A75: 8435415076944 | B75: JEAN PAUL GAULTIER | C75: Perfumaria/Colonia | D75: Não identificado no título | E75: Perfume De Perfume Jean Paul Gaultier Le | F75: 2 | G75: 4 | H75: 47740 | I75: 65 | J75: 734.46154 | L75: 1000 | M75: 717.04918 | N75: 0.39460448
A76: 7898639692955 | B76: G-TECH | C76: Saude/Bem-estar | D76: Não identificado no título | E76: Medidor De Pressão Digital De Pulso G-te | F76: 1 | G76: 2 | H76: 47380 | I76: 542 | J76: 87.416974 | K76: 87.416974
A77: 8435415050760 | B77: JEAN PAUL GAULTIER | C77: Perfumaria/Colonia | D77: Não identificado no título | E77: Perfume Jean Paul Gaultier Scandal Eau D | F77: 2 | G77: 6 | H77: 47030 | I77: 70 | J77: 671.85714 | L77: 1191.25 | M77: 604.83871 | N77: 0.96953333
A78: 3595471041197 | B78: MERCEDES-BENZ | C78: Perfumaria/Colonia | D78: Não identificado no título | E78: Perfume Mercedes-benz Club Black Eau De | F78: 1 | G78: 1 | H78: 46400 | I78: 150 | J78: 309.33333 | K78: 309.33333
A79: 3614273852821 | B79: YSL | C79: Perfumaria/Colonia | D79: Não identificado no título | E79: Yves Saint Laurent Myslf Edp - Perfume M | F79: 1 | G79: 2 | H79: 45800 | I79: 75 | J79: 610.66667 | M79: 610.66667
A80: 8411061781197 | B80: CAROLINA HERRERA | C80: Perfumaria/Colonia | D80: 30ml | E80: 212 Vip Rose Edp 30ml Feminino - Carolin | F80: 2 | G80: 5 | H80: 45240 | I80: 118 | J80: 383.38983 | L80: 840 | M80: 363.18584 | N80: 1.3128655
A81: 7898665430071 | B81: VITAFOR | C81: Suplementos/Nutricao | D81: Não identificado no título | E81: Vitamina D3 60 Cápsulas Vitafor Compra G | F81: 1 | G81: 1 | H81: 45100 | I81: 900 | J81: 50.111111 | K81: 50.111111
A82: 7908412515507 | B82: ELGIN | C82: Casa/Eletrodomesticos | D82: Não identificado no título | E82: Fogão Cooktop Elétrico Elgin 2 Bocas Pre | F82: 1 | G82: 1 | H82: 44800 | I82: 450 | J82: 99.555556 | K82: 99.555556
A83: 8435415062190 | B83: JEAN PAUL GAULTIER | C83: Perfumaria/Colonia | D83: Não identificado no título | E83: Le Beau Le Parfum Eau De Parfum Intense | F83: 2 | G83: 5 | H83: 44570 | I83: 55 | J83: 810.36364 | L83: 756.66667 | M83: 813.46154 | N83: 0.075059302
A84: 8432225129778 | B84: REVLON | C84: Outros/Diversos | D84: 150ml | E84: Spray Revlon Uniq One De 150ml | F84: 1 | G84: 1 | H84: 44200 | I84: 640 | J84: 69.0625 | K84: 69.0625
A85: 4975759103158 | B85: SOFT99 | C85: Automotivo | D85: 120ml | E85: Glaco Big 120ml - Cristalizador Vidros R | F85: 1 | G85: 1 | H85: 44000 | I85: 420 | J85: 104.7619 | K85: 104.7619
A86: 885911467629 | B86: DEWALT | C86: Ferramentas | D86: Não identificado no título | E86: Parafusadeira De Impacto 1/4 À Bateria | F86: 1 | G86: 1 | H86: 43600 | I86: 60 | J86: 726.66667 | K86: 726.66667
A87: 8435415032315 | B87: JEAN PAUL GAULTIER | C87: Perfumaria/Colonia | D87: Não identificado no título | E87: Perfume Jean Paul Gaultier Le Male Le Pa | F87: 2 | G87: 5 | H87: 43590 | I87: 74 | J87: 589.05405 | L87: 666.25 | M87: 552 | N87: 0.20697464
A88: 3614274091885 | B88: ARMANI BEAUTY | C88: Perfumaria/Colonia | D88: Não identificado no título | E88: Armani Beauty Perfume Feminino Acqua Di | F88: 1 | G88: 3 | H88: 42820 | I88: 61 | J88: 701.96721 | M88: 701.96721
A89: 3355991004665 | B89: JACQUES BOGART | C89: Perfumaria/Colonia | D89: Não identificado no título | E89: Jacques Bogart Silver Scent Eau De Toile | F89: 2 | G89: 5 | H89: 42000 | I89: 129 | J89: 325.5814 | K89: 294.11765 | L89: 444.44444 | N89: 0.51111111
A90: 7896086911919 | B90: MAHOGANY | C90: Perfumaria/Colonia | D90: Não identificado no título | E90: Fragrãncia Desodorante Corporal Make Me | F90: 1 | G90: 2 | H90: 41900 | I90: 210 | J90: 199.52381 | M90: 199.52381
A91: 4549526616860 | B91: CASIO | C91: Eletronicos/Games | D91: Não identificado no título | E91: Calculadora Científica 252 Funções Fx-82 | F91: 1 | G91: 1 | H91: 41300 | I91: 470 | J91: 87.87234 | K91: 87.87234
A92: 8411061043844 | B92: CAROLINA HERRERA | C92: Perfumaria/Colonia | D92: Não identificado no título | E92: Perfume Carolina Herrera 212 Vip Black E | F92: 2 | G92: 6 | H92: 40920 | I92: 66 | J92: 620 | L92: 636.36364 | M92: 611.81818 | N92: 0.040118871
A93: 3614273953832 | B93: ARMANI BEAUTY | C93: Perfumaria/Colonia | D93: Não identificado no título | E93: Armani Beauty, Perfume Masculino, Acqua | F93: 1 | G93: 2 | H93: 40300 | I93: 45 | J93: 895.55556 | M93: 895.55556
A94: 8411061865583 | B94: CAROLINA HERRERA | C94: Perfumaria/Colonia | D94: Não identificado no título | E94: Carolina Herrera 212 Sexy Eau De Toilett | F94: 2 | G94: 6 | H94: 39900 | I94: 56 | J94: 712.5 | L94: 700 | M94: 731.81818 | N94: 0.045454545
A95: 8435415032278 | B95: JEAN PAUL GAULTIER | C95: Perfumaria/Colonia | D95: Não identificado no título | E95: Perfume Jean Paul Gaultier Le Male Eau D | F95: 2 | G95: 4 | H95: 39150 | I95: 82 | J95: 477.43902 | L95: 456.81818 | M95: 485 | N95: 0.061691542
A96: 885911606134 | B96: DEWALT | C96: Ferramentas | D96: Não identificado no título | E96: Martelete Perfurador E Rompedor Dewalt M | F96: 1 | G96: 1 | H96: 38900 | I96: 20 | J96: 1945 | K96: 1945
A97: 3355991002319 | B97: JACQUES BOGART | C97: Perfumaria/Colonia | D97: Não identificado no título | E97: Jacques Bogart Silver Scent ( Tradiciona | F97: 1 | G97: 2 | H97: 38300 | I97: 140 | J97: 273.57143 | L97: 273.57143
A98: 3595471081032 | B98: MERCEDES-BENZ | C98: Perfumaria/Colonia | D98: 100ml | E98: Perfume Masculino Mercedes-benz Select N | F98: 2 | G98: 4 | H98: 38120 | I98: 126 | J98: 302.53968 | K98: 289.16667 | L98: 570 | N98: 0.97118156
A99: 3614273521307 | B99: AZZARO | C99: Perfumaria/Colonia | D99: 100ml | E99: Perfume Masculino Eau De Parfum Azzaro T | F99: 2 | G99: 3 | H99: 37600 | I99: 65 | J99: 578.46154 | K99: 920 | M99: 550 | N99: 0.67272727
A100: 3165140799690 | B100: BOSCH | C100: Ferramentas | D100: Não identificado no título | E100: Bolsa Para Ferramentas Bosch Mini Softca | F100: 1 | G100: 1 | H100: 36600 | I100: 730 | J100: 50.136986 | K100: 50.136986
A101: 8056669925798 | B101: DOLCE & GABBANA | C101: Perfumaria/Colonia | D101: Não identificado no título | E101: Dolce&gabbana Light Blue Eau De Parfum 2 | F101: 3 | G101: 6 | H101: 36340 | I101: 35 | J101: 1038.2857 | K101: 1080 | L101: 2050 | M101: 958.57143 | N101: 1.1385991
...

Sheet Dados Brutos
A1: Título | B1: Marca | C1: Vendas em $ | D1: Vendas em Unid. | E1: Preço Médio | F1: Tipo de Publicação | G1: Fulfillment | H1: Catálogo. | I1: Com Frete grátis | J1: Com Mercado Envios | K1: Com desconto | L1: SKU | M1: OEM | N1: GTIN | O1: N° PEÇA | P1: Estado | Q1: MercadoPago | R1: Republicada | S1: Condição | T1: Concorrente | U1: Categoria | V1: 1a Ocorrencia Marca (geral) | W1: 1a Ocorrencia Marca+Concorrente
A2: Aparelho De Medir Pressão Digital De Bra | B2: G-TECH | C2: 237000 | D2: 2200 | E2: 109.03076 | F2: Clássico | G2: Sim | H2: Sim | I2: Sim | J2: Sim | K2: Sim | L2: 11438 | N2: 7898639690388 | P2: active | Q2: Sim | R2: Não | S2: new | T2: SIENO | U2: Saude/Bem-estar | V2: =IF(COUNTIF($B$2:B2,B2)=1,1,0) -> 1 | W2: =IF(COUNTIFS($B$2:B2,B2,$T$2:T2,T2)=1,1,0) -> 1
A3: Oxímetro Oled G-tech Púrpura | B3: G-TECH | C3: 179000 | D3: 1900 | E3: 94.082401 | F3: Clássico | G3: Sim | H3: Sim | I3: Sim | J3: Sim | K3: Não | L3: 11426 | N3: 7898301059895 | P3: active | Q3: Sim | R3: Não | S3: new | T3: SIENO | U3: Saude/Bem-estar | V3: =IF(COUNTIF($B$2:B3,B3)=1,1,0) -> 0 | W3: =IF(COUNTIFS($B$2:B3,B3,$T$2:T3,T3)=1,1,0) -> 0
A4: Aparelho Medidor De Pressão Digital De B | B4: G-TECH | C4: 172000 | D4: 1600 | E4: 107.99184 | F4: Clássico | G4: Sim | H4: Sim | I4: Sim | J4: Sim | K4: Sim | L4: 11438 | N4: 7898639690388 | P4: paused | Q4: Sim | R4: Não | S4: new | T4: SIENO | U4: Saude/Bem-estar | V4: =IF(COUNTIF($B$2:B4,B4)=1,1,0) -> 0 | W4: =IF(COUNTIFS($B$2:B4,B4,$T$2:T4,T4)=1,1,0) -> 0
A5: Eudora Club 6 Voyage Deo-colônia 95ml Pa | B5: EUDORA | C5: 143000 | D5: 1400 | E5: 103.12618 | F5: Clássico | G5: Sim | H5: Sim | I5: Sim | J5: Sim | K5: Sim | L5: 19578 | N5: 7.8910339e+25 | P5: active | Q5: Sim | R5: Não | S5: new | T5: SIENO | U5: Perfumaria/Colonia | V5: =IF(COUNTIF($B$2:B5,B5)=1,1,0) -> 1 | W5: =IF(COUNTIFS($B$2:B5,B5,$T$2:T5,T5)=1,1,0) -> 1
A6: Aparelho De Pressão Arterial Manual Esfi | B6: PREMIUM | C6: 122000 | D6: 1800 | E6: 68.491279 | F6: Clássico | G6: Sim | H6: Sim | I6: Não | J6: Sim | K6: Não | L6: 15101 | N6: 7898301054494 | P6: active | Q6: Sim | R6: Não | S6: new | T6: SIENO | U6: Saude/Bem-estar | V6: =IF(COUNTIF($B$2:B6,B6)=1,1,0) -> 1 | W6: =IF(COUNTIFS($B$2:B6,B6,$T$2:T6,T6)=1,1,0) -> 1
A7: Oxímetro Led G-tech Branco/azul | B7: G-TECH | C7: 121000 | D7: 1700 | E7: 71.807116 | F7: Clássico | G7: Sim | H7: Sim | I7: Não | J7: Sim | K7: Não | L7: 11317 | N7: 7898639690999 | P7: active | Q7: Sim | R7: Não | S7: new | T7: SIENO | U7: Saude/Bem-estar | V7: =IF(COUNTIF($B$2:B7,B7)=1,1,0) -> 0 | W7: =IF(COUNTIFS($B$2:B7,B7,$T$2:T7,T7)=1,1,0) -> 0
A8: Oxímetro De Dedo Digital Portátil Pulso | B8: G-TECH | C8: 114000 | D8: 1200 | E8: 93.901414 | F8: Clássico | G8: Sim | H8: Sim | I8: Sim | J8: Sim | K8: Sim | L8: 11426 | N8: 7898301059895 | P8: active | Q8: Sim | R8: Não | S8: new | T8: SIENO | U8: Saude/Bem-estar | V8: =IF(COUNTIF($B$2:B8,B8)=1,1,0) -> 0 | W8: =IF(COUNTIFS($B$2:B8,B8,$T$2:T8,T8)=1,1,0) -> 0
A9: Aparelho Medidor De Pressão Arterial Dig | B9: MAIS - GTECH | C9: 110000 | D9: 820 | E9: 134.04171 | F9: Clássico | G9: Sim | H9: Sim | I9: Sim | J9: Sim | K9: Sim | L9: 15219 | N9: 7898639692924 | P9: active | Q9: Sim | R9: Não | S9: new | T9: SIENO | U9: Saude/Bem-estar | V9: =IF(COUNTIF($B$2:B9,B9)=1,1,0) -> 1 | W9: =IF(COUNTIFS($B$2:B9,B9,$T$2:T9,T9)=1,1,0) -> 1
A10: Perfume Nautica Voyage Eau De Toilette M | B10: NAUTICA | C10: 109000 | D10: 1100 | E10: 102.55892 | F10: Clássico | G10: Sim | H10: Sim | I10: Sim | J10: Sim | K10: Não | L10: 19712 | N10: 31655531908 | P10: active | Q10: Sim | R10: Não | S10: new | T10: SIENO | U10: Perfumaria/Colonia | V10: =IF(COUNTIF($B$2:B10,B10)=1,1,0) -> 1 | W10: =IF(COUNTIFS($B$2:B10,B10,$T$2:T10,T10)=1,1,0) -> 1
A11: Carretilha Maruri Black Tamba Bg 11 Rol; | B11: MARURI | C11: 99700 | D11: 260 | E11: 379.20141 | F11: Clássico | G11: Sim | H11: Sim | I11: Sim | J11: Sim | K11: Não | L11: 4710206002185 | N11: 4710206002185 | P11: active | Q11: Sim | R11: Não | S11: new | T11: SIENO | U11: Pesca/Nautica | V11: =IF(COUNTIF($B$2:B11,B11)=1,1,0) -> 1 | W11: =IF(COUNTIFS($B$2:B11,B11,$T$2:T11,T11)=1,1,0) -> 1
A12: Aparelho Medidor De Pressão Arterial Dig | B12: G-TECH | C12: 99700 | D12: 930 | E12: 107.04358 | F12: Clássico | G12: Sim | H12: Sim | I12: Sim | J12: Sim | K12: Sim | L12: 11438 | N12: 7.8986397e+25 | P12: active | Q12: Sim | R12: Não | S12: new | T12: SIENO | U12: Saude/Bem-estar | V12: =IF(COUNTIF($B$2:B12,B12)=1,1,0) -> 0 | W12: =IF(COUNTIFS($B$2:B12,B12,$T$2:T12,T12)=1,1,0) -> 0
A13: Perfumes Colônia Miniatura Cebolinha Tur | B13: JEQUITI | C13: 97700 | D13: 4400 | E13: 21.988762 | F13: Clássico | G13: Sim | H13: Sim | I13: Não | J13: Sim | K13: Não | L13: 7899952324523 | N13: 7899952324523 | P13: under_review | Q13: Sim | R13: Não | S13: new | T13: SIENO | U13: Perfumaria/Colonia | V13: =IF(COUNTIF($B$2:B13,B13)=1,1,0) -> 1 | W13: =IF(COUNTIFS($B$2:B13,B13,$T$2:T13,T13)=1,1,0) -> 1
A14: Yves Saint Laurent Y Edp 100ml Para Masc | B14: YVES SAINT LAURENT | C14: 94400 | D14: 140 | E14: 689.28555 | F14: Clássico | G14: Sim | H14: Sim | I14: Sim | J14: Sim | K14: Não | L14: 3614272050358 | P14: active | Q14: Sim | R14: Não | S14: new | T14: SIENO | U14: Perfumaria/Colonia | V14: =IF(COUNTIF($B$2:B14,B14)=1,1,0) -> 1 | W14: =IF(COUNTIFS($B$2:B14,B14,$T$2:T14,T14)=1,1,0) -> 1
A15: Termômetro Infravermelho Ultracompacto D | B15: G-TECH | C15: 92800 | D15: 1900 | E15: 48.258158 | F15: Clássico | G15: Sim | H15: Sim | I15: Não | J15: Sim | K15: Não | L15: 21777 | N15: 7898639692849 | P15: active | Q15: Sim | R15: Não | S15: new | T15: SIENO | U15: Saude/Bem-estar | V15: =IF(COUNTIF($B$2:B15,B15)=1,1,0) -> 0 | W15: =IF(COUNTIFS($B$2:B15,B15,$T$2:T15,T15)=1,1,0) -> 0
A16: Perfume Britney Spears Fantasy Eau De Pa | B16: BRITNEY SPEARS | C16: 92400 | D16: 480 | E16: 192.93186 | F16: Clássico | G16: Sim | H16: Sim | I16: Sim | J16: Sim | K16: Sim | L16: 07640372090037 | P16: active | Q16: Sim | R16: Não | S16: new | T16: SIENO | U16: Perfumaria/Colonia | V16: =IF(COUNTIF($B$2:B16,B16)=1,1,0) -> 1 | W16: =IF(COUNTIFS($B$2:B16,B16,$T$2:T16,T16)=1,1,0) -> 1
A17: Yves Saint Laurent Myslf Edp - Perfume M | B17: YVES SAINT LAURENT | C17: 92000 | D17: 130 | E17: 707.43315 | F17: Clássico | G17: Sim | H17: Sim | I17: Sim | J17: Sim | K17: Não | L17: 3614273852814 | N17: 3614273852814 | P17: active | Q17: Sim | R17: Não | S17: new | T17: SIENO | U17: Perfumaria/Colonia | V17: =IF(COUNTIF($B$2:B17,B17)=1,1,0) -> 0 | W17: =IF(COUNTIFS($B$2:B17,B17,$T$2:T17,T17)=1,1,0) -> 0
A18: Suplemento Alimentar Em Pó Glutamax Sem | B18: VITAFOR | C18: 91100 | D18: 1200 | E18: 76.723199 | F18: Clássico | G18: Sim | H18: Sim | I18: Não | J18: Sim | K18: Não | L18: 15928 | N18: 7898919865567 | P18: active | Q18: Sim | R18: Não | S18: new | T18: SIENO | U18: Suplementos/Nutricao | V18: =IF(COUNTIF($B$2:B18,B18)=1,1,0) -> 1 | W18: =IF(COUNTIFS($B$2:B18,B18,$T$2:T18,T18)=1,1,0) -> 1
A19: Dolce & Gabbana The One For Men Masculin | B19: DOLCE & GABBANA | C19: 84600 | D19: 150 | E19: 571.46216 | F19: Clássico | G19: Sim | H19: Sim | I19: Sim | J19: Sim | K19: Sim | L19: 8056669925859 | P19: active | Q19: Sim | R19: Não | S19: new | T19: SIENO | U19: Perfumaria/Colonia | V19: =IF(COUNTIF($B$2:B19,B19)=1,1,0) -> 1 | W19: =IF(COUNTIFS($B$2:B19,B19,$T$2:T19,T19)=1,1,0) -> 1
A20: Cilindro P/ Massas Aço Inox Massa Caseir | B20: BESTFER | C20: 84100 | D20: 750 | E20: 111.57529 | F20: Clássico | G20: Sim | H20: Sim | I20: Sim | J20: Sim | K20: Não | L20: 7899206170791 | N20: 7899206170791 | P20: active | Q20: Sim | R20: Não | S20: new | T20: SIENO | U20: Utensilios Cozinha/Jardim | V20: =IF(COUNTIF($B$2:B20,B20)=1,1,0) -> 1 | W20: =IF(COUNTIFS($B$2:B20,B20,$T$2:T20,T20)=1,1,0) -> 1
A21: Suplemento Fibras Alimentares Prebiótica | B21: RITUÁRIA | C21: 83800 | D21: 1400 | E21: 60.836906 | F21: Clássico | G21: Sim | H21: Sim | I21: Não | J21: Sim | K21: Não | L21: 7908407005693 | N21: 7908407005693 | P21: active | Q21: Sim | R21: Não | S21: new | T21: SIENO | U21: Suplementos/Nutricao | V21: =IF(COUNTIF($B$2:B21,B21)=1,1,0) -> 1 | W21: =IF(COUNTIFS($B$2:B21,B21,$T$2:T21,T21)=1,1,0) -> 1
A22: Oxímetro Pediátrico G-tech Verde E Cinza | B22: G-TECH | C22: 80800 | D22: 780 | E22: 104.00537 | F22: Clássico | G22: Sim | H22: Sim | I22: Sim | J22: Sim | K22: Sim | L22: 12309 | N22: 7898639691279 | P22: paused | Q22: Sim | R22: Não | S22: new | T22: SIENO | U22: Saude/Bem-estar | V22: =IF(COUNTIF($B$2:B22,B22)=1,1,0) -> 0 | W22: =IF(COUNTIFS($B$2:B22,B22,$T$2:T22,T22)=1,1,0) -> 0
A23: Aparelho De Pressão Digital De Braço G-t | B23: G-TECH | C23: 75800 | D23: 590 | E23: 128.19042 | F23: Clássico | G23: Sim | H23: Sim | I23: Sim | J23: Sim | K23: Sim | L23: 15219 | N23: 7898639692924 | P23: active | Q23: Sim | R23: Não | S23: new | T23: SIENO | U23: Saude/Bem-estar | V23: =IF(COUNTIF($B$2:B23,B23)=1,1,0) -> 0 | W23: =IF(COUNTIFS($B$2:B23,B23,$T$2:T23,T23)=1,1,0) -> 0
A24: Moedor Carne Bestfer Fazer Hambúrguer Ma | B24: BESTFER | C24: 74700 | D24: 720 | E24: 104.4507 | F24: Clássico | G24: Sim | H24: Sim | I24: Sim | J24: Sim | K24: Não | L24: 22118 | N24: 7899206169504 | P24: active | Q24: Sim | R24: Não | S24: new | T24: SIENO | U24: Outros/Diversos | V24: =IF(COUNTIF($B$2:B24,B24)=1,1,0) -> 0 | W24: =IF(COUNTIFS($B$2:B24,B24,$T$2:T24,T24)=1,1,0) -> 0
A25: Molinete Shimano Fx Fc 4000 Cor Preto/do | B25: SHIMANO | C25: 74300 | D25: 380 | E25: 195.00656 | F25: Clássico | G25: Sim | H25: Sim | I25: Sim | J25: Sim | K25: Sim | L25: 022255233699 | N25: 22255233699 | P25: active | Q25: Sim | R25: Não | S25: new | T25: SIENO | U25: Pesca/Nautica | V25: =IF(COUNTIF($B$2:B25,B25)=1,1,0) -> 1 | W25: =IF(COUNTIFS($B$2:B25,B25,$T$2:T25,T25)=1,1,0) -> 1
A26: Esfigmomanômetro Premium Aneróide Azul + | B26: PREMIUM | C26: 73900 | D26: 950 | E26: 77.989283 | F26: Clássico | G26: Sim | H26: Sim | I26: Não | J26: Sim | K26: Não | L26: 18455 | N26: 7898301056412 | P26: active | Q26: Sim | R26: Não | S26: new | T26: SIENO | U26: Saude/Bem-estar | V26: =IF(COUNTIF($B$2:B26,B26)=1,1,0) -> 0 | W26: =IF(COUNTIFS($B$2:B26,B26,$T$2:T26,T26)=1,1,0) -> 0
A27: Demaquilante Hada Labo Gokujyun Oil Clea | B27: HADALABO | C27: 73700 | D27: 1200 | E27: 63.300034 | F27: Clássico | G27: Sim | H27: Sim | I27: Não | J27: Sim | K27: Não | L27: 7898953272826 | N27: 7898953272826 | P27: active | Q27: Sim | R27: Não | S27: new | T27: SIENO | U27: Cosmeticos/Skincare | V27: =IF(COUNTIF($B$2:B27,B27)=1,1,0) -> 1 | W27: =IF(COUNTIFS($B$2:B27,B27,$T$2:T27,T27)=1,1,0) -> 1
A28: Xô Febre Compressa Refrescante - Baixar | B28: LIKLUC | C28: 67000 | D28: 1900 | E28: 35.806636 | F28: Clássico | G28: Sim | H28: Sim | I28: Não | J28: Sim | K28: Não | L28: 751320866073 | N28: 751320866073 | P28: active | Q28: Sim | R28: Não | S28: new | T28: SIENO | U28: Saude/Bem-estar | V28: =IF(COUNTIF($B$2:B28,B28)=1,1,0) -> 1 | W28: =IF(COUNTIFS($B$2:B28,B28,$T$2:T28,T28)=1,1,0) -> 1
A29: G-tech Eletroestimulador Massageador Ten | B29: G-TECH | C29: 57700 | D29: 380 | E29: 149.92855 | F29: Clássico | G29: Sim | H29: Sim | I29: Sim | J29: Sim | K29: Não | L29: 13486 | N29: 7898639690630 | P29: active | Q29: Sim | R29: Não | S29: new | T29: SIENO | U29: Saude/Bem-estar | V29: =IF(COUNTIF($B$2:B29,B29)=1,1,0) -> 0 | W29: =IF(COUNTIFS($B$2:B29,B29,$T$2:T29,T29)=1,1,0) -> 0
A30: Molinete Shimano Ix 4000r Traseiro Cor P | B30: SHIMANO | C30: 57600 | D30: 440 | E30: 131.30966 | F30: Clássico | G30: Sim | H30: Sim | I30: Sim | J30: Sim | K30: Não | L30: 7794290370754 | N30: 7794290370754 | P30: active | Q30: Sim | R30: Não | S30: new | T30: SIENO | U30: Pesca/Nautica | V30: =IF(COUNTIF($B$2:B30,B30)=1,1,0) -> 0 | W30: =IF(COUNTIFS($B$2:B30,B30,$T$2:T30,T30)=1,1,0) -> 0
A31: Ferro De Passar Roupa À Seco Ou Vapor Bl | B31: BLACK & DECKER | C31: 55500 | D31: 440 | E31: 127.09265 | F31: Clássico | G31: Sim | H31: Sim | I31: Sim | J31: Sim | K31: Sim | L31: 7898735581641 | P31: active | Q31: Sim | R31: Não | S31: new | T31: SIENO | U31: Ferramentas | V31: =IF(COUNTIF($B$2:B31,B31)=1,1,0) -> 1 | W31: =IF(COUNTIFS($B$2:B31,B31,$T$2:T31,T31)=1,1,0) -> 1
A32: Carretilha Pesca Black Tamba Bg 12kg Dra | B32: MARURI | C32: 55400 | D32: 140 | E32: 407.28206 | F32: Clássico | G32: Sim | H32: Sim | I32: Sim | J32: Sim | K32: Não | L32: 4710206002192 | N32: 4710206002192 | P32: active | Q32: Sim | R32: Não | S32: new | T32: SIENO | U32: Pesca/Nautica | V32: =IF(COUNTIF($B$2:B32,B32)=1,1,0) -> 0 | W32: =IF(COUNTIFS($B$2:B32,B32,$T$2:T32,T32)=1,1,0) -> 0
A33: Suplemento Alimentar Colagentek Tipo Ii | B33: VITAFOR | C33: 54900 | D33: 330 | E33: 165.40199 | F33: Clássico | G33: Sim | H33: Sim | I33: Sim | J33: Sim | K33: Sim | L33: 7898665435397 | N33: 7898665435397 | P33: paused | Q33: Sim | R33: Não | S33: new | T33: SIENO | U33: Suplementos/Nutricao | V33: =IF(COUNTIF($B$2:B33,B33)=1,1,0) -> 0 | W33: =IF(COUNTIFS($B$2:B33,B33,$T$2:T33,T33)=1,1,0) -> 0
A34: Suplemento Fibras Alimentares Prebiótica | B34: RITUÁRIA | C34: 54100 | D34: 900 | E34: 60.442369 | F34: Clássico | G34: Sim | H34: Sim | I34: Não | J34: Sim | K34: Não | L34: 7908407005693 | N34: 7908407005693 | P34: active | Q34: Sim | R34: Não | S34: new | T34: SIENO | U34: Suplementos/Nutricao | V34: =IF(COUNTIF($B$2:B34,B34)=1,1,0) -> 0 | W34: =IF(COUNTIFS($B$2:B34,B34,$T$2:T34,T34)=1,1,0) -> 0
A35: Suplemento Fórmula 4mag Magnésio Rituári | B35: RITUÁRIA | C35: 54000 | D35: 1200 | E35: 44.043592 | F35: Clássico | G35: Sim | H35: Sim | I35: Não | J35: Sim | K35: Não | L35: 7908407007796 | P35: paused | Q35: Sim | R35: Não | S35: new | T35: SIENO | U35: Suplementos/Nutricao | V35: =IF(COUNTIF($B$2:B35,B35)=1,1,0) -> 0 | W35: =IF(COUNTIFS($B$2:B35,B35,$T$2:T35,T35)=1,1,0) -> 0
A36: Carretilha Maruri Black Tamba Pro 11 Rol | B36: MARURI | C36: 53500 | D36: 190 | E36: 284.31383 | F36: Clássico | G36: Sim | H36: Sim | I36: Sim | J36: Sim | K36: Sim | L36: 4710206002208 | N36: 4710206002208 | P36: active | Q36: Sim | R36: Não | S36: new | T36: SIENO | U36: Pesca/Nautica | V36: =IF(COUNTIF($B$2:B36,B36)=1,1,0) -> 0 | W36: =IF(COUNTIFS($B$2:B36,B36,$T$2:T36,T36)=1,1,0) -> 0
A37: Ciclo Hello Hello! Lata Eau De Cologne F | B37: CICLO | C37: 51200 | D37: 770 | E37: 66.742999 | F37: Clássico | G37: Sim | H37: Sim | I37: Não | J37: Sim | K37: Não | L37: 18853 | N37: 7898936769473 | P37: active | Q37: Sim | R37: Não | S37: new | T37: SIENO | U37: Perfumaria/Colonia | V37: =IF(COUNTIF($B$2:B37,B37)=1,1,0) -> 1 | W37: =IF(COUNTIFS($B$2:B37,B37,$T$2:T37,T37)=1,1,0) -> 1
A38: Perfume Masculino Boss Bottled Eau De To | B38: HUGO BOSS | C38: 50000 | D38: 140 | E38: 354.28191 | F38: Clássico | G38: Sim | H38: Sim | I38: Sim | J38: Sim | K38: Não | L38: 737052351100 | N38: 737052351100 | P38: active | Q38: Sim | R38: Não | S38: new | T38: SIENO | U38: Perfumaria/Colonia | V38: =IF(COUNTIF($B$2:B38,B38)=1,1,0) -> 1 | W38: =IF(COUNTIFS($B$2:B38,B38,$T$2:T38,T38)=1,1,0) -> 1
A39: Tiras Reagentes G-tech Vita Para Monitor | B39: G-TECH | C39: 49100 | D39: 1200 | E39: 41.088954 | F39: Clássico | G39: Sim | H39: Sim | I39: Não | J39: Sim | K39: Sim | L39: 19986 | N39: 7898639693594 | P39: paused | Q39: Sim | R39: Não | S39: new | T39: SIENO | U39: Saude/Bem-estar | V39: =IF(COUNTIF($B$2:B39,B39)=1,1,0) -> 0 | W39: =IF(COUNTIFS($B$2:B39,B39,$T$2:T39,T39)=1,1,0) -> 0
A40: Aparelho De Pressão Digital G-tech Gp400 | B40: G-TECH | C40: 48900 | D40: 610 | E40: 79.923448 | F40: Clássico | G40: Sim | H40: Sim | I40: Sim | J40: Sim | K40: Não | L40: 15760 | N40: 7898639692948 | P40: paused | Q40: Sim | R40: Não | S40: new | T40: SIENO | U40: Saude/Bem-estar | V40: =IF(COUNTIF($B$2:B40,B40)=1,1,0) -> 0 | W40: =IF(COUNTIFS($B$2:B40,B40,$T$2:T40,T40)=1,1,0) -> 0
A41: Club 6 Voyage Eudora Deo Colônia 95ml Co | B41: EUDORA | C41: 48500 | D41: 470 | E41: 103.91839 | F41: Clássico | G41: Sim | H41: Sim | I41: Sim | J41: Sim | K41: Sim | L41: 7891033872923 | P41: active | Q41: Sim | R41: Não | S41: new | T41: SIENO | U41: Perfumaria/Colonia | V41: =IF(COUNTIF($B$2:B41,B41)=1,1,0) -> 0 | W41: =IF(COUNTIFS($B$2:B41,B41,$T$2:T41,T41)=1,1,0) -> 0
A42: Medidor De Pressão Digital De Pulso G-te | B42: G-TECH | C42: 47200 | D42: 540 | E42: 87.953985 | F42: Clássico | G42: Sim | H42: Sim | I42: Sim | J42: Sim | K42: Não | L42: 15823 | N42: 7898639692955 | P42: active | Q42: Sim | R42: Não | S42: new | T42: SIENO | U42: Saude/Bem-estar | V42: =IF(COUNTIF($B$2:B42,B42)=1,1,0) -> 0 | W42: =IF(COUNTIFS($B$2:B42,B42,$T$2:T42,T42)=1,1,0) -> 0
A43: Perfume Mercedes-benz Club Black Eau De | B43: MERCEDES-BENZ | C43: 46400 | D43: 150 | E43: 305.47178 | F43: Clássico | G43: Sim | H43: Sim | I43: Sim | J43: Sim | K43: Sim | L43: 10911 | N43: 3595471041197 | P43: active | Q43: Sim | R43: Não | S43: new | T43: SIENO | U43: Perfumaria/Colonia | V43: =IF(COUNTIF($B$2:B43,B43)=1,1,0) -> 1 | W43: =IF(COUNTIFS($B$2:B43,B43,$T$2:T43,T43)=1,1,0) -> 1
A44: Vitamina D3 60 Cápsulas Vitafor Compra G | B44: VITAFOR | C44: 45100 | D44: 900 | E44: 50.159711 | F44: Clássico | G44: Sim | H44: Sim | I44: Não | J44: Sim | K44: Não | L44: 7898665430071 | N44: 7898665430071 | P44: active | Q44: Sim | R44: Não | S44: new | T44: SIENO | U44: Suplementos/Nutricao | V44: =IF(COUNTIF($B$2:B44,B44)=1,1,0) -> 0 | W44: =IF(COUNTIFS($B$2:B44,B44,$T$2:T44,T44)=1,1,0) -> 0
A45: Fogão Cooktop Elétrico Elgin 2 Bocas Pre | B45: ELGIN | C45: 44800 | D45: 450 | E45: 99.210177 | F45: Clássico | G45: Sim | H45: Sim | I45: Sim | J45: Sim | K45: Sim | L45: 7908412515507 | N45: 7908412515507 | P45: active | Q45: Sim | R45: Não | S45: new | T45: SIENO | U45: Casa/Eletrodomesticos | V45: =IF(COUNTIF($B$2:B45,B45)=1,1,0) -> 1 | W45: =IF(COUNTIFS($B$2:B45,B45,$T$2:T45,T45)=1,1,0) -> 1
A46: Spray Revlon Uniq One De 150ml | B46: REVLON | C46: 44200 | D46: 640 | E46: 68.967223 | F46: Clássico | G46: Sim | H46: Sim | I46: Não | J46: Sim | K46: Não | L46: 8432225129778 | N46: 8432225129778 | P46: active | Q46: Sim | R46: Não | S46: new | T46: SIENO | U46: Outros/Diversos | V46: =IF(COUNTIF($B$2:B46,B46)=1,1,0) -> 1 | W46: =IF(COUNTIFS($B$2:B46,B46,$T$2:T46,T46)=1,1,0) -> 1
A47: Glaco Big 120ml - Cristalizador Vidros R | B47: SOFT99 | C47: 44000 | D47: 420 | E47: 104.99 | F47: Premium | G47: Sim | H47: Sim | I47: Sim | J47: Sim | K47: Não | L47: 22673 | N47: 4975759103158 | P47: active | Q47: Sim | R47: Não | S47: new | T47: SIENO | U47: Automotivo | V47: =IF(COUNTIF($B$2:B47,B47)=1,1,0) -> 1 | W47: =IF(COUNTIFS($B$2:B47,B47,$T$2:T47,T47)=1,1,0) -> 1
A48: Parafusadeira De Impacto 1/4 À Bateria | B48: DEWALT | C48: 43600 | D48: 60 | E48: 792 | F48: Clássico | G48: Sim | H48: Sim | I48: Sim | J48: Sim | K48: Sim | L48: 885911467629 | N48: 885911467629 | P48: paused | Q48: Sim | R48: Não | S48: new | T48: SIENO | U48: Ferramentas | V48: =IF(COUNTIF($B$2:B48,B48)=1,1,0) -> 1 | W48: =IF(COUNTIFS($B$2:B48,B48,$T$2:T48,T48)=1,1,0) -> 1
A49: Calculadora Científica 252 Funções Fx-82 | B49: CASIO | C49: 41300 | D49: 470 | E49: 88.513726 | F49: Clássico | G49: Sim | H49: Sim | I49: Sim | J49: Sim | K49: Não | L49: 4549526616860 | N49: 4549526616860 | P49: active | Q49: Sim | R49: Não | S49: new | T49: SIENO | U49: Eletronicos/Games | V49: =IF(COUNTIF($B$2:B49,B49)=1,1,0) -> 1 | W49: =IF(COUNTIFS($B$2:B49,B49,$T$2:T49,T49)=1,1,0) -> 1
A50: Martelete Perfurador E Rompedor Dewalt M | B50: DEWALT | C50: 38900 | D50: 20 | E50: 1769.9909 | F50: Premium | G50: Sim | H50: Sim | I50: Sim | J50: Sim | K50: Sim | L50: 885911606134 | N50: 885911606134 | P50: paused | Q50: Sim | R50: Não | S50: new | T50: SIENO | U50: Ferramentas | V50: =IF(COUNTIF($B$2:B50,B50)=1,1,0) -> 0 | W50: =IF(COUNTIFS($B$2:B50,B50,$T$2:T50,T50)=1,1,0) -> 0
A51: Bolsa Para Ferramentas Bosch Mini Softca | B51: BOSCH | C51: 36600 | D51: 730 | E51: 49.99 | F51: Clássico | G51: Sim | H51: Sim | I51: Não | J51: Sim | K51: Não | L51: 3165140799690 | N51: 3165140799690 | P51: active | Q51: Sim | R51: Não | S51: new | T51: SIENO | U51: Ferramentas | V51: =IF(COUNTIF($B$2:B51,B51)=1,1,0) -> 1 | W51: =IF(COUNTIFS($B$2:B51,B51,$T$2:T51,T51)=1,1,0) -> 1
A52: Perfume Masculino Homme Eau De Toilette | B52: JOOP! | C52: 35000 | D52: 150 | E52: 229.99 | F52: Clássico | G52: Sim | H52: Sim | I52: Sim | J52: Sim | K52: Não | L52: 5167 | N52: 3607345809915 | P52: active | Q52: Sim | R52: Não | S52: new | T52: SIENO | U52: Perfumaria/Colonia | V52: =IF(COUNTIF($B$2:B52,B52)=1,1,0) -> 1 | W52: =IF(COUNTIFS($B$2:B52,B52,$T$2:T52,T52)=1,1,0) -> 1
A53: Pressurizador De Água Lorenzetti Pl-20 3 | B53: LORENZETTI | C53: 34300 | D53: 30 | E53: 1070.3875 | F53: Clássico | G53: Sim | H53: Sim | I53: Sim | J53: Sim | K53: Sim | L53: 7896451842145 | N53: 7896451842145 | P53: active | Q53: Sim | R53: Não | S53: new | T53: SIENO | U53: Casa/Eletrodomesticos | V53: =IF(COUNTIF($B$2:B53,B53)=1,1,0) -> 1 | W53: =IF(COUNTIFS($B$2:B53,B53,$T$2:T53,T53)=1,1,0) -> 1
... A62: Rituária Magnésio 4mag 180 Cápsulas Sem | B62: RITUÁRIA | C62: 32500 | D62: 400 | E62: 80.620496 | F62: Clássico | G62: Sim | H62: Sim | I62: Sim | J62: Sim | K62: Não | L62: 7908407008557 | N62: 7908407008557 | P62: active | Q62: Sim | R62: Não | S62: new | T62: SIENO | U62: Suplementos/Nutricao | V62: =IF(COUNTIF($B$2:B62,B62)=1,1,0) -> 0 | W62: =IF(COUNTIFS($B$2:B62,B62,$T$2:T62,T62)=1,1,0) -> 0
A63: Controle Sony Dualsense Sem Fio White Ps | B63: PLAYSTATION | C63: 32100 | D63: 80 | E63: 401.865 | F63: Clássico | G63: Sim | H63: Sim | I63: Sim | J63: Sim | K63: Não | L63: 711719574293 | P63: active | Q63: Sim | R63: Não | S63: new | T63: SIENO | U63: Eletronicos/Games | V63: =IF(COUNTIF($B$2:B63,B63)=1,1,0) -> 1 | W63: =IF(COUNTIFS($B$2:B63,B63,$T$2:T63,T63)=1,1,0) -> 1
A64: Carretilha Black Tamba S2 12 Rolamentos | B64: MARURI | C64: 31700 | D64: 100 | E64: 334 | F64: Premium | G64: Sim | H64: Sim | I64: Sim | J64: Sim | K64: Sim | L64: 4710122017409 | N64: 4710122017409 | P64: active | Q64: Sim | R64: Não | S64: new | T64: SIENO | U64: Pesca/Nautica | V64: =IF(COUNTIF($B$2:B64,B64)=1,1,0) -> 0 | W64: =IF(COUNTIFS($B$2:B64,B64,$T$2:T64,T64)=1,1,0) -> 0
A65: Descascador De Laranjas Máquina De Desca | B65: BESTFER | C65: 31400 | D65: 320 | E65: 99 | F65: Clássico | G65: Sim | H65: Não | I65: Sim | J65: Sim | K65: Não | L65: 7899206165001 | N65: 7899206165001 | P65: active | Q65: Sim | R65: Não | S65: new | T65: SIENO | U65: Utensilios Cozinha/Jardim | V65: =IF(COUNTIF($B$2:B65,B65)=1,1,0) -> 0 | W65: =IF(COUNTIFS($B$2:B65,B65,$T$2:T65,T65)=1,1,0) -> 0
A66: Perfume Masculino Mercedes-benz Select N | B66: MERCEDES-BENZ | C66: 31200 | D66: 110 | E66: 291.27692 | F66: Clássico | G66: Sim | H66: Sim | I66: Sim | J66: Sim | K66: Não | L66: 12209 | N66: 3595471081032 | P66: paused | Q66: Sim | R66: Não | S66: new | T66: SIENO | U66: Perfumaria/Colonia | V66: =IF(COUNTIF($B$2:B66,B66)=1,1,0) -> 0 | W66: =IF(COUNTIFS($B$2:B66,B66,$T$2:T66,T66)=1,1,0) -> 0
A67: Perfume Gabriela Sabatini Feminino Edt 6 | B67: GABRIELA SABATINI | C67: 30700 | D67: 320 | E67: 97.496952 | F67: Clássico | G67: Sim | H67: Sim | I67: Sim | J67: Sim | K67: Não | L67: 5111 | N67: 8005610325507 | P67: paused | Q67: Sim | R67: Não | S67: new | T67: SIENO | U67: Perfumaria/Colonia | V67: =IF(COUNTIF($B$2:B67,B67)=1,1,0) -> 1 | W67: =IF(COUNTIFS($B$2:B67,B67,$T$2:T67,T67)=1,1,0) -> 1
A68: Carretilha Marine Brisa Ls 8000 - Drag 5 | B68: MARINE | C68: 30600 | D68: 90 | E68: 355.25581 | F68: Clássico | G68: Sim | H68: Sim | I68: Sim | J68: Sim | K68: Sim | L68: 7908137908370 | N68: 7908137908370 | P68: paused | Q68: Sim | R68: Não | S68: new | T68: SIENO | U68: Pesca/Nautica | V68: =IF(COUNTIF($B$2:B68,B68)=1,1,0) -> 1 | W68: =IF(COUNTIFS($B$2:B68,B68,$T$2:T68,T68)=1,1,0) -> 1
A69: Jacques Bogart Silver Scent Intense Edt | B69: JACQUES BOGART | C69: 29500 | D69: 100 | E69: 307.5426 | F69: Clássico | G69: Sim | H69: Sim | I69: Sim | J69: Sim | K69: Não | L69: 22137 | N69: 3355991004672 | P69: active | Q69: Sim | R69: Não | S69: new | T69: SIENO | U69: Perfumaria/Colonia | V69: =IF(COUNTIF($B$2:B69,B69)=1,1,0) -> 1 | W69: =IF(COUNTIFS($B$2:B69,B69,$T$2:T69,T69)=1,1,0) -> 1
A70: Carretilha Shimano New Tekota 800pg Dire | B70: SHIMANO | C70: 29500 | D70: 10 | E70: 2270.1846 | F70: Premium | G70: Sim | H70: Sim | I70: Sim | J70: Sim | K70: Sim | L70: 022255241779 | N70: 22255241779 | P70: active | Q70: Sim | R70: Não | S70: new | T70: SIENO | U70: Pesca/Nautica | V70: =IF(COUNTIF($B$2:B70,B70)=1,1,0) -> 0 | W70: =IF(COUNTIFS($B$2:B70,B70,$T$2:T70,T70)=1,1,0) -> 0
A71: Perfume Masculino Eudora Club 6 Exclusiv | B71: EUDORA | C71: 29500 | D71: 310 | E71: 96.071564 | F71: Clássico | G71: Sim | H71: Sim | I71: Sim | J71: Sim | K71: Não | L71: 7891033507528 | N71: 7891033507528 | P71: paused | Q71: Sim | R71: Não | S71: new | T71: SIENO | U71: Perfumaria/Colonia | V71: =IF(COUNTIF($B$2:B71,B71)=1,1,0) -> 0 | W71: =IF(COUNTIFS($B$2:B71,B71,$T$2:T71,T71)=1,1,0) -> 0
A72: Perfume Masculino Eau De Toilette Azzaro | B72: AZZARO | C72: 29400 | D72: 120 | E72: 255.56513 | F72: Clássico | G72: Sim | H72: Sim | I72: Sim | J72: Sim | K72: Sim | L72: 3351500011476 | N72: 3351500011476 | P72: active | Q72: Sim | R72: Não | S72: new | T72: SIENO | U72: Perfumaria/Colonia | V72: =IF(COUNTIF($B$2:B72,B72)=1,1,0) -> 1 | W72: =IF(COUNTIFS($B$2:B72,B72,$T$2:T72,T72)=1,1,0) -> 1
A73: Pneu Mtb Chaoyang Phantom Wet Aro 29x2.2 | B73: CHAOYANG | C73: 29300 | D73: 210 | E73: 140.80538 | F73: Clássico | G73: Sim | H73: Sim | I73: Sim | J73: Sim | K73: Sim | L73: 6938112688509 | N73: 6.9381127e+25 | P73: active | Q73: Sim | R73: Não | S73: new | T73: SIENO | U73: Bike/Ciclismo | V73: =IF(COUNTIF($B$2:B73,B73)=1,1,0) -> 1 | W73: =IF(COUNTIFS($B$2:B73,B73,$T$2:T73,T73)=1,1,0) -> 1
A74: Carretel Carretilha Shimano Slx Slx151xg | B74: SHIMANO | C74: 28900 | D74: 40 | E74: 801.62889 | F74: Clássico | G74: Sim | H74: Sim | I74: Sim | J74: Sim | K74: Não | L74: 7794290341679 | P74: active | Q74: Sim | R74: Não | S74: new | T74: SIENO | U74: Pesca/Nautica | V74: =IF(COUNTIF($B$2:B74,B74)=1,1,0) -> 0 | W74: =IF(COUNTIFS($B$2:B74,B74,$T$2:T74,T74)=1,1,0) -> 0
A75: Jacques Bogart Silver Scent Eau De Toile | B75: JACQUES BOGART | C75: 28900 | D75: 100 | E75: 282.88431 | F75: Clássico | G75: Sim | H75: Não | I75: Sim | J75: Sim | K75: Sim | L75: 19419 | N75: 3355991004665 | P75: paused | Q75: Sim | R75: Não | S75: new | T75: SIENO | U75: Perfumaria/Colonia | V75: =IF(COUNTIF($B$2:B75,B75)=1,1,0) -> 0 | W75: =IF(COUNTIFS($B$2:B75,B75,$T$2:T75,T75)=1,1,0) -> 0
A76: Parafusadeira A Bateria 3,6v C/ Estojo E | B76: WESCO | C76: 28300 | D76: 170 | E76: 170.69247 | F76: Clássico | G76: Sim | H76: Sim | I76: Sim | J76: Sim | K76: Não | L76: 6943475888671 | N76: 6943475888671 | P76: active | Q76: Sim | R76: Não | S76: new | T76: SIENO | U76: Ferramentas | V76: =IF(COUNTIF($B$2:B76,B76)=1,1,0) -> 1 | W76: =IF(COUNTIFS($B$2:B76,B76,$T$2:T76,T76)=1,1,0) -> 1
A77: Calculadora Científica Casio Fx-82ms 2nd | B77: CASIO | C77: 28000 | D77: 500 | E77: 55.654215 | F77: Clássico | G77: Sim | H77: Sim | I77: Não | J77: Sim | K77: Não | L77: 4549526616884 | N77: 4549526616884 | P77: active | Q77: Sim | R77: Não | S77: new | T77: SIENO | U77: Eletronicos/Games | V77: =IF(COUNTIF($B$2:B77,B77)=1,1,0) -> 0 | W77: =IF(COUNTIFS($B$2:B77,B77,$T$2:T77,T77)=1,1,0) -> 0
A78: Canivete Tático Invictus Phanton Black A | B78: INVICTUS | C78: 27700 | D78: 160 | E78: 178.6871 | F78: Premium | G78: Sim | H78: Sim | I78: Sim | J78: Sim | K78: Não | L78: 7908005385913 | N78: 7908005385913 | P78: active | Q78: Sim | R78: Não | S78: new | T78: SIENO | U78: Tatico/Outdoor | V78: =IF(COUNTIF($B$2:B78,B78)=1,1,0) -> 1 | W78: =IF(COUNTIFS($B$2:B78,B78,$T$2:T78,T78)=1,1,0) -> 1
A79: Mavala Stop Parar De Roer Unha 10ml Tran | B79: MAVALA | C79: 27600 | D79: 280 | E79: 97.549576 | F79: Clássico | G79: Sim | H79: Sim | I79: Sim | J79: Sim | K79: Não | L79: 5646 | N79: 7618900903081 | P79: active | Q79: Sim | R79: Não | S79: new | T79: SIENO | U79: Cosmeticos/Skincare | V79: =IF(COUNTIF($B$2:B79,B79)=1,1,0) -> 1 | W79: =IF(COUNTIFS($B$2:B79,B79,$T$2:T79,T79)=1,1,0) -> 1
A80: Perfume Feminino Euphoria Eau De Parfum | B80: CALVIN KLEIN | C80: 27300 | D80: 70 | E80: 408.1209 | F80: Clássico | G80: Sim | H80: Sim | I80: Sim | J80: Sim | K80: Não | L80: 88300162505 | N80: 88300162505 | P80: active | Q80: Sim | R80: Não | S80: new | T80: SIENO | U80: Perfumaria/Colonia | V80: =IF(COUNTIF($B$2:B80,B80)=1,1,0) -> 1 | W80: =IF(COUNTIFS($B$2:B80,B80,$T$2:T80,T80)=1,1,0) -> 1
A81: Perfume Cuba Gold Masculino 100ml | B81: CUBA PARIS | C81: 27200 | D81: 460 | E81: 58.939502 | F81: Clássico | G81: Sim | H81: Sim | I81: Não | J81: Sim | K81: Não | L81: 5425017732389 | N81: 5425017732389 | P81: active | Q81: Sim | R81: Não | S81: new | T81: SIENO | U81: Perfumaria/Colonia | V81: =IF(COUNTIF($B$2:B81,B81)=1,1,0) -> 1 | W81: =IF(COUNTIFS($B$2:B81,B81,$T$2:T81,T81)=1,1,0) -> 1
A82: Protetor Solar Clareador Manchas Biosole | B82: ADA TINA ITALY | C82: 26600 | D82: 190 | E82: 139.99 | F82: Clássico | G82: Sim | H82: Sim | I82: Sim | J82: Sim | K82: Não | L82: 21838 | N82: 7.8967685e+25 | P82: active | Q82: Sim | R82: Não | S82: new | T82: SIENO | U82: Cosmeticos/Skincare | V82: =IF(COUNTIF($B$2:B82,B82)=1,1,0) -> 1 | W82: =IF(COUNTIFS($B$2:B82,B82,$T$2:T82,T82)=1,1,0) -> 1
A83: Burberry Goddess Perfume Feminino Edp 10 | B83: BURBERRY | C83: 26600 | D83: 50 | E83: 577.195 | F83: Clássico | G83: Sim | H83: Sim | I83: Sim | J83: Sim | K83: Sim | L83: 3616302020652 | N83: 3616302020652 | P83: paused | Q83: Sim | R83: Não | S83: new | T83: SIENO | U83: Perfumaria/Colonia | V83: =IF(COUNTIF($B$2:B83,B83)=1,1,0) -> 1 | W83: =IF(COUNTIFS($B$2:B83,B83,$T$2:T83,T83)=1,1,0) -> 1
A84: Pressurizador Mini Bomba Komeco Tp 40 Br | B84: KOMECO | C84: 26100 | D84: 70 | E84: 353.11284 | F84: Clássico | G84: Sim | H84: Sim | I84: Sim | J84: Sim | K84: Não | L84: 7896873179881 | N84: 7896873179881 | P84: active | Q84: Sim | R84: Não | S84: new | T84: SIENO | U84: Casa/Eletrodomesticos | V84: =IF(COUNTIF($B$2:B84,B84)=1,1,0) -> 0 | W84: =IF(COUNTIFS($B$2:B84,B84,$T$2:T84,T84)=1,1,0) -> 0
A85: Carretilha Maruri Avante Bg By Denis Gar | B85: MARURI | C85: 25700 | D85: 60 | E85: 435.56 | F85: Clássico | G85: Sim | H85: Sim | I85: Sim | J85: Sim | K85: Sim | L85: 4710122008117 | N85: 4710122008117 | P85: active | Q85: Sim | R85: Não | S85: new | T85: SIENO | U85: Pesca/Nautica | V85: =IF(COUNTIF($B$2:B85,B85)=1,1,0) -> 0 | W85: =IF(COUNTIFS($B$2:B85,B85,$T$2:T85,T85)=1,1,0) -> 0
A86: Perfume Árabe Masculino French Avenue Li | B86: FRENCH AVENUE | C86: 25600 | D86: 90 | E86: 297.42919 | F86: Clássico | G86: Sim | H86: Sim | I86: Sim | J86: Sim | K86: Sim | L86: 6290360375694 | N86: 6290360375694 | P86: paused | Q86: Sim | R86: Não | S86: new | T86: SIENO | U86: Perfumaria/Colonia | V86: =IF(COUNTIF($B$2:B86,B86)=1,1,0) -> 1 | W86: =IF(COUNTIFS($B$2:B86,B86,$T$2:T86,T86)=1,1,0) -> 1
... A92: Fita Para Teste De Glicose Code Free G-4 | B92: BIOLAND | C92: 23600 | D92: 740 | E92: 32.095415 | F92: Clássico | G92: Sim | H92: Sim | I92: Não | J92: Sim | K92: Não | L92: 6939184632414 | N92: 6.9391846e+25 | P92: active | Q92: Sim | R92: Não | S92: new | T92: SIENO | U92: Saude/Bem-estar | V92: =IF(COUNTIF($B$2:B92,B92)=1,1,0) -> 1 | W92: =IF(COUNTIFS($B$2:B92,B92,$T$2:T92,T92)=1,1,0) -> 1
A93: Parafusadeira De Impacto 1/4'' Atomic Br | B93: DEWALT | C93: 23400 | D93: 30 | E93: 899 | F93: Clássico | G93: Sim | H93: Sim | I93: Sim | J93: Sim | K93: Sim | L93: 885911912204 | P93: paused | Q93: Sim | R93: Não | S93: new | T93: SIENO | U93: Ferramentas | V93: =IF(COUNTIF($B$2:B93,B93)=1,1,0) -> 0 | W93: =IF(COUNTIFS($B$2:B93,B93,$T$2:T93,T93)=1,1,0) -> 0
A94: Guardian® 8,5g 30 Sachês Em Pó Central N | B94: CENTRAL NUTRITION | C94: 23200 | D94: 100 | E94: 220.94 | F94: Clássico | G94: Sim | H94: Sim | I94: Sim | J94: Sim | K94: Não | L94: 7898962163504 | N94: 7898962163504 | P94: active | Q94: Sim | R94: Não | S94: new | T94: SIENO | U94: Suplementos/Nutricao | V94: =IF(COUNTIF($B$2:B94,B94)=1,1,0) -> 0 | W94: =IF(COUNTIFS($B$2:B94,B94,$T$2:T94,T94)=1,1,0) -> 0
A95: Inalador E Neb G-tech Nebmesh2 Adulto E | B95: G-TECH | C95: 22900 | D95: 150 | E95: 149.99 | F95: Clássico | G95: Sim | H95: Sim | I95: Sim | J95: Sim | K95: Não | L95: 15336 | N95: 7898639692856 | P95: active | Q95: Sim | R95: Não | S95: new | T95: SIENO | U95: Saude/Bem-estar | V95: =IF(COUNTIF($B$2:B95,B95)=1,1,0) -> 0 | W95: =IF(COUNTIFS($B$2:B95,B95,$T$2:T95,T95)=1,1,0) -> 0
A96: Chá Funcional Desinchá Dia Original 60 S | B96: DESINCHÁ | C96: 22700 | D96: 490 | E96: 46.35549 | F96: Clássico | G96: Sim | H96: Sim | I96: Não | J96: Sim | K96: Não | L96: 16455 | N96: 7899592821017 | P96: active | Q96: Sim | R96: Não | S96: new | T96: SIENO | U96: Suplementos/Nutricao | V96: =IF(COUNTIF($B$2:B96,B96)=1,1,0) -> 1 | W96: =IF(COUNTIFS($B$2:B96,B96,$T$2:T96,T96)=1,1,0) -> 1
A97: Perfume Masculino Azzaro Forever Wanted | B97: AZZARO | C97: 22300 | D97: 40 | E97: 620.22972 | F97: Clássico | G97: Sim | H97: Sim | I97: Sim | J97: Sim | K97: Não | L97: 3614274258073 | N97: 3614274258073 | P97: paused | Q97: Sim | R97: Não | S97: new | T97: SIENO | U97: Perfumaria/Colonia | V97: =IF(COUNTIF($B$2:B97,B97)=1,1,0) -> 0 | W97: =IF(COUNTIFS($B$2:B97,B97,$T$2:T97,T97)=1,1,0) -> 0
A98: Carretilha Avenger 11000 Marine Sports V | B98: MARINE | C98: 22000 | D98: 60 | E98: 349.43889 | F98: Clássico | G98: Sim | H98: Sim | I98: Sim | J98: Sim | K98: Não | L98: 7908137911493 | P98: active | Q98: Sim | R98: Não | S98: new | T98: SIENO | U98: Pesca/Nautica | V98: =IF(COUNTIF($B$2:B98,B98)=1,1,0) -> 0 | W98: =IF(COUNTIFS($B$2:B98,B98,$T$2:T98,T98)=1,1,0) -> 0
A99: Tend Skin Solution Líquido 236ml Loção P | B99: TEND SKIN | C99: 22000 | D99: 100 | E99: 231.33158 | F99: Premium | G99: Sim | H99: Sim | I99: Sim | J99: Sim | K99: Sim | L99: 9866 | N99: 6.07575e+23 | P99: active | Q99: Sim | R99: Não | S99: new | T99: SIENO | U99: Outros/Diversos | V99: =IF(COUNTIF($B$2:B99,B99)=1,1,0) -> 1 | W99: =IF(COUNTIFS($B$2:B99,B99,$T$2:T99,T99)=1,1,0) -> 1
A100: Omegafor Family 120 Cápsulas Vitafor Sem | B100: VITAFOR | C100: 22000 | D100: 220 | E100: 97.572222 | F100: Clássico | G100: Sim | H100: Sim | I100: Sim | J100: Sim | K100: Não | L100: 7898665431320 | N100: 7898665431320 | P100: active | Q100: Sim | R100: Não | S100: new | T100: SIENO | U100: Suplementos/Nutricao | V100: =IF(COUNTIF($B$2:B100,B100)=1,1,0) -> 0 | W100: =IF(COUNTIFS($B$2:B100,B100,$T$2:T100,T100)=1,1,0) -> 0
A101: Tesoura De Poda Profissional Com Lâmina | B101: TRAMONTINA | C101: 21900 | D101: 260 | E101: 85.125837 | F101: Clássico | G101: Sim | H101: Sim | I101: Sim | J101: Sim | K101: Não | L101: 7891117064190 | N101: 7891117064190 | P101: active | Q101: Sim | R101: Não | S101: new | T101: SIENO | U101: Utensilios Cozinha/Jardim | V101: =IF(COUNTIF($B$2:B101,B101)=1,1,0) -> 1 | W101: =IF(COUNTIFS($B$2:B101,B101,$T$2:T101,T101)=1,1,0) -> 1
A102: Aparelho De Pressão Digital De Pulso Pre | B102: PREMIUM | C102: 21500 | D102: 300 | E102: 72.746814 | F102: Clássico | G102: Sim | H102: Sim | I102: Não | J102: Sim | K102: Sim | L102: 11785 | N102: 7898639690524 | P102: active | Q102: Sim | R102: Não | S102: new | T102: SIENO | U102: Saude/Bem-estar | V102: =IF(COUNTIF($B$2:B102,B102)=1,1,0) -> 0 | W102: =IF(COUNTIFS($B$2:B102,B102,$T$2:T102,T102)=1,1,0) -> 0
A103: Cool Water Davidoff Eau De Toilette - Pe | B103: DAVIDOFF | C103: 21400 | D103: 120 | E103: 184.47276 | F103: Clássico | G103: Sim | H103: Sim | I103: Sim | J103: Sim | K103: Não | L103: 4793 | N103: 3414202000572 | P103: active | Q103: Sim | R103: Não | S103: new | T103: SIENO | U103: Perfumaria/Colonia | V103: =IF(COUNTIF($B$2:B103,B103)=1,1,0) -> 1 | W103: =IF(COUNTIFS($B$2:B103,B103,$T$2:T103,T103)=1,1,0) -> 1
A104: Mini Otoscópio Luz De Led C/ Espéculos M | B104: MIKATOS | C104: 20800 | D104: 100 | E104: 200.32221 | F104: Clássico | G104: Sim | H104: Sim | I104: Sim | J104: Sim | K104: Sim | L104: 7899524418872 | N104: 7899524418872 | P104: active | Q104: Sim | R104: Não | S104: new | T104: SIENO | U104: Saude/Bem-estar | V104: =IF(COUNTIF($B$2:B104,B104)=1,1,0) -> 1 | W104: =IF(COUNTIFS($B$2:B104,B104,$T$2:T104,T104)=1,1,0) -> 1
A105: Perfume Manasik Lilac 100ml Eau De Parfu | B105: MANASIK | C105: 20800 | D105: 230 | E105: 89.390687 | F105: Clássico | G105: Sim | H105: Sim | I105: Sim | J105: Sim | K105: Não | L105: 8439627624306 | N105: 8439627624306 | P105: active | Q105: Sim | R105: Não | S105: new | T105: SIENO | U105: Perfumaria/Colonia | V105: =IF(COUNTIF($B$2:B105,B105)=1,1,0) -> 1 | W105: =IF(COUNTIFS($B$2:B105,B105,$T$2:T105,T105)=1,1,0) -> 1
A106: Carretilha Pesca Maruri Black Tamba Pro | B106: MARURI | C106: 20000 | D106: 70 | E106: 302.55288 | F106: Clássico | G106: Sim | H106: Sim | I106: Sim | J106: Sim | K106: Sim | L106: 4710206002215 | N106: 4710206002215 | P106: active | Q106: Sim | R106: Não | S106: new | T106: SIENO | U106: Pesca/Nautica | V106: =IF(COUNTIF($B$2:B106,B106)=1,1,0) -> 0 | W106: =IF(COUNTIFS($B$2:B106,B106,$T$2:T106,T106)=1,1,0) -> 0
A107: Marine Sports Arena 4000fd Prateado Dire | B107: MARINE SPORTS | C107: 19900 | D107: 340 | E107: 57.63658 | F107: Clássico | G107: Sim | H107: Sim | I107: Não | J107: Sim | K107: Não | L107: 7908137907168 | N107: 7908137907168 | P107: active | Q107: Sim | R107: Não | S107: new | T107: SIENO | U107: Outros/Diversos | V107: =IF(COUNTIF($B$2:B107,B107)=1,1,0) -> 0 | W107: =IF(COUNTIFS($B$2:B107,B107,$T$2:T107,T107)=1,1,0) -> 0
A108: Colchao Mor Camping Casa Multi Casal Com | B108: MOR | C108: 19400 | D108: 150 | E108: 132.6026 | F108: Clássico | G108: Sim | H108: Sim | I108: Sim | J108: Sim | K108: Sim | L108: 7898706990236 | N108: 7898706990236 | P108: active | Q108: Sim | R108: Não | S108: new | T108: SIENO | U108: Casa/Eletrodomesticos | V108: =IF(COUNTIF($B$2:B108,B108)=1,1,0) -> 1 | W108: =IF(COUNTIFS($B$2:B108,B108,$T$2:T108,T108)=1,1,0) -> 1
A109: Ciclo Body Splash Feminino Nah Cardoso H | B109: CICLO | C109: 19300 | D109: 480 | E109: 40.173534 | F109: Clássico | G109: Sim | H109: Sim | I109: Não | J109: Sim | K109: Não | L109: 7898410311808 | N109: 7898410311808 | P109: active | Q109: Sim | R109: Não | S109: new | T109: SIENO | U109: Perfumaria/Colonia | V109: =IF(COUNTIF($B$2:B109,B109)=1,1,0) -> 0 | W109: =IF(COUNTIFS($B$2:B109,B109,$T$2:T109,T109)=1,1,0) -> 0
A110: Fonte Atx 200w Real Fortrek Pws-2003 Biv | B110: FORTREK | C110: 19100 | D110: 410 | E110: 46.838824 | F110: Clássico | G110: Sim | H110: Sim | I110: Não | J110: Sim | K110: Não | L110: 7898554605528 | N110: 7898554605528 | P110: paused | Q110: Sim | R110: Não | S110: new | T110: SIENO | U110: Eletronicos/Games | V110: =IF(COUNTIF($B$2:B110,B110)=1,1,0) -> 1 | W110: =IF(COUNTIFS($B$2:B110,B110,$T$2:T110,T110)=1,1,0) -> 1
... A112: Pomada Para Cuidado Dos Seios Com Lanoli | B112: LANSINOH | C112: 18800 | D112: 170 | E112: 107.95345 | F112: Clássico | G112: Sim | H112: Sim | I112: Não | J112: Sim | K112: Sim | L112: 742832706285 | N112: 742832706285 | P112: active | Q112: Sim | R112: Não | S112: new | T112: SIENO | U112: Outros/Diversos | V112: =IF(COUNTIF($B$2:B112,B112)=1,1,0) -> 1 | W112: =IF(COUNTIFS($B$2:B112,B112,$T$2:T112,T112)=1,1,0) -> 1
A113: Base Líquida Bt Skin L30 40ml Bruna Tava | B113: BRUNA TAVARES | C113: 18600 | D113: 210 | E113: 89.82913 | F113: Clássico | G113: Sim | H113: Sim | I113: Sim | J113: Sim | K113: Não | L113: 7908985912314 | P113: paused | Q113: Sim | R113: Não | S113: new | T113: SIENO | U113: Cosmeticos/Skincare | V113: =IF(COUNTIF($B$2:B113,B113)=1,1,0) -> 1 | W113: =IF(COUNTIFS($B$2:B113,B113,$T$2:T113,T113)=1,1,0) -> 1
A114: Perfume Masculino Attar Árabe Al Wesal W | B114: AL WATANIAH | C114: 18500 | D114: 120 | E114: 159.85371 | F114: Clássico | G114: Sim | H114: Sim | I114: Sim | J114: Sim | K114: Não | L114: 18344 | N114: 5055810014933 | P114: paused | Q114: Sim | R114: Não | S114: new | T114: SIENO | U114: Perfumaria/Colonia | V114: =IF(COUNTIF($B$2:B114,B114)=1,1,0) -> 1 | W114: =IF(COUNTIFS($B$2:B114,B114,$T$2:T114,T114)=1,1,0) -> 1
...
