Workbook

Sheet Resumo Executivo
B2: Priorização de Entrada em Perfumaria — Top 100 Marcas (Nubmetrics, ago/2026)
B3: Categorias MLB1246 / MLB6284 no Mercado Livre · dados reais de vendas extraídos pelo Nubmetrics
B5: Marcas analisadas | C5: 100
B6: Vendas somadas (top 100 marcas) | C6: =SUM(Dados!F2:F101) -> 193562500
B7: Unidades vendidas (top 100 marcas) | C7: =SUM(Dados!G2:G101) -> 1165718
B8: Marcas do seu mix de nicho já nesta lista | C8: =COUNTIF(Dados!D2:D101,"Sim") -> 3
B10: Achado principal: seu mix de nicho já é validado pelos dados
B11: XERJOFF, NISHANE e PARFUMS DE MARLY — as 3 marcas de nicho que você já definiu para a perfumaria — aparecem no top 100 do Mercado Livre com Saturação Baixa e Tendência Crescendo, e ticket médio entre R$1.500 e R$2.300 por unidade (muito acima da média do mercado, que fica na faixa de R$50-150). Poucos vendedores disputando (28-52), demanda comprovada e posicionamento de alta perfumaria: é exatamente o perfil de 'maior lucro e mais requinte' que você quer, e os dados confirmam que ainda há espaço pra entrar sem brigar de preço com 500 vendedores. SOSPIRO e CREED (mesma faixa de nicho) mostram o mesmo padrão, caso queira ampliar o mix.
B13: Como o modelo de pontuação funciona
B14: Pontuação 0-100 combinando 4 fatores, com pesos que você pode ajustar na aba "Priorização de Entrada" (célula amarela): ticket médio (proxy de lucro/requinte — 35%), poucos vendedores concorrendo (facilidade de entrada com capital de giro limitado — 25%), saturação baixa (espaço de mercado — 20%) e tendência de crescimento — 20%). Não é uma medida de margem real (não temos custo de aquisição nem frete) — é um proxy para ordenar por onde vale mais a pena negociar primeiro.
B16: Ondas de entrada sugeridas (pensando no seu capital de giro)
B17: • | C17: Onda 1 (as 12 melhor pontuadas): negociar/testar primeiro — melhor combinação de ticket alto, pouca concorrência e crescimento. Investimento menor por SKU testado, retorno relativo maior.
B18: • | C18: Onda 2 (próximas 28): fila de espera — bons candidatos, mas com mais concorrência ou ticket mais baixo. Entrar depois que o caixa das primeiras marcas already girar.
B19: • | C19: Onda 3 (as 60 restantes): marcas grandes/saturadas (ex: Natura, O Boticário) ou de menor ticket — exigem mais capital ou brigam mais no preço. Deixar para quando já tiver capital de giro mais folgado.
B21: Como usar este relatório
B22: • | C22: Aba "Priorização de Entrada": a lista pronta, já ordenada pela pontuação, com a onda sugerida na primeira coluna. Linhas verdes = Onda 1. Linhas roxas = já está no seu mix de nicho.
B23: • | C23: Aba "Dados": os 100 registros do Nubmetrics, convertidos para número (Vendas, Unidades, % Catálogo), com a coluna "Posicionamento" — minha classificação de cada marca (Nacional/Massa, Árabe/Import Acessível, Designer/Importado, Alta Perfumaria/Nicho). Marcas que eu não conhecia bem ficaram como "A verificar" — não chutei.
B24: • | C24: Pesos ajustáveis: mude as células amarelas no topo de "Priorização de Entrada" pra dar mais ou menos peso a cada fator — tudo recalcula sozinho.
B26: Limitações
B27: • | C27: Isso é ranking de vendas e concorrência no Mercado Livre — não é sua margem real. Custo de aquisição, frete, imposto e MOQ do fornecedor de cada marca não estão aqui e mudam a conta.
B28: • | C28: "Posicionamento" é minha classificação por conhecimento geral do mercado de perfumaria, não um dado do Nubmetrics — trate como ponto de partida, não como verdade absoluta, principalmente nas marcas marcadas "A verificar".
B29: • | C29: "Ranking de demanda" (coluna da aba Dados) é outra métrica do Nubmetrics que não incorporei na pontuação por não ter certeza da metodologia exata (maioria das marcas aparece como 0) — vale conferir direto na plataforma antes de usar.
B30: • | C30: Retrato de agosto/2026 — sazonalidade (datas comemorativas, por exemplo) pode alterar bastante esse ranking em outros meses.

Sheet Priorização de Entrada
A1: Pesos do modelo (ajuste livremente — a pontuação recalcula sozinha)
A3: Peso: Ticket médio (proxy de lucro/requinte) | B3: 0.35
A4: Peso: Poucos vendedores (facilidade/capital de entrada) | B4: 0.25
A5: Peso: Saturação baixa (espaço de mercado) | B5: 0.2
A6: Peso: Tendência de crescimento | B6: 0.2
A7: Soma dos pesos (deve ser 100%) | B7: =SUM(B3:B6) -> 1
A9: Onda de Entrada | B9: Marca | C9: Posicionamento | D9: Já no seu mix? | E9: Pontuação (0-100) | F9: Ticket Médio (R$) | G9: Nº Vendedores | H9: Saturação | I9: Tendência | J9: Vendas (R$) | K9: Unidades Vendidas | L9: % Catálogo
A10: =IF(1<=12,"Onda 1 — testar agora",IF(1<=40,"Onda 2 — próximos passos","Onda 3 — depois de consolidar")) -> Onda 1 — testar agora | B10: =INDEX(Dados!$B:$B,MATCH(1,Dados!$O:$O,0)) -> CREED | C10: =INDEX(Dados!$C:$C,MATCH(1,Dados!$O:$O,0)) -> Alta Perfumaria/Nicho | D10: =INDEX(Dados!$D:$D,MATCH(1,Dados!$O:$O,0)) -> Não | E10: =INDEX(Dados!$N:$N,MATCH(1,Dados!$O:$O,0)) -> 98.883627 | F10: =INDEX(Dados!$H:$H,MATCH(1,Dados!$O:$O,0)) -> 2290.7407 | G10: =INDEX(Dados!$K:$K,MATCH(1,Dados!$O:$O,0)) -> 33 | H10: =INDEX(Dados!$L:$L,MATCH(1,Dados!$O:$O,0)) -> Baixa | I10: =INDEX(Dados!$I:$I,MATCH(1,Dados!$O:$O,0)) -> Crescendo | J10: =INDEX(Dados!$F:$F,MATCH(1,Dados!$O:$O,0)) -> 371100 | K10: =INDEX(Dados!$G:$G,MATCH(1,Dados!$O:$O,0)) -> 162 | L10: =INDEX(Dados!$J:$J,MATCH(1,Dados!$O:$O,0)) -> 0.7324
A11: =IF(2<=12,"Onda 1 — testar agora",IF(2<=40,"Onda 2 — próximos passos","Onda 3 — depois de consolidar")) -> Onda 1 — testar agora | B11: =INDEX(Dados!$B:$B,MATCH(2,Dados!$O:$O,0)) -> PARFUMS DE MARLY | C11: =INDEX(Dados!$C:$C,MATCH(2,Dados!$O:$O,0)) -> Alta Perfumaria/Nicho | D11: =INDEX(Dados!$D:$D,MATCH(2,Dados!$O:$O,0)) -> Sim | E11: =INDEX(Dados!$N:$N,MATCH(2,Dados!$O:$O,0)) -> 94.224929 | F11: =INDEX(Dados!$H:$H,MATCH(2,Dados!$O:$O,0)) -> 1976.9737 | G11: =INDEX(Dados!$K:$K,MATCH(2,Dados!$O:$O,0)) -> 29 | H11: =INDEX(Dados!$L:$L,MATCH(2,Dados!$O:$O,0)) -> Baixa | I11: =INDEX(Dados!$I:$I,MATCH(2,Dados!$O:$O,0)) -> Crescendo | J11: =INDEX(Dados!$F:$F,MATCH(2,Dados!$O:$O,0)) -> 300500 | K11: =INDEX(Dados!$G:$G,MATCH(2,Dados!$O:$O,0)) -> 152 | L11: =INDEX(Dados!$J:$J,MATCH(2,Dados!$O:$O,0)) -> 0.7123
A12: =IF(3<=12,"Onda 1 — testar agora",IF(3<=40,"Onda 2 — próximos passos","Onda 3 — depois de consolidar")) -> Onda 1 — testar agora | B12: =INDEX(Dados!$B:$B,MATCH(3,Dados!$O:$O,0)) -> NISHANE | C12: =INDEX(Dados!$C:$C,MATCH(3,Dados!$O:$O,0)) -> Alta Perfumaria/Nicho | D12: =INDEX(Dados!$D:$D,MATCH(3,Dados!$O:$O,0)) -> Sim | E12: =INDEX(Dados!$N:$N,MATCH(3,Dados!$O:$O,0)) -> 91.353946 | F12: =INDEX(Dados!$H:$H,MATCH(3,Dados!$O:$O,0)) -> 1786.8545 | G12: =INDEX(Dados!$K:$K,MATCH(3,Dados!$O:$O,0)) -> 28 | H12: =INDEX(Dados!$L:$L,MATCH(3,Dados!$O:$O,0)) -> Baixa | I12: =INDEX(Dados!$I:$I,MATCH(3,Dados!$O:$O,0)) -> Crescendo | J12: =INDEX(Dados!$F:$F,MATCH(3,Dados!$O:$O,0)) -> 380600 | K12: =INDEX(Dados!$G:$G,MATCH(3,Dados!$O:$O,0)) -> 213 | L12: =INDEX(Dados!$J:$J,MATCH(3,Dados!$O:$O,0)) -> 0.7377
A13: =IF(4<=12,"Onda 1 — testar agora",IF(4<=40,"Onda 2 — próximos passos","Onda 3 — depois de consolidar")) -> Onda 1 — testar agora | B13: =INDEX(Dados!$B:$B,MATCH(4,Dados!$O:$O,0)) -> XERJOFF | C13: =INDEX(Dados!$C:$C,MATCH(4,Dados!$O:$O,0)) -> Alta Perfumaria/Nicho | D13: =INDEX(Dados!$D:$D,MATCH(4,Dados!$O:$O,0)) -> Sim | E13: =INDEX(Dados!$N:$N,MATCH(4,Dados!$O:$O,0)) -> 76.838621 | F13: =INDEX(Dados!$H:$H,MATCH(4,Dados!$O:$O,0)) -> 1544.4668 | G13: =INDEX(Dados!$K:$K,MATCH(4,Dados!$O:$O,0)) -> 52 | H13: =INDEX(Dados!$L:$L,MATCH(4,Dados!$O:$O,0)) -> Média | I13: =INDEX(Dados!$I:$I,MATCH(4,Dados!$O:$O,0)) -> Crescendo | J13: =INDEX(Dados!$F:$F,MATCH(4,Dados!$O:$O,0)) -> 767600 | K13: =INDEX(Dados!$G:$G,MATCH(4,Dados!$O:$O,0)) -> 497 | L13: =INDEX(Dados!$J:$J,MATCH(4,Dados!$O:$O,0)) -> 0.7483
A14: =IF(5<=12,"Onda 1 — testar agora",IF(5<=40,"Onda 2 — próximos passos","Onda 3 — depois de consolidar")) -> Onda 1 — testar agora | B14: =INDEX(Dados!$B:$B,MATCH(5,Dados!$O:$O,0)) -> SOSPIRO | C14: =INDEX(Dados!$C:$C,MATCH(5,Dados!$O:$O,0)) -> Alta Perfumaria/Nicho | D14: =INDEX(Dados!$D:$D,MATCH(5,Dados!$O:$O,0)) -> Não | E14: =INDEX(Dados!$N:$N,MATCH(5,Dados!$O:$O,0)) -> 75.120981 | F14: =INDEX(Dados!$H:$H,MATCH(5,Dados!$O:$O,0)) -> 1396.6216 | G14: =INDEX(Dados!$K:$K,MATCH(5,Dados!$O:$O,0)) -> 36 | H14: =INDEX(Dados!$L:$L,MATCH(5,Dados!$O:$O,0)) -> Média | I14: =INDEX(Dados!$I:$I,MATCH(5,Dados!$O:$O,0)) -> Crescendo | J14: =INDEX(Dados!$F:$F,MATCH(5,Dados!$O:$O,0)) -> 826800 | K14: =INDEX(Dados!$G:$G,MATCH(5,Dados!$O:$O,0)) -> 592 | L14: =INDEX(Dados!$J:$J,MATCH(5,Dados!$O:$O,0)) -> 0.6364
A15: =IF(6<=12,"Onda 1 — testar agora",IF(6<=40,"Onda 2 — próximos passos","Onda 3 — depois de consolidar")) -> Onda 1 — testar agora | B15: =INDEX(Dados!$B:$B,MATCH(6,Dados!$O:$O,0)) -> MAISON ASRAR | C15: =INDEX(Dados!$C:$C,MATCH(6,Dados!$O:$O,0)) -> Árabe/Import Acessível | D15: =INDEX(Dados!$D:$D,MATCH(6,Dados!$O:$O,0)) -> Não | E15: =INDEX(Dados!$N:$N,MATCH(6,Dados!$O:$O,0)) -> 68.797449 | F15: =INDEX(Dados!$H:$H,MATCH(6,Dados!$O:$O,0)) -> 385.81818 | G15: =INDEX(Dados!$K:$K,MATCH(6,Dados!$O:$O,0)) -> 62 | H15: =INDEX(Dados!$L:$L,MATCH(6,Dados!$O:$O,0)) -> Baixa | I15: =INDEX(Dados!$I:$I,MATCH(6,Dados!$O:$O,0)) -> Crescendo | J15: =INDEX(Dados!$F:$F,MATCH(6,Dados!$O:$O,0)) -> 424400 | K15: =INDEX(Dados!$G:$G,MATCH(6,Dados!$O:$O,0)) -> 1100 | L15: =INDEX(Dados!$J:$J,MATCH(6,Dados!$O:$O,0)) -> 0.7066
A16: =IF(7<=12,"Onda 1 — testar agora",IF(7<=40,"Onda 2 — próximos passos","Onda 3 — depois de consolidar")) -> Onda 1 — testar agora | B16: =INDEX(Dados!$B:$B,MATCH(7,Dados!$O:$O,0)) -> IN THE BOX | C16: =INDEX(Dados!$C:$C,MATCH(7,Dados!$O:$O,0)) -> A verificar | D16: =INDEX(Dados!$D:$D,MATCH(7,Dados!$O:$O,0)) -> Não | E16: =INDEX(Dados!$N:$N,MATCH(7,Dados!$O:$O,0)) -> 68.263049 | F16: =INDEX(Dados!$H:$H,MATCH(7,Dados!$O:$O,0)) -> 224.63636 | G16: =INDEX(Dados!$K:$K,MATCH(7,Dados!$O:$O,0)) -> 5 | H16: =INDEX(Dados!$L:$L,MATCH(7,Dados!$O:$O,0)) -> Baixa | I16: =INDEX(Dados!$I:$I,MATCH(7,Dados!$O:$O,0)) -> Crescendo | J16: =INDEX(Dados!$F:$F,MATCH(7,Dados!$O:$O,0)) -> 247100 | K16: =INDEX(Dados!$G:$G,MATCH(7,Dados!$O:$O,0)) -> 1100 | L16: =INDEX(Dados!$J:$J,MATCH(7,Dados!$O:$O,0)) -> 0.2176
A17: =IF(8<=12,"Onda 1 — testar agora",IF(8<=40,"Onda 2 — próximos passos","Onda 3 — depois de consolidar")) -> Onda 1 — testar agora | B17: =INDEX(Dados!$B:$B,MATCH(8,Dados!$O:$O,0)) -> AL HARAMAIN | C17: =INDEX(Dados!$C:$C,MATCH(8,Dados!$O:$O,0)) -> Árabe/Import Acessível | D17: =INDEX(Dados!$D:$D,MATCH(8,Dados!$O:$O,0)) -> Não | E17: =INDEX(Dados!$N:$N,MATCH(8,Dados!$O:$O,0)) -> 67.607294 | F17: =INDEX(Dados!$H:$H,MATCH(8,Dados!$O:$O,0)) -> 321.20766 | G17: =INDEX(Dados!$K:$K,MATCH(8,Dados!$O:$O,0)) -> 68 | H17: =INDEX(Dados!$L:$L,MATCH(8,Dados!$O:$O,0)) -> Baixa | I17: =INDEX(Dados!$I:$I,MATCH(8,Dados!$O:$O,0)) -> Crescendo | J17: =INDEX(Dados!$F:$F,MATCH(8,Dados!$O:$O,0)) -> 218100 | K17: =INDEX(Dados!$G:$G,MATCH(8,Dados!$O:$O,0)) -> 679 | L17: =INDEX(Dados!$J:$J,MATCH(8,Dados!$O:$O,0)) -> 0.7247
A18: =IF(9<=12,"Onda 1 — testar agora",IF(9<=40,"Onda 2 — próximos passos","Onda 3 — depois de consolidar")) -> Onda 1 — testar agora | B18: =INDEX(Dados!$B:$B,MATCH(9,Dados!$O:$O,0)) -> LESCENT | C18: =INDEX(Dados!$C:$C,MATCH(9,Dados!$O:$O,0)) -> A verificar | D18: =INDEX(Dados!$D:$D,MATCH(9,Dados!$O:$O,0)) -> Não | E18: =INDEX(Dados!$N:$N,MATCH(9,Dados!$O:$O,0)) -> 65.705103 | F18: =INDEX(Dados!$H:$H,MATCH(9,Dados!$O:$O,0)) -> 59.433566 | G18: =INDEX(Dados!$K:$K,MATCH(9,Dados!$O:$O,0)) -> 6 | H18: =INDEX(Dados!$L:$L,MATCH(9,Dados!$O:$O,0)) -> Baixa | I18: =INDEX(Dados!$I:$I,MATCH(9,Dados!$O:$O,0)) -> Crescendo | J18: =INDEX(Dados!$F:$F,MATCH(9,Dados!$O:$O,0)) -> 849900 | K18: =INDEX(Dados!$G:$G,MATCH(9,Dados!$O:$O,0)) -> 14300 | L18: =INDEX(Dados!$J:$J,MATCH(9,Dados!$O:$O,0)) -> 0.5215
A19: =IF(10<=12,"Onda 1 — testar agora",IF(10<=40,"Onda 2 — próximos passos","Onda 3 — depois de consolidar")) -> Onda 1 — testar agora | B19: =INDEX(Dados!$B:$B,MATCH(10,Dados!$O:$O,0)) -> FERRARI | C19: =INDEX(Dados!$C:$C,MATCH(10,Dados!$O:$O,0)) -> Designer/Importado | D19: =INDEX(Dados!$D:$D,MATCH(10,Dados!$O:$O,0)) -> Não | E19: =INDEX(Dados!$N:$N,MATCH(10,Dados!$O:$O,0)) -> 65.348606 | F19: =INDEX(Dados!$H:$H,MATCH(10,Dados!$O:$O,0)) -> 193.30435 | G19: =INDEX(Dados!$K:$K,MATCH(10,Dados!$O:$O,0)) -> 77 | H19: =INDEX(Dados!$L:$L,MATCH(10,Dados!$O:$O,0)) -> Baixa | I19: =INDEX(Dados!$I:$I,MATCH(10,Dados!$O:$O,0)) -> Crescendo | J19: =INDEX(Dados!$F:$F,MATCH(10,Dados!$O:$O,0)) -> 444600 | K19: =INDEX(Dados!$G:$G,MATCH(10,Dados!$O:$O,0)) -> 2300 | L19: =INDEX(Dados!$J:$J,MATCH(10,Dados!$O:$O,0)) -> 0.6234
A20: =IF(11<=12,"Onda 1 — testar agora",IF(11<=40,"Onda 2 — próximos passos","Onda 3 — depois de consolidar")) -> Onda 1 — testar agora | B20: =INDEX(Dados!$B:$B,MATCH(11,Dados!$O:$O,0)) -> GRANADO | C20: =INDEX(Dados!$C:$C,MATCH(11,Dados!$O:$O,0)) -> Nacional/Massa | D20: =INDEX(Dados!$D:$D,MATCH(11,Dados!$O:$O,0)) -> Não | E20: =INDEX(Dados!$N:$N,MATCH(11,Dados!$O:$O,0)) -> 65.152245 | F20: =INDEX(Dados!$H:$H,MATCH(11,Dados!$O:$O,0)) -> 182.66667 | G20: =INDEX(Dados!$K:$K,MATCH(11,Dados!$O:$O,0)) -> 78 | H20: =INDEX(Dados!$L:$L,MATCH(11,Dados!$O:$O,0)) -> Baixa | I20: =INDEX(Dados!$I:$I,MATCH(11,Dados!$O:$O,0)) -> Crescendo | J20: =INDEX(Dados!$F:$F,MATCH(11,Dados!$O:$O,0)) -> 602800 | K20: =INDEX(Dados!$G:$G,MATCH(11,Dados!$O:$O,0)) -> 3300 | L20: =INDEX(Dados!$J:$J,MATCH(11,Dados!$O:$O,0)) -> 0.6229
A21: =IF(12<=12,"Onda 1 — testar agora",IF(12<=40,"Onda 2 — próximos passos","Onda 3 — depois de consolidar")) -> Onda 1 — testar agora | B21: =INDEX(Dados!$B:$B,MATCH(12,Dados!$O:$O,0)) -> NARCISO RODRIGUEZ | C21: =INDEX(Dados!$C:$C,MATCH(12,Dados!$O:$O,0)) -> Designer/Importado | D21: =INDEX(Dados!$D:$D,MATCH(12,Dados!$O:$O,0)) -> Não | E21: =INDEX(Dados!$N:$N,MATCH(12,Dados!$O:$O,0)) -> 63.743301 | F21: =INDEX(Dados!$H:$H,MATCH(12,Dados!$O:$O,0)) -> 671.88264 | G21: =INDEX(Dados!$K:$K,MATCH(12,Dados!$O:$O,0)) -> 45 | H21: =INDEX(Dados!$L:$L,MATCH(12,Dados!$O:$O,0)) -> Média | I21: =INDEX(Dados!$I:$I,MATCH(12,Dados!$O:$O,0)) -> Crescendo | J21: =INDEX(Dados!$F:$F,MATCH(12,Dados!$O:$O,0)) -> 274800 | K21: =INDEX(Dados!$G:$G,MATCH(12,Dados!$O:$O,0)) -> 409 | L21: =INDEX(Dados!$J:$J,MATCH(12,Dados!$O:$O,0)) -> 0.6547
A22: =IF(13<=12,"Onda 1 — testar agora",IF(13<=40,"Onda 2 — próximos passos","Onda 3 — depois de consolidar")) -> Onda 2 — próximos passos | B22: =INDEX(Dados!$B:$B,MATCH(13,Dados!$O:$O,0)) -> BRAND COLLECTION | C22: =INDEX(Dados!$C:$C,MATCH(13,Dados!$O:$O,0)) -> Nacional/Contratipo | D22: =INDEX(Dados!$D:$D,MATCH(13,Dados!$O:$O,0)) -> Não | E22: =INDEX(Dados!$N:$N,MATCH(13,Dados!$O:$O,0)) -> 63.510099 | F22: =INDEX(Dados!$H:$H,MATCH(13,Dados!$O:$O,0)) -> 57.47561 | G22: =INDEX(Dados!$K:$K,MATCH(13,Dados!$O:$O,0)) -> 70 | H22: =INDEX(Dados!$L:$L,MATCH(13,Dados!$O:$O,0)) -> Baixa | I22: =INDEX(Dados!$I:$I,MATCH(13,Dados!$O:$O,0)) -> Crescendo | J22: =INDEX(Dados!$F:$F,MATCH(13,Dados!$O:$O,0)) -> 471300 | K22: =INDEX(Dados!$G:$G,MATCH(13,Dados!$O:$O,0)) -> 8200 | L22: =INDEX(Dados!$J:$J,MATCH(13,Dados!$O:$O,0)) -> 0.6627
A23: =IF(14<=12,"Onda 1 — testar agora",IF(14<=40,"Onda 2 — próximos passos","Onda 3 — depois de consolidar")) -> Onda 2 — próximos passos | B23: =INDEX(Dados!$B:$B,MATCH(14,Dados!$O:$O,0)) -> BVLGARI | C23: =INDEX(Dados!$C:$C,MATCH(14,Dados!$O:$O,0)) -> Designer/Importado Premium | D23: =INDEX(Dados!$D:$D,MATCH(14,Dados!$O:$O,0)) -> Não | E23: =INDEX(Dados!$N:$N,MATCH(14,Dados!$O:$O,0)) -> 62.719233 | F23: =INDEX(Dados!$H:$H,MATCH(14,Dados!$O:$O,0)) -> 644.71204 | G23: =INDEX(Dados!$K:$K,MATCH(14,Dados!$O:$O,0)) -> 63 | H23: =INDEX(Dados!$L:$L,MATCH(14,Dados!$O:$O,0)) -> Média | I23: =INDEX(Dados!$I:$I,MATCH(14,Dados!$O:$O,0)) -> Crescendo | J23: =INDEX(Dados!$F:$F,MATCH(14,Dados!$O:$O,0)) -> 615700 | K23: =INDEX(Dados!$G:$G,MATCH(14,Dados!$O:$O,0)) -> 955 | L23: =INDEX(Dados!$J:$J,MATCH(14,Dados!$O:$O,0)) -> 0.6653
A24: =IF(15<=12,"Onda 1 — testar agora",IF(15<=40,"Onda 2 — próximos passos","Onda 3 — depois de consolidar")) -> Onda 2 — próximos passos | B24: =INDEX(Dados!$B:$B,MATCH(15,Dados!$O:$O,0)) -> CHANEL | C24: =INDEX(Dados!$C:$C,MATCH(15,Dados!$O:$O,0)) -> Designer/Importado Premium | D24: =INDEX(Dados!$D:$D,MATCH(15,Dados!$O:$O,0)) -> Não | E24: =INDEX(Dados!$N:$N,MATCH(15,Dados!$O:$O,0)) -> 58.553596 | F24: =INDEX(Dados!$H:$H,MATCH(15,Dados!$O:$O,0)) -> 1000 | G24: =INDEX(Dados!$K:$K,MATCH(15,Dados!$O:$O,0)) -> 51 | H24: =INDEX(Dados!$L:$L,MATCH(15,Dados!$O:$O,0)) -> Baixa | I24: =INDEX(Dados!$I:$I,MATCH(15,Dados!$O:$O,0)) -> Diminuindo | J24: =INDEX(Dados!$F:$F,MATCH(15,Dados!$O:$O,0)) -> 1400000 | K24: =INDEX(Dados!$G:$G,MATCH(15,Dados!$O:$O,0)) -> 1400 | L24: =INDEX(Dados!$J:$J,MATCH(15,Dados!$O:$O,0)) -> 0.6857
A25: =IF(16<=12,"Onda 1 — testar agora",IF(16<=40,"Onda 2 — próximos passos","Onda 3 — depois de consolidar")) -> Onda 2 — próximos passos | B25: =INDEX(Dados!$B:$B,MATCH(16,Dados!$O:$O,0)) -> ISSEY MIYAKE | C25: =INDEX(Dados!$C:$C,MATCH(16,Dados!$O:$O,0)) -> Designer/Importado | D25: =INDEX(Dados!$D:$D,MATCH(16,Dados!$O:$O,0)) -> Não | E25: =INDEX(Dados!$N:$N,MATCH(16,Dados!$O:$O,0)) -> 58.311119 | F25: =INDEX(Dados!$H:$H,MATCH(16,Dados!$O:$O,0)) -> 387.2 | G25: =INDEX(Dados!$K:$K,MATCH(16,Dados!$O:$O,0)) -> 77 | H25: =INDEX(Dados!$L:$L,MATCH(16,Dados!$O:$O,0)) -> Média | I25: =INDEX(Dados!$I:$I,MATCH(16,Dados!$O:$O,0)) -> Crescendo | J25: =INDEX(Dados!$F:$F,MATCH(16,Dados!$O:$O,0)) -> 968000 | K25: =INDEX(Dados!$G:$G,MATCH(16,Dados!$O:$O,0)) -> 2500 | L25: =INDEX(Dados!$J:$J,MATCH(16,Dados!$O:$O,0)) -> 0.7072
A26: =IF(17<=12,"Onda 1 — testar agora",IF(17<=40,"Onda 2 — próximos passos","Onda 3 — depois de consolidar")) -> Onda 2 — próximos passos | B26: =INDEX(Dados!$B:$B,MATCH(17,Dados!$O:$O,0)) -> MOSCHINO | C26: =INDEX(Dados!$C:$C,MATCH(17,Dados!$O:$O,0)) -> Designer/Importado | D26: =INDEX(Dados!$D:$D,MATCH(17,Dados!$O:$O,0)) -> Não | E26: =INDEX(Dados!$N:$N,MATCH(17,Dados!$O:$O,0)) -> 57.965553 | F26: =INDEX(Dados!$H:$H,MATCH(17,Dados!$O:$O,0)) -> 322.51429 | G26: =INDEX(Dados!$K:$K,MATCH(17,Dados!$O:$O,0)) -> 58 | H26: =INDEX(Dados!$L:$L,MATCH(17,Dados!$O:$O,0)) -> Média | I26: =INDEX(Dados!$I:$I,MATCH(17,Dados!$O:$O,0)) -> Crescendo | J26: =INDEX(Dados!$F:$F,MATCH(17,Dados!$O:$O,0)) -> 282200 | K26: =INDEX(Dados!$G:$G,MATCH(17,Dados!$O:$O,0)) -> 875 | L26: =INDEX(Dados!$J:$J,MATCH(17,Dados!$O:$O,0)) -> 0.7136
A27: =IF(18<=12,"Onda 1 — testar agora",IF(18<=40,"Onda 2 — próximos passos","Onda 3 — depois de consolidar")) -> Onda 2 — próximos passos | B27: =INDEX(Dados!$B:$B,MATCH(18,Dados!$O:$O,0)) -> TOMMY HILFIGER | C27: =INDEX(Dados!$C:$C,MATCH(18,Dados!$O:$O,0)) -> Designer/Importado | D27: =INDEX(Dados!$D:$D,MATCH(18,Dados!$O:$O,0)) -> Não | E27: =INDEX(Dados!$N:$N,MATCH(18,Dados!$O:$O,0)) -> 57.628607 | F27: =INDEX(Dados!$H:$H,MATCH(18,Dados!$O:$O,0)) -> 271.67756 | G27: =INDEX(Dados!$K:$K,MATCH(18,Dados!$O:$O,0)) -> 45 | H27: =INDEX(Dados!$L:$L,MATCH(18,Dados!$O:$O,0)) -> Média | I27: =INDEX(Dados!$I:$I,MATCH(18,Dados!$O:$O,0)) -> Crescendo | J27: =INDEX(Dados!$F:$F,MATCH(18,Dados!$O:$O,0)) -> 249400 | K27: =INDEX(Dados!$G:$G,MATCH(18,Dados!$O:$O,0)) -> 918 | L27: =INDEX(Dados!$J:$J,MATCH(18,Dados!$O:$O,0)) -> 0.6894
A28: =IF(19<=12,"Onda 1 — testar agora",IF(19<=40,"Onda 2 — próximos passos","Onda 3 — depois de consolidar")) -> Onda 2 — próximos passos | B28: =INDEX(Dados!$B:$B,MATCH(19,Dados!$O:$O,0)) -> LAB 8 FRAGRANCES | C28: =INDEX(Dados!$C:$C,MATCH(19,Dados!$O:$O,0)) -> A verificar | D28: =INDEX(Dados!$D:$D,MATCH(19,Dados!$O:$O,0)) -> Não | E28: =INDEX(Dados!$N:$N,MATCH(19,Dados!$O:$O,0)) -> 56.546241 | F28: =INDEX(Dados!$H:$H,MATCH(19,Dados!$O:$O,0)) -> 178.69565 | G28: =INDEX(Dados!$K:$K,MATCH(19,Dados!$O:$O,0)) -> 35 | H28: =INDEX(Dados!$L:$L,MATCH(19,Dados!$O:$O,0)) -> Média | I28: =INDEX(Dados!$I:$I,MATCH(19,Dados!$O:$O,0)) -> Crescendo | J28: =INDEX(Dados!$F:$F,MATCH(19,Dados!$O:$O,0)) -> 411000 | K28: =INDEX(Dados!$G:$G,MATCH(19,Dados!$O:$O,0)) -> 2300 | L28: =INDEX(Dados!$J:$J,MATCH(19,Dados!$O:$O,0)) -> 0.5849
A29: =IF(20<=12,"Onda 1 — testar agora",IF(20<=40,"Onda 2 — próximos passos","Onda 3 — depois de consolidar")) -> Onda 2 — próximos passos | B29: =INDEX(Dados!$B:$B,MATCH(20,Dados!$O:$O,0)) -> ANIMALE | C29: =INDEX(Dados!$C:$C,MATCH(20,Dados!$O:$O,0)) -> Designer/Importado | D29: =INDEX(Dados!$D:$D,MATCH(20,Dados!$O:$O,0)) -> Não | E29: =INDEX(Dados!$N:$N,MATCH(20,Dados!$O:$O,0)) -> 55.721002 | F29: =INDEX(Dados!$H:$H,MATCH(20,Dados!$O:$O,0)) -> 233.17647 | G29: =INDEX(Dados!$K:$K,MATCH(20,Dados!$O:$O,0)) -> 84 | H29: =INDEX(Dados!$L:$L,MATCH(20,Dados!$O:$O,0)) -> Média | I29: =INDEX(Dados!$I:$I,MATCH(20,Dados!$O:$O,0)) -> Crescendo | J29: =INDEX(Dados!$F:$F,MATCH(20,Dados!$O:$O,0)) -> 396400 | K29: =INDEX(Dados!$G:$G,MATCH(20,Dados!$O:$O,0)) -> 1700 | L29: =INDEX(Dados!$J:$J,MATCH(20,Dados!$O:$O,0)) -> 0.5472
A30: =IF(21<=12,"Onda 1 — testar agora",IF(21<=40,"Onda 2 — próximos passos","Onda 3 — depois de consolidar")) -> Onda 2 — próximos passos | B30: =INDEX(Dados!$B:$B,MATCH(21,Dados!$O:$O,0)) -> PARIS CORNER | C30: =INDEX(Dados!$C:$C,MATCH(21,Dados!$O:$O,0)) -> Árabe/Import Acessível | D30: =INDEX(Dados!$D:$D,MATCH(21,Dados!$O:$O,0)) -> Não | E30: =INDEX(Dados!$N:$N,MATCH(21,Dados!$O:$O,0)) -> 55.680433 | F30: =INDEX(Dados!$H:$H,MATCH(21,Dados!$O:$O,0)) -> 265.94737 | G30: =INDEX(Dados!$K:$K,MATCH(21,Dados!$O:$O,0)) -> 100 | H30: =INDEX(Dados!$L:$L,MATCH(21,Dados!$O:$O,0)) -> Média | I30: =INDEX(Dados!$I:$I,MATCH(21,Dados!$O:$O,0)) -> Crescendo | J30: =INDEX(Dados!$F:$F,MATCH(21,Dados!$O:$O,0)) -> 505300 | K30: =INDEX(Dados!$G:$G,MATCH(21,Dados!$O:$O,0)) -> 1900 | L30: =INDEX(Dados!$J:$J,MATCH(21,Dados!$O:$O,0)) -> 0.7238
A31: =IF(22<=12,"Onda 1 — testar agora",IF(22<=40,"Onda 2 — próximos passos","Onda 3 — depois de consolidar")) -> Onda 2 — próximos passos | B31: =INDEX(Dados!$B:$B,MATCH(22,Dados!$O:$O,0)) -> AFNAN | C31: =INDEX(Dados!$C:$C,MATCH(22,Dados!$O:$O,0)) -> Árabe/Import Acessível | D31: =INDEX(Dados!$D:$D,MATCH(22,Dados!$O:$O,0)) -> Não | E31: =INDEX(Dados!$N:$N,MATCH(22,Dados!$O:$O,0)) -> 55.086201 | F31: =INDEX(Dados!$H:$H,MATCH(22,Dados!$O:$O,0)) -> 333.33333 | G31: =INDEX(Dados!$K:$K,MATCH(22,Dados!$O:$O,0)) -> 148 | H31: =INDEX(Dados!$L:$L,MATCH(22,Dados!$O:$O,0)) -> Média | I31: =INDEX(Dados!$I:$I,MATCH(22,Dados!$O:$O,0)) -> Crescendo | J31: =INDEX(Dados!$F:$F,MATCH(22,Dados!$O:$O,0)) -> 1600000 | K31: =INDEX(Dados!$G:$G,MATCH(22,Dados!$O:$O,0)) -> 4800 | L31: =INDEX(Dados!$J:$J,MATCH(22,Dados!$O:$O,0)) -> 0.6917
A32: =IF(23<=12,"Onda 1 — testar agora",IF(23<=40,"Onda 2 — próximos passos","Onda 3 — depois de consolidar")) -> Onda 2 — próximos passos | B32: =INDEX(Dados!$B:$B,MATCH(23,Dados!$O:$O,0)) -> RAYHAAN | C32: =INDEX(Dados!$C:$C,MATCH(23,Dados!$O:$O,0)) -> Árabe/Import Acessível | D32: =INDEX(Dados!$D:$D,MATCH(23,Dados!$O:$O,0)) -> Não | E32: =INDEX(Dados!$N:$N,MATCH(23,Dados!$O:$O,0)) -> 54.947175 | F32: =INDEX(Dados!$H:$H,MATCH(23,Dados!$O:$O,0)) -> 266.66667 | G32: =INDEX(Dados!$K:$K,MATCH(23,Dados!$O:$O,0)) -> 122 | H32: =INDEX(Dados!$L:$L,MATCH(23,Dados!$O:$O,0)) -> Média | I32: =INDEX(Dados!$I:$I,MATCH(23,Dados!$O:$O,0)) -> Crescendo | J32: =INDEX(Dados!$F:$F,MATCH(23,Dados!$O:$O,0)) -> 1200000 | K32: =INDEX(Dados!$G:$G,MATCH(23,Dados!$O:$O,0)) -> 4500 | L32: =INDEX(Dados!$J:$J,MATCH(23,Dados!$O:$O,0)) -> 0.6679
A33: =IF(24<=12,"Onda 1 — testar agora",IF(24<=40,"Onda 2 — próximos passos","Onda 3 — depois de consolidar")) -> Onda 2 — próximos passos | B33: =INDEX(Dados!$B:$B,MATCH(24,Dados!$O:$O,0)) -> RASASI | C33: =INDEX(Dados!$C:$C,MATCH(24,Dados!$O:$O,0)) -> Árabe/Import Acessível | D33: =INDEX(Dados!$D:$D,MATCH(24,Dados!$O:$O,0)) -> Não | E33: =INDEX(Dados!$N:$N,MATCH(24,Dados!$O:$O,0)) -> 54.722752 | F33: =INDEX(Dados!$H:$H,MATCH(24,Dados!$O:$O,0)) -> 258.62069 | G33: =INDEX(Dados!$K:$K,MATCH(24,Dados!$O:$O,0)) -> 125 | H33: =INDEX(Dados!$L:$L,MATCH(24,Dados!$O:$O,0)) -> Média | I33: =INDEX(Dados!$I:$I,MATCH(24,Dados!$O:$O,0)) -> Crescendo | J33: =INDEX(Dados!$F:$F,MATCH(24,Dados!$O:$O,0)) -> 1500000 | K33: =INDEX(Dados!$G:$G,MATCH(24,Dados!$O:$O,0)) -> 5800 | L33: =INDEX(Dados!$J:$J,MATCH(24,Dados!$O:$O,0)) -> 0.6473
A34: =IF(25<=12,"Onda 1 — testar agora",IF(25<=40,"Onda 2 — próximos passos","Onda 3 — depois de consolidar")) -> Onda 2 — próximos passos | B34: =INDEX(Dados!$B:$B,MATCH(25,Dados!$O:$O,0)) -> PHEBO | C34: =INDEX(Dados!$C:$C,MATCH(25,Dados!$O:$O,0)) -> Nacional/Massa | D34: =INDEX(Dados!$D:$D,MATCH(25,Dados!$O:$O,0)) -> Não | E34: =INDEX(Dados!$N:$N,MATCH(25,Dados!$O:$O,0)) -> 54.597765 | F34: =INDEX(Dados!$H:$H,MATCH(25,Dados!$O:$O,0)) -> 106.52174 | G34: =INDEX(Dados!$K:$K,MATCH(25,Dados!$O:$O,0)) -> 60 | H34: =INDEX(Dados!$L:$L,MATCH(25,Dados!$O:$O,0)) -> Média | I34: =INDEX(Dados!$I:$I,MATCH(25,Dados!$O:$O,0)) -> Crescendo | J34: =INDEX(Dados!$F:$F,MATCH(25,Dados!$O:$O,0)) -> 245000 | K34: =INDEX(Dados!$G:$G,MATCH(25,Dados!$O:$O,0)) -> 2300 | L34: =INDEX(Dados!$J:$J,MATCH(25,Dados!$O:$O,0)) -> 0.5217
A35: =IF(26<=12,"Onda 1 — testar agora",IF(26<=40,"Onda 2 — próximos passos","Onda 3 — depois de consolidar")) -> Onda 2 — próximos passos | B35: =INDEX(Dados!$B:$B,MATCH(26,Dados!$O:$O,0)) -> DIOR | C35: =INDEX(Dados!$C:$C,MATCH(26,Dados!$O:$O,0)) -> Designer/Importado Premium | D35: =INDEX(Dados!$D:$D,MATCH(26,Dados!$O:$O,0)) -> Não | E35: =INDEX(Dados!$N:$N,MATCH(26,Dados!$O:$O,0)) -> 54.278718 | F35: =INDEX(Dados!$H:$H,MATCH(26,Dados!$O:$O,0)) -> 777.77778 | G35: =INDEX(Dados!$K:$K,MATCH(26,Dados!$O:$O,0)) -> 77 | H35: =INDEX(Dados!$L:$L,MATCH(26,Dados!$O:$O,0)) -> Baixa | I35: =INDEX(Dados!$I:$I,MATCH(26,Dados!$O:$O,0)) -> Diminuindo | J35: =INDEX(Dados!$F:$F,MATCH(26,Dados!$O:$O,0)) -> 2100000 | K35: =INDEX(Dados!$G:$G,MATCH(26,Dados!$O:$O,0)) -> 2700 | L35: =INDEX(Dados!$J:$J,MATCH(26,Dados!$O:$O,0)) -> 0.8113
A36: =IF(27<=12,"Onda 1 — testar agora",IF(27<=40,"Onda 2 — próximos passos","Onda 3 — depois de consolidar")) -> Onda 2 — próximos passos | B36: =INDEX(Dados!$B:$B,MATCH(27,Dados!$O:$O,0)) -> JEAN PAUL GAULTIER | C36: =INDEX(Dados!$C:$C,MATCH(27,Dados!$O:$O,0)) -> Designer/Importado | D36: =INDEX(Dados!$D:$D,MATCH(27,Dados!$O:$O,0)) -> Não | E36: =INDEX(Dados!$N:$N,MATCH(27,Dados!$O:$O,0)) -> 53.848123 | F36: =INDEX(Dados!$H:$H,MATCH(27,Dados!$O:$O,0)) -> 638.88889 | G36: =INDEX(Dados!$K:$K,MATCH(27,Dados!$O:$O,0)) -> 27 | H36: =INDEX(Dados!$L:$L,MATCH(27,Dados!$O:$O,0)) -> Alta | I36: =INDEX(Dados!$I:$I,MATCH(27,Dados!$O:$O,0)) -> Crescendo | J36: =INDEX(Dados!$F:$F,MATCH(27,Dados!$O:$O,0)) -> 4600000 | K36: =INDEX(Dados!$G:$G,MATCH(27,Dados!$O:$O,0)) -> 7200 | L36: =INDEX(Dados!$J:$J,MATCH(27,Dados!$O:$O,0)) -> 0.7093
A37: =IF(28<=12,"Onda 1 — testar agora",IF(28<=40,"Onda 2 — próximos passos","Onda 3 — depois de consolidar")) -> Onda 2 — próximos passos | B37: =INDEX(Dados!$B:$B,MATCH(28,Dados!$O:$O,0)) -> ERIAN | C37: =INDEX(Dados!$C:$C,MATCH(28,Dados!$O:$O,0)) -> A verificar | D37: =INDEX(Dados!$D:$D,MATCH(28,Dados!$O:$O,0)) -> Não | E37: =INDEX(Dados!$N:$N,MATCH(28,Dados!$O:$O,0)) -> 53.72241 | F37: =INDEX(Dados!$H:$H,MATCH(28,Dados!$O:$O,0)) -> 575.30769 | G37: =INDEX(Dados!$K:$K,MATCH(28,Dados!$O:$O,0)) -> 2 | H37: =INDEX(Dados!$L:$L,MATCH(28,Dados!$O:$O,0)) -> Alta | I37: =INDEX(Dados!$I:$I,MATCH(28,Dados!$O:$O,0)) -> Crescendo | J37: =INDEX(Dados!$F:$F,MATCH(28,Dados!$O:$O,0)) -> 747900 | K37: =INDEX(Dados!$G:$G,MATCH(28,Dados!$O:$O,0)) -> 1300 | L37: =INDEX(Dados!$J:$J,MATCH(28,Dados!$O:$O,0)) -> 0.8462
A38: =IF(29<=12,"Onda 1 — testar agora",IF(29<=40,"Onda 2 — próximos passos","Onda 3 — depois de consolidar")) -> Onda 2 — próximos passos | B38: =INDEX(Dados!$B:$B,MATCH(29,Dados!$O:$O,0)) -> ARMANI BEAUTY | C38: =INDEX(Dados!$C:$C,MATCH(29,Dados!$O:$O,0)) -> Designer/Importado | D38: =INDEX(Dados!$D:$D,MATCH(29,Dados!$O:$O,0)) -> Não | E38: =INDEX(Dados!$N:$N,MATCH(29,Dados!$O:$O,0)) -> 53.70694 | F38: =INDEX(Dados!$H:$H,MATCH(29,Dados!$O:$O,0)) -> 585.36585 | G38: =INDEX(Dados!$K:$K,MATCH(29,Dados!$O:$O,0)) -> 7 | H38: =INDEX(Dados!$L:$L,MATCH(29,Dados!$O:$O,0)) -> Alta | I38: =INDEX(Dados!$I:$I,MATCH(29,Dados!$O:$O,0)) -> Crescendo | J38: =INDEX(Dados!$F:$F,MATCH(29,Dados!$O:$O,0)) -> 2400000 | K38: =INDEX(Dados!$G:$G,MATCH(29,Dados!$O:$O,0)) -> 4100 | L38: =INDEX(Dados!$J:$J,MATCH(29,Dados!$O:$O,0)) -> 0.5539
A39: =IF(30<=12,"Onda 1 — testar agora",IF(30<=40,"Onda 2 — próximos passos","Onda 3 — depois de consolidar")) -> Onda 2 — próximos passos | B39: =INDEX(Dados!$B:$B,MATCH(30,Dados!$O:$O,0)) -> PRADA | C39: =INDEX(Dados!$C:$C,MATCH(30,Dados!$O:$O,0)) -> Designer/Importado | D39: =INDEX(Dados!$D:$D,MATCH(30,Dados!$O:$O,0)) -> Não | E39: =INDEX(Dados!$N:$N,MATCH(30,Dados!$O:$O,0)) -> 53.666697 | F39: =INDEX(Dados!$H:$H,MATCH(30,Dados!$O:$O,0)) -> 722.22222 | G39: =INDEX(Dados!$K:$K,MATCH(30,Dados!$O:$O,0)) -> 70 | H39: =INDEX(Dados!$L:$L,MATCH(30,Dados!$O:$O,0)) -> Média | I39: =INDEX(Dados!$I:$I,MATCH(30,Dados!$O:$O,0)) -> Estável | J39: =INDEX(Dados!$F:$F,MATCH(30,Dados!$O:$O,0)) -> 1300000 | K39: =INDEX(Dados!$G:$G,MATCH(30,Dados!$O:$O,0)) -> 1800 | L39: =INDEX(Dados!$J:$J,MATCH(30,Dados!$O:$O,0)) -> 0.7171
A40: =IF(31<=12,"Onda 1 — testar agora",IF(31<=40,"Onda 2 — próximos passos","Onda 3 — depois de consolidar")) -> Onda 2 — próximos passos | B40: =INDEX(Dados!$B:$B,MATCH(31,Dados!$O:$O,0)) -> RABANNE | C40: =INDEX(Dados!$C:$C,MATCH(31,Dados!$O:$O,0)) -> Designer/Importado | D40: =INDEX(Dados!$D:$D,MATCH(31,Dados!$O:$O,0)) -> Não | E40: =INDEX(Dados!$N:$N,MATCH(31,Dados!$O:$O,0)) -> 52.694697 | F40: =INDEX(Dados!$H:$H,MATCH(31,Dados!$O:$O,0)) -> 574.46809 | G40: =INDEX(Dados!$K:$K,MATCH(31,Dados!$O:$O,0)) -> 32 | H40: =INDEX(Dados!$L:$L,MATCH(31,Dados!$O:$O,0)) -> Média | I40: =INDEX(Dados!$I:$I,MATCH(31,Dados!$O:$O,0)) -> Estável | J40: =INDEX(Dados!$F:$F,MATCH(31,Dados!$O:$O,0)) -> 8100000 | K40: =INDEX(Dados!$G:$G,MATCH(31,Dados!$O:$O,0)) -> 14100 | L40: =INDEX(Dados!$J:$J,MATCH(31,Dados!$O:$O,0)) -> 0.6857
A41: =IF(32<=12,"Onda 1 — testar agora",IF(32<=40,"Onda 2 — próximos passos","Onda 3 — depois de consolidar")) -> Onda 2 — próximos passos | B41: =INDEX(Dados!$B:$B,MATCH(32,Dados!$O:$O,0)) -> FRENCH AVENUE | C41: =INDEX(Dados!$C:$C,MATCH(32,Dados!$O:$O,0)) -> Árabe/Import Acessível (a verificar) | D41: =INDEX(Dados!$D:$D,MATCH(32,Dados!$O:$O,0)) -> Não | E41: =INDEX(Dados!$N:$N,MATCH(32,Dados!$O:$O,0)) -> 52.29254 | F41: =INDEX(Dados!$H:$H,MATCH(32,Dados!$O:$O,0)) -> 307.69231 | G41: =INDEX(Dados!$K:$K,MATCH(32,Dados!$O:$O,0)) -> 219 | H41: =INDEX(Dados!$L:$L,MATCH(32,Dados!$O:$O,0)) -> Média | I41: =INDEX(Dados!$I:$I,MATCH(32,Dados!$O:$O,0)) -> Crescendo | J41: =INDEX(Dados!$F:$F,MATCH(32,Dados!$O:$O,0)) -> 2400000 | K41: =INDEX(Dados!$G:$G,MATCH(32,Dados!$O:$O,0)) -> 7800 | L41: =INDEX(Dados!$J:$J,MATCH(32,Dados!$O:$O,0)) -> 0.7042
A42: =IF(33<=12,"Onda 1 — testar agora",IF(33<=40,"Onda 2 — próximos passos","Onda 3 — depois de consolidar")) -> Onda 2 — próximos passos | B42: =INDEX(Dados!$B:$B,MATCH(33,Dados!$O:$O,0)) -> YVES SAINT LAURENT | C42: =INDEX(Dados!$C:$C,MATCH(33,Dados!$O:$O,0)) -> Designer/Importado | D42: =INDEX(Dados!$D:$D,MATCH(33,Dados!$O:$O,0)) -> Não | E42: =INDEX(Dados!$N:$N,MATCH(33,Dados!$O:$O,0)) -> 52.05516 | F42: =INDEX(Dados!$H:$H,MATCH(33,Dados!$O:$O,0)) -> 638.88889 | G42: =INDEX(Dados!$K:$K,MATCH(33,Dados!$O:$O,0)) -> 80 | H42: =INDEX(Dados!$L:$L,MATCH(33,Dados!$O:$O,0)) -> Alta | I42: =INDEX(Dados!$I:$I,MATCH(33,Dados!$O:$O,0)) -> Crescendo | J42: =INDEX(Dados!$F:$F,MATCH(33,Dados!$O:$O,0)) -> 2300000 | K42: =INDEX(Dados!$G:$G,MATCH(33,Dados!$O:$O,0)) -> 3600 | L42: =INDEX(Dados!$J:$J,MATCH(33,Dados!$O:$O,0)) -> 0.7057
A43: =IF(34<=12,"Onda 1 — testar agora",IF(34<=40,"Onda 2 — próximos passos","Onda 3 — depois de consolidar")) -> Onda 2 — próximos passos | B43: =INDEX(Dados!$B:$B,MATCH(34,Dados!$O:$O,0)) -> BURBERRY | C43: =INDEX(Dados!$C:$C,MATCH(34,Dados!$O:$O,0)) -> Designer/Importado | D43: =INDEX(Dados!$D:$D,MATCH(34,Dados!$O:$O,0)) -> Não | E43: =INDEX(Dados!$N:$N,MATCH(34,Dados!$O:$O,0)) -> 50.521943 | F43: =INDEX(Dados!$H:$H,MATCH(34,Dados!$O:$O,0)) -> 500.9 | G43: =INDEX(Dados!$K:$K,MATCH(34,Dados!$O:$O,0)) -> 63 | H43: =INDEX(Dados!$L:$L,MATCH(34,Dados!$O:$O,0)) -> Média | I43: =INDEX(Dados!$I:$I,MATCH(34,Dados!$O:$O,0)) -> Estável | J43: =INDEX(Dados!$F:$F,MATCH(34,Dados!$O:$O,0)) -> 500900 | K43: =INDEX(Dados!$G:$G,MATCH(34,Dados!$O:$O,0)) -> 1000 | L43: =INDEX(Dados!$J:$J,MATCH(34,Dados!$O:$O,0)) -> 0.7762
A44: =IF(35<=12,"Onda 1 — testar agora",IF(35<=40,"Onda 2 — próximos passos","Onda 3 — depois de consolidar")) -> Onda 2 — próximos passos | B44: =INDEX(Dados!$B:$B,MATCH(35,Dados!$O:$O,0)) -> NUANCIELO | C44: =INDEX(Dados!$C:$C,MATCH(35,Dados!$O:$O,0)) -> A verificar | D44: =INDEX(Dados!$D:$D,MATCH(35,Dados!$O:$O,0)) -> Não | E44: =INDEX(Dados!$N:$N,MATCH(35,Dados!$O:$O,0)) -> 48.997981 | F44: =INDEX(Dados!$H:$H,MATCH(35,Dados!$O:$O,0)) -> 272.73743 | G44: =INDEX(Dados!$K:$K,MATCH(35,Dados!$O:$O,0)) -> 5 | H44: =INDEX(Dados!$L:$L,MATCH(35,Dados!$O:$O,0)) -> Média | I44: =INDEX(Dados!$I:$I,MATCH(35,Dados!$O:$O,0)) -> Estável | J44: =INDEX(Dados!$F:$F,MATCH(35,Dados!$O:$O,0)) -> 244100 | K44: =INDEX(Dados!$G:$G,MATCH(35,Dados!$O:$O,0)) -> 895 | L44: =INDEX(Dados!$J:$J,MATCH(35,Dados!$O:$O,0)) -> 0.3115
A45: =IF(36<=12,"Onda 1 — testar agora",IF(36<=40,"Onda 2 — próximos passos","Onda 3 — depois de consolidar")) -> Onda 2 — próximos passos | B45: =INDEX(Dados!$B:$B,MATCH(36,Dados!$O:$O,0)) -> VERSACE | C45: =INDEX(Dados!$C:$C,MATCH(36,Dados!$O:$O,0)) -> Designer/Importado | D45: =INDEX(Dados!$D:$D,MATCH(36,Dados!$O:$O,0)) -> Não | E45: =INDEX(Dados!$N:$N,MATCH(36,Dados!$O:$O,0)) -> 48.474569 | F45: =INDEX(Dados!$H:$H,MATCH(36,Dados!$O:$O,0)) -> 468.75 | G45: =INDEX(Dados!$K:$K,MATCH(36,Dados!$O:$O,0)) -> 109 | H45: =INDEX(Dados!$L:$L,MATCH(36,Dados!$O:$O,0)) -> Alta | I45: =INDEX(Dados!$I:$I,MATCH(36,Dados!$O:$O,0)) -> Crescendo | J45: =INDEX(Dados!$F:$F,MATCH(36,Dados!$O:$O,0)) -> 1500000 | K45: =INDEX(Dados!$G:$G,MATCH(36,Dados!$O:$O,0)) -> 3200 | L45: =INDEX(Dados!$J:$J,MATCH(36,Dados!$O:$O,0)) -> 0.726
A46: =IF(37<=12,"Onda 1 — testar agora",IF(37<=40,"Onda 2 — próximos passos","Onda 3 — depois de consolidar")) -> Onda 2 — próximos passos | B46: =INDEX(Dados!$B:$B,MATCH(37,Dados!$O:$O,0)) -> FEROFIRE | C46: =INDEX(Dados!$C:$C,MATCH(37,Dados!$O:$O,0)) -> A verificar | D46: =INDEX(Dados!$D:$D,MATCH(37,Dados!$O:$O,0)) -> Não | E46: =INDEX(Dados!$N:$N,MATCH(37,Dados!$O:$O,0)) -> 47.18444 | F46: =INDEX(Dados!$H:$H,MATCH(37,Dados!$O:$O,0)) -> 154.04167 | G46: =INDEX(Dados!$K:$K,MATCH(37,Dados!$O:$O,0)) -> 5 | H46: =INDEX(Dados!$L:$L,MATCH(37,Dados!$O:$O,0)) -> Alta | I46: =INDEX(Dados!$I:$I,MATCH(37,Dados!$O:$O,0)) -> Crescendo | J46: =INDEX(Dados!$F:$F,MATCH(37,Dados!$O:$O,0)) -> 739400 | K46: =INDEX(Dados!$G:$G,MATCH(37,Dados!$O:$O,0)) -> 4800 | L46: =INDEX(Dados!$J:$J,MATCH(37,Dados!$O:$O,0)) -> 0.4286
A47: =IF(38<=12,"Onda 1 — testar agora",IF(38<=40,"Onda 2 — próximos passos","Onda 3 — depois de consolidar")) -> Onda 2 — próximos passos | B47: =INDEX(Dados!$B:$B,MATCH(38,Dados!$O:$O,0)) -> LIPX | C47: =INDEX(Dados!$C:$C,MATCH(38,Dados!$O:$O,0)) -> A verificar | D47: =INDEX(Dados!$D:$D,MATCH(38,Dados!$O:$O,0)) -> Não | E47: =INDEX(Dados!$N:$N,MATCH(38,Dados!$O:$O,0)) -> 46.765161 | F47: =INDEX(Dados!$H:$H,MATCH(38,Dados!$O:$O,0)) -> 195.2381 | G47: =INDEX(Dados!$K:$K,MATCH(38,Dados!$O:$O,0)) -> 36 | H47: =INDEX(Dados!$L:$L,MATCH(38,Dados!$O:$O,0)) -> Alta | I47: =INDEX(Dados!$I:$I,MATCH(38,Dados!$O:$O,0)) -> Crescendo | J47: =INDEX(Dados!$F:$F,MATCH(38,Dados!$O:$O,0)) -> 4100000 | K47: =INDEX(Dados!$G:$G,MATCH(38,Dados!$O:$O,0)) -> 21000 | L47: =INDEX(Dados!$J:$J,MATCH(38,Dados!$O:$O,0)) -> 0.8333
A48: =IF(39<=12,"Onda 1 — testar agora",IF(39<=40,"Onda 2 — próximos passos","Onda 3 — depois de consolidar")) -> Onda 2 — próximos passos | B48: =INDEX(Dados!$B:$B,MATCH(39,Dados!$O:$O,0)) -> BIDAYA | C48: =INDEX(Dados!$C:$C,MATCH(39,Dados!$O:$O,0)) -> Árabe/Import Acessível | D48: =INDEX(Dados!$D:$D,MATCH(39,Dados!$O:$O,0)) -> Não | E48: =INDEX(Dados!$N:$N,MATCH(39,Dados!$O:$O,0)) -> 46.47012 | F48: =INDEX(Dados!$H:$H,MATCH(39,Dados!$O:$O,0)) -> 277.77778 | G48: =INDEX(Dados!$K:$K,MATCH(39,Dados!$O:$O,0)) -> 82 | H48: =INDEX(Dados!$L:$L,MATCH(39,Dados!$O:$O,0)) -> Alta | I48: =INDEX(Dados!$I:$I,MATCH(39,Dados!$O:$O,0)) -> Crescendo | J48: =INDEX(Dados!$F:$F,MATCH(39,Dados!$O:$O,0)) -> 1500000 | K48: =INDEX(Dados!$G:$G,MATCH(39,Dados!$O:$O,0)) -> 5400 | L48: =INDEX(Dados!$J:$J,MATCH(39,Dados!$O:$O,0)) -> 0.6021
A49: =IF(40<=12,"Onda 1 — testar agora",IF(40<=40,"Onda 2 — próximos passos","Onda 3 — depois de consolidar")) -> Onda 2 — próximos passos | B49: =INDEX(Dados!$B:$B,MATCH(40,Dados!$O:$O,0)) -> ISABELLE LA BELLE ASAD BOURBON | C49: =INDEX(Dados!$C:$C,MATCH(40,Dados!$O:$O,0)) -> A verificar | D49: =INDEX(Dados!$D:$D,MATCH(40,Dados!$O:$O,0)) -> Não | E49: =INDEX(Dados!$N:$N,MATCH(40,Dados!$O:$O,0)) -> 46.184862 | F49: =INDEX(Dados!$H:$H,MATCH(40,Dados!$O:$O,0)) -> 86.405405 | G49: =INDEX(Dados!$K:$K,MATCH(40,Dados!$O:$O,0)) -> 4 | H49: =INDEX(Dados!$L:$L,MATCH(40,Dados!$O:$O,0)) -> Alta | I49: =INDEX(Dados!$I:$I,MATCH(40,Dados!$O:$O,0)) -> Crescendo | J49: =INDEX(Dados!$F:$F,MATCH(40,Dados!$O:$O,0)) -> 319700 | K49: =INDEX(Dados!$G:$G,MATCH(40,Dados!$O:$O,0)) -> 3700 | L49: =INDEX(Dados!$J:$J,MATCH(40,Dados!$O:$O,0)) -> 0
A50: =IF(41<=12,"Onda 1 — testar agora",IF(41<=40,"Onda 2 — próximos passos","Onda 3 — depois de consolidar")) -> Onda 3 — depois de consolidar | B50: =INDEX(Dados!$B:$B,MATCH(41,Dados!$O:$O,0)) -> GOTA BRASIL | C50: =INDEX(Dados!$C:$C,MATCH(41,Dados!$O:$O,0)) -> Nacional/Massa | D50: =INDEX(Dados!$D:$D,MATCH(41,Dados!$O:$O,0)) -> Não | E50: =INDEX(Dados!$N:$N,MATCH(41,Dados!$O:$O,0)) -> 46.071948 | F50: =INDEX(Dados!$H:$H,MATCH(41,Dados!$O:$O,0)) -> 74.586957 | G50: =INDEX(Dados!$K:$K,MATCH(41,Dados!$O:$O,0)) -> 2 | H50: =INDEX(Dados!$L:$L,MATCH(41,Dados!$O:$O,0)) -> Alta | I50: =INDEX(Dados!$I:$I,MATCH(41,Dados!$O:$O,0)) -> Crescendo | J50: =INDEX(Dados!$F:$F,MATCH(41,Dados!$O:$O,0)) -> 343100 | K50: =INDEX(Dados!$G:$G,MATCH(41,Dados!$O:$O,0)) -> 4600 | L50: =INDEX(Dados!$J:$J,MATCH(41,Dados!$O:$O,0)) -> 0.0588
A51: =IF(42<=12,"Onda 1 — testar agora",IF(42<=40,"Onda 2 — próximos passos","Onda 3 — depois de consolidar")) -> Onda 3 — depois de consolidar | B51: =INDEX(Dados!$B:$B,MATCH(42,Dados!$O:$O,0)) -> PARIS INTENSE | C51: =INDEX(Dados!$C:$C,MATCH(42,Dados!$O:$O,0)) -> Nacional/Contratipo (a verificar) | D51: =INDEX(Dados!$D:$D,MATCH(42,Dados!$O:$O,0)) -> Não | E51: =INDEX(Dados!$N:$N,MATCH(42,Dados!$O:$O,0)) -> 45.888966 | F51: =INDEX(Dados!$H:$H,MATCH(42,Dados!$O:$O,0)) -> 67.039106 | G51: =INDEX(Dados!$K:$K,MATCH(42,Dados!$O:$O,0)) -> 4 | H51: =INDEX(Dados!$L:$L,MATCH(42,Dados!$O:$O,0)) -> Alta | I51: =INDEX(Dados!$I:$I,MATCH(42,Dados!$O:$O,0)) -> Crescendo | J51: =INDEX(Dados!$F:$F,MATCH(42,Dados!$O:$O,0)) -> 1200000 | K51: =INDEX(Dados!$G:$G,MATCH(42,Dados!$O:$O,0)) -> 17900 | L51: =INDEX(Dados!$J:$J,MATCH(42,Dados!$O:$O,0)) -> 0.5926
A52: =IF(43<=12,"Onda 1 — testar agora",IF(43<=40,"Onda 2 — próximos passos","Onda 3 — depois de consolidar")) -> Onda 3 — depois de consolidar | B52: =INDEX(Dados!$B:$B,MATCH(43,Dados!$O:$O,0)) -> JOOP! | C52: =INDEX(Dados!$C:$C,MATCH(43,Dados!$O:$O,0)) -> Designer/Importado | D52: =INDEX(Dados!$D:$D,MATCH(43,Dados!$O:$O,0)) -> Não | E52: =INDEX(Dados!$N:$N,MATCH(43,Dados!$O:$O,0)) -> 45.836866 | F52: =INDEX(Dados!$H:$H,MATCH(43,Dados!$O:$O,0)) -> 209.7619 | G52: =INDEX(Dados!$K:$K,MATCH(43,Dados!$O:$O,0)) -> 70 | H52: =INDEX(Dados!$L:$L,MATCH(43,Dados!$O:$O,0)) -> Alta | I52: =INDEX(Dados!$I:$I,MATCH(43,Dados!$O:$O,0)) -> Crescendo | J52: =INDEX(Dados!$F:$F,MATCH(43,Dados!$O:$O,0)) -> 440500 | K52: =INDEX(Dados!$G:$G,MATCH(43,Dados!$O:$O,0)) -> 2100 | L52: =INDEX(Dados!$J:$J,MATCH(43,Dados!$O:$O,0)) -> 0.6425
A53: =IF(44<=12,"Onda 1 — testar agora",IF(44<=40,"Onda 2 — próximos passos","Onda 3 — depois de consolidar")) -> Onda 3 — depois de consolidar | B53: =INDEX(Dados!$B:$B,MATCH(44,Dados!$O:$O,0)) -> ISABELLE LA BELLE | C53: =INDEX(Dados!$C:$C,MATCH(44,Dados!$O:$O,0)) -> A verificar | D53: =INDEX(Dados!$D:$D,MATCH(44,Dados!$O:$O,0)) -> Não | E53: =INDEX(Dados!$N:$N,MATCH(44,Dados!$O:$O,0)) -> 45.186826 | F53: =INDEX(Dados!$H:$H,MATCH(44,Dados!$O:$O,0)) -> 78.651685 | G53: =INDEX(Dados!$K:$K,MATCH(44,Dados!$O:$O,0)) -> 30 | H53: =INDEX(Dados!$L:$L,MATCH(44,Dados!$O:$O,0)) -> Alta | I53: =INDEX(Dados!$I:$I,MATCH(44,Dados!$O:$O,0)) -> Crescendo | J53: =INDEX(Dados!$F:$F,MATCH(44,Dados!$O:$O,0)) -> 1400000 | K53: =INDEX(Dados!$G:$G,MATCH(44,Dados!$O:$O,0)) -> 17800 | L53: =INDEX(Dados!$J:$J,MATCH(44,Dados!$O:$O,0)) -> 0.3901
A54: =IF(45<=12,"Onda 1 — testar agora",IF(45<=40,"Onda 2 — próximos passos","Onda 3 — depois de consolidar")) -> Onda 3 — depois de consolidar | B54: =INDEX(Dados!$B:$B,MATCH(45,Dados!$O:$O,0)) -> AURA BEAUTY | C54: =INDEX(Dados!$C:$C,MATCH(45,Dados!$O:$O,0)) -> A verificar | D54: =INDEX(Dados!$D:$D,MATCH(45,Dados!$O:$O,0)) -> Não | E54: =INDEX(Dados!$N:$N,MATCH(45,Dados!$O:$O,0)) -> 44.924444 | F54: =INDEX(Dados!$H:$H,MATCH(45,Dados!$O:$O,0)) -> 76.977778 | G54: =INDEX(Dados!$K:$K,MATCH(45,Dados!$O:$O,0)) -> 37 | H54: =INDEX(Dados!$L:$L,MATCH(45,Dados!$O:$O,0)) -> Alta | I54: =INDEX(Dados!$I:$I,MATCH(45,Dados!$O:$O,0)) -> Crescendo | J54: =INDEX(Dados!$F:$F,MATCH(45,Dados!$O:$O,0)) -> 346400 | K54: =INDEX(Dados!$G:$G,MATCH(45,Dados!$O:$O,0)) -> 4500 | L54: =INDEX(Dados!$J:$J,MATCH(45,Dados!$O:$O,0)) -> 0.5082
A55: =IF(46<=12,"Onda 1 — testar agora",IF(46<=40,"Onda 2 — próximos passos","Onda 3 — depois de consolidar")) -> Onda 3 — depois de consolidar | B55: =INDEX(Dados!$B:$B,MATCH(46,Dados!$O:$O,0)) -> NAUTICA | C55: =INDEX(Dados!$C:$C,MATCH(46,Dados!$O:$O,0)) -> Designer/Importado | D55: =INDEX(Dados!$D:$D,MATCH(46,Dados!$O:$O,0)) -> Não | E55: =INDEX(Dados!$N:$N,MATCH(46,Dados!$O:$O,0)) -> 44.891325 | F55: =INDEX(Dados!$H:$H,MATCH(46,Dados!$O:$O,0)) -> 110.23622 | G55: =INDEX(Dados!$K:$K,MATCH(46,Dados!$O:$O,0)) -> 53 | H55: =INDEX(Dados!$L:$L,MATCH(46,Dados!$O:$O,0)) -> Alta | I55: =INDEX(Dados!$I:$I,MATCH(46,Dados!$O:$O,0)) -> Crescendo | J55: =INDEX(Dados!$F:$F,MATCH(46,Dados!$O:$O,0)) -> 1400000 | K55: =INDEX(Dados!$G:$G,MATCH(46,Dados!$O:$O,0)) -> 12700 | L55: =INDEX(Dados!$J:$J,MATCH(46,Dados!$O:$O,0)) -> 0.6536
A56: =IF(47<=12,"Onda 1 — testar agora",IF(47<=40,"Onda 2 — próximos passos","Onda 3 — depois de consolidar")) -> Onda 3 — depois de consolidar | B56: =INDEX(Dados!$B:$B,MATCH(47,Dados!$O:$O,0)) -> ULRIC DE VARENS | C56: =INDEX(Dados!$C:$C,MATCH(47,Dados!$O:$O,0)) -> Designer/Importado | D56: =INDEX(Dados!$D:$D,MATCH(47,Dados!$O:$O,0)) -> Não | E56: =INDEX(Dados!$N:$N,MATCH(47,Dados!$O:$O,0)) -> 44.802144 | F56: =INDEX(Dados!$H:$H,MATCH(47,Dados!$O:$O,0)) -> 82.258065 | G56: =INDEX(Dados!$K:$K,MATCH(47,Dados!$O:$O,0)) -> 43 | H56: =INDEX(Dados!$L:$L,MATCH(47,Dados!$O:$O,0)) -> Alta | I56: =INDEX(Dados!$I:$I,MATCH(47,Dados!$O:$O,0)) -> Crescendo | J56: =INDEX(Dados!$F:$F,MATCH(47,Dados!$O:$O,0)) -> 255000 | K56: =INDEX(Dados!$G:$G,MATCH(47,Dados!$O:$O,0)) -> 3100 | L56: =INDEX(Dados!$J:$J,MATCH(47,Dados!$O:$O,0)) -> 0.4819
A57: =IF(48<=12,"Onda 1 — testar agora",IF(48<=40,"Onda 2 — próximos passos","Onda 3 — depois de consolidar")) -> Onda 3 — depois de consolidar | B57: =INDEX(Dados!$B:$B,MATCH(48,Dados!$O:$O,0)) -> WEPINK | C57: =INDEX(Dados!$C:$C,MATCH(48,Dados!$O:$O,0)) -> Nacional/Massa | D57: =INDEX(Dados!$D:$D,MATCH(48,Dados!$O:$O,0)) -> Não | E57: =INDEX(Dados!$N:$N,MATCH(48,Dados!$O:$O,0)) -> 44.772237 | F57: =INDEX(Dados!$H:$H,MATCH(48,Dados!$O:$O,0)) -> 106.87023 | G57: =INDEX(Dados!$K:$K,MATCH(48,Dados!$O:$O,0)) -> 55 | H57: =INDEX(Dados!$L:$L,MATCH(48,Dados!$O:$O,0)) -> Baixa | I57: =INDEX(Dados!$I:$I,MATCH(48,Dados!$O:$O,0)) -> Diminuindo | J57: =INDEX(Dados!$F:$F,MATCH(48,Dados!$O:$O,0)) -> 1400000 | K57: =INDEX(Dados!$G:$G,MATCH(48,Dados!$O:$O,0)) -> 13100 | L57: =INDEX(Dados!$J:$J,MATCH(48,Dados!$O:$O,0)) -> 0.6097
A58: =IF(49<=12,"Onda 1 — testar agora",IF(49<=40,"Onda 2 — próximos passos","Onda 3 — depois de consolidar")) -> Onda 3 — depois de consolidar | B58: =INDEX(Dados!$B:$B,MATCH(49,Dados!$O:$O,0)) -> FRAGRANCE WORLD | C58: =INDEX(Dados!$C:$C,MATCH(49,Dados!$O:$O,0)) -> Árabe/Import Acessível | D58: =INDEX(Dados!$D:$D,MATCH(49,Dados!$O:$O,0)) -> Não | E58: =INDEX(Dados!$N:$N,MATCH(49,Dados!$O:$O,0)) -> 44.668923 | F58: =INDEX(Dados!$H:$H,MATCH(49,Dados!$O:$O,0)) -> 164.31818 | G58: =INDEX(Dados!$K:$K,MATCH(49,Dados!$O:$O,0)) -> 84 | H58: =INDEX(Dados!$L:$L,MATCH(49,Dados!$O:$O,0)) -> Alta | I58: =INDEX(Dados!$I:$I,MATCH(49,Dados!$O:$O,0)) -> Crescendo | J58: =INDEX(Dados!$F:$F,MATCH(49,Dados!$O:$O,0)) -> 361500 | K58: =INDEX(Dados!$G:$G,MATCH(49,Dados!$O:$O,0)) -> 2200 | L58: =INDEX(Dados!$J:$J,MATCH(49,Dados!$O:$O,0)) -> 0.7273
A59: =IF(50<=12,"Onda 1 — testar agora",IF(50<=40,"Onda 2 — próximos passos","Onda 3 — depois de consolidar")) -> Onda 3 — depois de consolidar | B59: =INDEX(Dados!$B:$B,MATCH(50,Dados!$O:$O,0)) -> HINODE | C59: =INDEX(Dados!$C:$C,MATCH(50,Dados!$O:$O,0)) -> Nacional/Massa | D59: =INDEX(Dados!$D:$D,MATCH(50,Dados!$O:$O,0)) -> Não | E59: =INDEX(Dados!$N:$N,MATCH(50,Dados!$O:$O,0)) -> 44.666039 | F59: =INDEX(Dados!$H:$H,MATCH(50,Dados!$O:$O,0)) -> 104.34783 | G59: =INDEX(Dados!$K:$K,MATCH(50,Dados!$O:$O,0)) -> 57 | H59: =INDEX(Dados!$L:$L,MATCH(50,Dados!$O:$O,0)) -> Baixa | I59: =INDEX(Dados!$I:$I,MATCH(50,Dados!$O:$O,0)) -> Diminuindo | J59: =INDEX(Dados!$F:$F,MATCH(50,Dados!$O:$O,0)) -> 1200000 | K59: =INDEX(Dados!$G:$G,MATCH(50,Dados!$O:$O,0)) -> 11500 | L59: =INDEX(Dados!$J:$J,MATCH(50,Dados!$O:$O,0)) -> 0.6262
A60: =IF(51<=12,"Onda 1 — testar agora",IF(51<=40,"Onda 2 — próximos passos","Onda 3 — depois de consolidar")) -> Onda 3 — depois de consolidar | B60: =INDEX(Dados!$B:$B,MATCH(51,Dados!$O:$O,0)) -> PARIS ELYSEES | C60: =INDEX(Dados!$C:$C,MATCH(51,Dados!$O:$O,0)) -> Nacional/Massa | D60: =INDEX(Dados!$D:$D,MATCH(51,Dados!$O:$O,0)) -> Não | E60: =INDEX(Dados!$N:$N,MATCH(51,Dados!$O:$O,0)) -> 44.334765 | F60: =INDEX(Dados!$H:$H,MATCH(51,Dados!$O:$O,0)) -> 73.809524 | G60: =INDEX(Dados!$K:$K,MATCH(51,Dados!$O:$O,0)) -> 53 | H60: =INDEX(Dados!$L:$L,MATCH(51,Dados!$O:$O,0)) -> Alta | I60: =INDEX(Dados!$I:$I,MATCH(51,Dados!$O:$O,0)) -> Crescendo | J60: =INDEX(Dados!$F:$F,MATCH(51,Dados!$O:$O,0)) -> 3100000 | K60: =INDEX(Dados!$G:$G,MATCH(51,Dados!$O:$O,0)) -> 42000 | L60: =INDEX(Dados!$J:$J,MATCH(51,Dados!$O:$O,0)) -> 0.5089
A61: =IF(52<=12,"Onda 1 — testar agora",IF(52<=40,"Onda 2 — próximos passos","Onda 3 — depois de consolidar")) -> Onda 3 — depois de consolidar | B61: =INDEX(Dados!$B:$B,MATCH(52,Dados!$O:$O,0)) -> CUBA PARIS | C61: =INDEX(Dados!$C:$C,MATCH(52,Dados!$O:$O,0)) -> Designer/Importado | D61: =INDEX(Dados!$D:$D,MATCH(52,Dados!$O:$O,0)) -> Não | E61: =INDEX(Dados!$N:$N,MATCH(52,Dados!$O:$O,0)) -> 44.309904 | F61: =INDEX(Dados!$H:$H,MATCH(52,Dados!$O:$O,0)) -> 65.54 | G61: =INDEX(Dados!$K:$K,MATCH(52,Dados!$O:$O,0)) -> 50 | H61: =INDEX(Dados!$L:$L,MATCH(52,Dados!$O:$O,0)) -> Média | I61: =INDEX(Dados!$I:$I,MATCH(52,Dados!$O:$O,0)) -> Estável | J61: =INDEX(Dados!$F:$F,MATCH(52,Dados!$O:$O,0)) -> 327700 | K61: =INDEX(Dados!$G:$G,MATCH(52,Dados!$O:$O,0)) -> 5000 | L61: =INDEX(Dados!$J:$J,MATCH(52,Dados!$O:$O,0)) -> 0.5862
A62: =IF(53<=12,"Onda 1 — testar agora",IF(53<=40,"Onda 2 — próximos passos","Onda 3 — depois de consolidar")) -> Onda 3 — depois de consolidar | B62: =INDEX(Dados!$B:$B,MATCH(53,Dados!$O:$O,0)) -> CICLO | C62: =INDEX(Dados!$C:$C,MATCH(53,Dados!$O:$O,0)) -> Nacional/Massa | D62: =INDEX(Dados!$D:$D,MATCH(53,Dados!$O:$O,0)) -> Não | E62: =INDEX(Dados!$N:$N,MATCH(53,Dados!$O:$O,0)) -> 43.863355 | F62: =INDEX(Dados!$H:$H,MATCH(53,Dados!$O:$O,0)) -> 69.525424 | G62: =INDEX(Dados!$K:$K,MATCH(53,Dados!$O:$O,0)) -> 65 | H62: =INDEX(Dados!$L:$L,MATCH(53,Dados!$O:$O,0)) -> Alta | I62: =INDEX(Dados!$I:$I,MATCH(53,Dados!$O:$O,0)) -> Crescendo | J62: =INDEX(Dados!$F:$F,MATCH(53,Dados!$O:$O,0)) -> 820400 | K62: =INDEX(Dados!$G:$G,MATCH(53,Dados!$O:$O,0)) -> 11800 | L62: =INDEX(Dados!$J:$J,MATCH(53,Dados!$O:$O,0)) -> 0.5895
A63: =IF(54<=12,"Onda 1 — testar agora",IF(54<=40,"Onda 2 — próximos passos","Onda 3 — depois de consolidar")) -> Onda 3 — depois de consolidar | B63: =INDEX(Dados!$B:$B,MATCH(54,Dados!$O:$O,0)) -> LA RIVE | C63: =INDEX(Dados!$C:$C,MATCH(54,Dados!$O:$O,0)) -> Importado Acessível/Contratipo | D63: =INDEX(Dados!$D:$D,MATCH(54,Dados!$O:$O,0)) -> Não | E63: =INDEX(Dados!$N:$N,MATCH(54,Dados!$O:$O,0)) -> 43.587989 | F63: =INDEX(Dados!$H:$H,MATCH(54,Dados!$O:$O,0)) -> 75.858268 | G63: =INDEX(Dados!$K:$K,MATCH(54,Dados!$O:$O,0)) -> 76 | H63: =INDEX(Dados!$L:$L,MATCH(54,Dados!$O:$O,0)) -> Alta | I63: =INDEX(Dados!$I:$I,MATCH(54,Dados!$O:$O,0)) -> Crescendo | J63: =INDEX(Dados!$F:$F,MATCH(54,Dados!$O:$O,0)) -> 963400 | K63: =INDEX(Dados!$G:$G,MATCH(54,Dados!$O:$O,0)) -> 12700 | L63: =INDEX(Dados!$J:$J,MATCH(54,Dados!$O:$O,0)) -> 0.5669
A64: =IF(55<=12,"Onda 1 — testar agora",IF(55<=40,"Onda 2 — próximos passos","Onda 3 — depois de consolidar")) -> Onda 3 — depois de consolidar | B64: =INDEX(Dados!$B:$B,MATCH(55,Dados!$O:$O,0)) -> VICTORIA'S SECRET | C64: =INDEX(Dados!$C:$C,MATCH(55,Dados!$O:$O,0)) -> Designer/Importado | D64: =INDEX(Dados!$D:$D,MATCH(55,Dados!$O:$O,0)) -> Não | E64: =INDEX(Dados!$N:$N,MATCH(55,Dados!$O:$O,0)) -> 43.50969 | F64: =INDEX(Dados!$H:$H,MATCH(55,Dados!$O:$O,0)) -> 143.8 | G64: =INDEX(Dados!$K:$K,MATCH(55,Dados!$O:$O,0)) -> 109 | H64: =INDEX(Dados!$L:$L,MATCH(55,Dados!$O:$O,0)) -> Baixa | I64: =INDEX(Dados!$I:$I,MATCH(55,Dados!$O:$O,0)) -> Diminuindo | J64: =INDEX(Dados!$F:$F,MATCH(55,Dados!$O:$O,0)) -> 862800 | K64: =INDEX(Dados!$G:$G,MATCH(55,Dados!$O:$O,0)) -> 6000 | L64: =INDEX(Dados!$J:$J,MATCH(55,Dados!$O:$O,0)) -> 0.7192
A65: =IF(56<=12,"Onda 1 — testar agora",IF(56<=40,"Onda 2 — próximos passos","Onda 3 — depois de consolidar")) -> Onda 3 — depois de consolidar | B65: =INDEX(Dados!$B:$B,MATCH(56,Dados!$O:$O,0)) -> CAROLINA HERRERA | C65: =INDEX(Dados!$C:$C,MATCH(56,Dados!$O:$O,0)) -> Designer/Importado | D65: =INDEX(Dados!$D:$D,MATCH(56,Dados!$O:$O,0)) -> Não | E65: =INDEX(Dados!$N:$N,MATCH(56,Dados!$O:$O,0)) -> 42.010985 | F65: =INDEX(Dados!$H:$H,MATCH(56,Dados!$O:$O,0)) -> 523.07692 | G65: =INDEX(Dados!$K:$K,MATCH(56,Dados!$O:$O,0)) -> 29 | H65: =INDEX(Dados!$L:$L,MATCH(56,Dados!$O:$O,0)) -> Alta | I65: =INDEX(Dados!$I:$I,MATCH(56,Dados!$O:$O,0)) -> Estável | J65: =INDEX(Dados!$F:$F,MATCH(56,Dados!$O:$O,0)) -> 10200000 | K65: =INDEX(Dados!$G:$G,MATCH(56,Dados!$O:$O,0)) -> 19500 | L65: =INDEX(Dados!$J:$J,MATCH(56,Dados!$O:$O,0)) -> 0.6718
A66: =IF(57<=12,"Onda 1 — testar agora",IF(57<=40,"Onda 2 — próximos passos","Onda 3 — depois de consolidar")) -> Onda 3 — depois de consolidar | B66: =INDEX(Dados!$B:$B,MATCH(57,Dados!$O:$O,0)) -> CHLOÉ | C66: =INDEX(Dados!$C:$C,MATCH(57,Dados!$O:$O,0)) -> Designer/Importado | D66: =INDEX(Dados!$D:$D,MATCH(57,Dados!$O:$O,0)) -> Não | E66: =INDEX(Dados!$N:$N,MATCH(57,Dados!$O:$O,0)) -> 41.7662 | F66: =INDEX(Dados!$H:$H,MATCH(57,Dados!$O:$O,0)) -> 562.40914 | G66: =INDEX(Dados!$K:$K,MATCH(57,Dados!$O:$O,0)) -> 54 | H66: =INDEX(Dados!$L:$L,MATCH(57,Dados!$O:$O,0)) -> Média | I66: =INDEX(Dados!$I:$I,MATCH(57,Dados!$O:$O,0)) -> Diminuindo | J66: =INDEX(Dados!$F:$F,MATCH(57,Dados!$O:$O,0)) -> 541600 | K66: =INDEX(Dados!$G:$G,MATCH(57,Dados!$O:$O,0)) -> 963 | L66: =INDEX(Dados!$J:$J,MATCH(57,Dados!$O:$O,0)) -> 0.7429
A67: =IF(58<=12,"Onda 1 — testar agora",IF(58<=40,"Onda 2 — próximos passos","Onda 3 — depois de consolidar")) -> Onda 3 — depois de consolidar | B67: =INDEX(Dados!$B:$B,MATCH(58,Dados!$O:$O,0)) -> JEQUITI | C67: =INDEX(Dados!$C:$C,MATCH(58,Dados!$O:$O,0)) -> Nacional/Massa | D67: =INDEX(Dados!$D:$D,MATCH(58,Dados!$O:$O,0)) -> Não | E67: =INDEX(Dados!$N:$N,MATCH(58,Dados!$O:$O,0)) -> 41.420254 | F67: =INDEX(Dados!$H:$H,MATCH(58,Dados!$O:$O,0)) -> 35.830619 | G67: =INDEX(Dados!$K:$K,MATCH(58,Dados!$O:$O,0)) -> 122 | H67: =INDEX(Dados!$L:$L,MATCH(58,Dados!$O:$O,0)) -> Alta | I67: =INDEX(Dados!$I:$I,MATCH(58,Dados!$O:$O,0)) -> Crescendo | J67: =INDEX(Dados!$F:$F,MATCH(58,Dados!$O:$O,0)) -> 2200000 | K67: =INDEX(Dados!$G:$G,MATCH(58,Dados!$O:$O,0)) -> 61400 | L67: =INDEX(Dados!$J:$J,MATCH(58,Dados!$O:$O,0)) -> 0.5443
A68: =IF(59<=12,"Onda 1 — testar agora",IF(59<=40,"Onda 2 — próximos passos","Onda 3 — depois de consolidar")) -> Onda 3 — depois de consolidar | B68: =INDEX(Dados!$B:$B,MATCH(59,Dados!$O:$O,0)) -> GIVENCHY | C68: =INDEX(Dados!$C:$C,MATCH(59,Dados!$O:$O,0)) -> Designer/Importado | D68: =INDEX(Dados!$D:$D,MATCH(59,Dados!$O:$O,0)) -> Não | E68: =INDEX(Dados!$N:$N,MATCH(59,Dados!$O:$O,0)) -> 40.356532 | F68: =INDEX(Dados!$H:$H,MATCH(59,Dados!$O:$O,0)) -> 525.5 | G68: =INDEX(Dados!$K:$K,MATCH(59,Dados!$O:$O,0)) -> 79 | H68: =INDEX(Dados!$L:$L,MATCH(59,Dados!$O:$O,0)) -> Média | I68: =INDEX(Dados!$I:$I,MATCH(59,Dados!$O:$O,0)) -> Diminuindo | J68: =INDEX(Dados!$F:$F,MATCH(59,Dados!$O:$O,0)) -> 630600 | K68: =INDEX(Dados!$G:$G,MATCH(59,Dados!$O:$O,0)) -> 1200 | L68: =INDEX(Dados!$J:$J,MATCH(59,Dados!$O:$O,0)) -> 0.7158
A69: =IF(60<=12,"Onda 1 — testar agora",IF(60<=40,"Onda 2 — próximos passos","Onda 3 — depois de consolidar")) -> Onda 3 — depois de consolidar | B69: =INDEX(Dados!$B:$B,MATCH(60,Dados!$O:$O,0)) -> ARMAF | C69: =INDEX(Dados!$C:$C,MATCH(60,Dados!$O:$O,0)) -> Árabe/Import Acessível | D69: =INDEX(Dados!$D:$D,MATCH(60,Dados!$O:$O,0)) -> Não | E69: =INDEX(Dados!$N:$N,MATCH(60,Dados!$O:$O,0)) -> 39.800928 | F69: =INDEX(Dados!$H:$H,MATCH(60,Dados!$O:$O,0)) -> 244.25287 | G69: =INDEX(Dados!$K:$K,MATCH(60,Dados!$O:$O,0)) -> 264 | H69: =INDEX(Dados!$L:$L,MATCH(60,Dados!$O:$O,0)) -> Alta | I69: =INDEX(Dados!$I:$I,MATCH(60,Dados!$O:$O,0)) -> Crescendo | J69: =INDEX(Dados!$F:$F,MATCH(60,Dados!$O:$O,0)) -> 8500000 | K69: =INDEX(Dados!$G:$G,MATCH(60,Dados!$O:$O,0)) -> 34800 | L69: =INDEX(Dados!$J:$J,MATCH(60,Dados!$O:$O,0)) -> 0.6872
A70: =IF(61<=12,"Onda 1 — testar agora",IF(61<=40,"Onda 2 — próximos passos","Onda 3 — depois de consolidar")) -> Onda 3 — depois de consolidar | B70: =INDEX(Dados!$B:$B,MATCH(61,Dados!$O:$O,0)) -> DOLCE & GABBANA | C70: =INDEX(Dados!$C:$C,MATCH(61,Dados!$O:$O,0)) -> Designer/Importado | D70: =INDEX(Dados!$D:$D,MATCH(61,Dados!$O:$O,0)) -> Não | E70: =INDEX(Dados!$N:$N,MATCH(61,Dados!$O:$O,0)) -> 39.053523 | F70: =INDEX(Dados!$H:$H,MATCH(61,Dados!$O:$O,0)) -> 500 | G70: =INDEX(Dados!$K:$K,MATCH(61,Dados!$O:$O,0)) -> 106 | H70: =INDEX(Dados!$L:$L,MATCH(61,Dados!$O:$O,0)) -> Média | I70: =INDEX(Dados!$I:$I,MATCH(61,Dados!$O:$O,0)) -> Diminuindo | J70: =INDEX(Dados!$F:$F,MATCH(61,Dados!$O:$O,0)) -> 1900000 | K70: =INDEX(Dados!$G:$G,MATCH(61,Dados!$O:$O,0)) -> 3800 | L70: =INDEX(Dados!$J:$J,MATCH(61,Dados!$O:$O,0)) -> 0.7247
A71: =IF(62<=12,"Onda 1 — testar agora",IF(62<=40,"Onda 2 — próximos passos","Onda 3 — depois de consolidar")) -> Onda 3 — depois de consolidar | B71: =INDEX(Dados!$B:$B,MATCH(62,Dados!$O:$O,0)) -> MONTBLANC | C71: =INDEX(Dados!$C:$C,MATCH(62,Dados!$O:$O,0)) -> Designer/Importado Premium | D71: =INDEX(Dados!$D:$D,MATCH(62,Dados!$O:$O,0)) -> Não | E71: =INDEX(Dados!$N:$N,MATCH(62,Dados!$O:$O,0)) -> 38.219578 | F71: =INDEX(Dados!$H:$H,MATCH(62,Dados!$O:$O,0)) -> 403.35 | G71: =INDEX(Dados!$K:$K,MATCH(62,Dados!$O:$O,0)) -> 87 | H71: =INDEX(Dados!$L:$L,MATCH(62,Dados!$O:$O,0)) -> Média | I71: =INDEX(Dados!$I:$I,MATCH(62,Dados!$O:$O,0)) -> Diminuindo | J71: =INDEX(Dados!$F:$F,MATCH(62,Dados!$O:$O,0)) -> 806700 | K71: =INDEX(Dados!$G:$G,MATCH(62,Dados!$O:$O,0)) -> 2000 | L71: =INDEX(Dados!$J:$J,MATCH(62,Dados!$O:$O,0)) -> 0.6828
A72: =IF(63<=12,"Onda 1 — testar agora",IF(63<=40,"Onda 2 — próximos passos","Onda 3 — depois de consolidar")) -> Onda 3 — depois de consolidar | B72: =INDEX(Dados!$B:$B,MATCH(63,Dados!$O:$O,0)) -> L'ACQUA DI FIORI | C72: =INDEX(Dados!$C:$C,MATCH(63,Dados!$O:$O,0)) -> A verificar | D72: =INDEX(Dados!$D:$D,MATCH(63,Dados!$O:$O,0)) -> Não | E72: =INDEX(Dados!$N:$N,MATCH(63,Dados!$O:$O,0)) -> 37.647667 | F72: =INDEX(Dados!$H:$H,MATCH(63,Dados!$O:$O,0)) -> 222 | G72: =INDEX(Dados!$K:$K,MATCH(63,Dados!$O:$O,0)) -> 22 | H72: =INDEX(Dados!$L:$L,MATCH(63,Dados!$O:$O,0)) -> Média | I72: =INDEX(Dados!$I:$I,MATCH(63,Dados!$O:$O,0)) -> Diminuindo | J72: =INDEX(Dados!$F:$F,MATCH(63,Dados!$O:$O,0)) -> 288600 | K72: =INDEX(Dados!$G:$G,MATCH(63,Dados!$O:$O,0)) -> 1300 | L72: =INDEX(Dados!$J:$J,MATCH(63,Dados!$O:$O,0)) -> 0.6218
A73: =IF(64<=12,"Onda 1 — testar agora",IF(64<=40,"Onda 2 — próximos passos","Onda 3 — depois de consolidar")) -> Onda 3 — depois de consolidar | B73: =INDEX(Dados!$B:$B,MATCH(64,Dados!$O:$O,0)) -> LAB8 FLUY | C73: =INDEX(Dados!$C:$C,MATCH(64,Dados!$O:$O,0)) -> A verificar | D73: =INDEX(Dados!$D:$D,MATCH(64,Dados!$O:$O,0)) -> Não | E73: =INDEX(Dados!$N:$N,MATCH(64,Dados!$O:$O,0)) -> 37.015978 | F73: =INDEX(Dados!$H:$H,MATCH(64,Dados!$O:$O,0)) -> 200.58333 | G73: =INDEX(Dados!$K:$K,MATCH(64,Dados!$O:$O,0)) -> 31 | H73: =INDEX(Dados!$L:$L,MATCH(64,Dados!$O:$O,0)) -> Média | I73: =INDEX(Dados!$I:$I,MATCH(64,Dados!$O:$O,0)) -> Diminuindo | J73: =INDEX(Dados!$F:$F,MATCH(64,Dados!$O:$O,0)) -> 722100 | K73: =INDEX(Dados!$G:$G,MATCH(64,Dados!$O:$O,0)) -> 3600 | L73: =INDEX(Dados!$J:$J,MATCH(64,Dados!$O:$O,0)) -> 0.6489
A74: =IF(65<=12,"Onda 1 — testar agora",IF(65<=40,"Onda 2 — próximos passos","Onda 3 — depois de consolidar")) -> Onda 3 — depois de consolidar | B74: =INDEX(Dados!$B:$B,MATCH(65,Dados!$O:$O,0)) -> AZZARO | C74: =INDEX(Dados!$C:$C,MATCH(65,Dados!$O:$O,0)) -> Designer/Importado | D74: =INDEX(Dados!$D:$D,MATCH(65,Dados!$O:$O,0)) -> Não | E74: =INDEX(Dados!$N:$N,MATCH(65,Dados!$O:$O,0)) -> 36.914159 | F74: =INDEX(Dados!$H:$H,MATCH(65,Dados!$O:$O,0)) -> 337.83784 | G74: =INDEX(Dados!$K:$K,MATCH(65,Dados!$O:$O,0)) -> 96 | H74: =INDEX(Dados!$L:$L,MATCH(65,Dados!$O:$O,0)) -> Alta | I74: =INDEX(Dados!$I:$I,MATCH(65,Dados!$O:$O,0)) -> Estável | J74: =INDEX(Dados!$F:$F,MATCH(65,Dados!$O:$O,0)) -> 2500000 | K74: =INDEX(Dados!$G:$G,MATCH(65,Dados!$O:$O,0)) -> 7400 | L74: =INDEX(Dados!$J:$J,MATCH(65,Dados!$O:$O,0)) -> 0.6694
A75: =IF(66<=12,"Onda 1 — testar agora",IF(66<=40,"Onda 2 — próximos passos","Onda 3 — depois de consolidar")) -> Onda 3 — depois de consolidar | B75: =INDEX(Dados!$B:$B,MATCH(66,Dados!$O:$O,0)) -> THIERRY MUGLER | C75: =INDEX(Dados!$C:$C,MATCH(66,Dados!$O:$O,0)) -> Designer/Importado | D75: =INDEX(Dados!$D:$D,MATCH(66,Dados!$O:$O,0)) -> Não | E75: =INDEX(Dados!$N:$N,MATCH(66,Dados!$O:$O,0)) -> 36.901363 | F75: =INDEX(Dados!$H:$H,MATCH(66,Dados!$O:$O,0)) -> 787.79762 | G75: =INDEX(Dados!$K:$K,MATCH(66,Dados!$O:$O,0)) -> 4 | H75: =INDEX(Dados!$L:$L,MATCH(66,Dados!$O:$O,0)) -> Alta | I75: =INDEX(Dados!$I:$I,MATCH(66,Dados!$O:$O,0)) -> Diminuindo | J75: =INDEX(Dados!$F:$F,MATCH(66,Dados!$O:$O,0)) -> 264700 | K75: =INDEX(Dados!$G:$G,MATCH(66,Dados!$O:$O,0)) -> 336 | L75: =INDEX(Dados!$J:$J,MATCH(66,Dados!$O:$O,0)) -> 0.4737
A76: =IF(67<=12,"Onda 1 — testar agora",IF(67<=40,"Onda 2 — próximos passos","Onda 3 — depois de consolidar")) -> Onda 3 — depois de consolidar | B76: =INDEX(Dados!$B:$B,MATCH(67,Dados!$O:$O,0)) -> KHADLAJ | C76: =INDEX(Dados!$C:$C,MATCH(67,Dados!$O:$O,0)) -> Árabe/Import Acessível | D76: =INDEX(Dados!$D:$D,MATCH(67,Dados!$O:$O,0)) -> Não | E76: =INDEX(Dados!$N:$N,MATCH(67,Dados!$O:$O,0)) -> 36.468318 | F76: =INDEX(Dados!$H:$H,MATCH(67,Dados!$O:$O,0)) -> 213.45 | G76: =INDEX(Dados!$K:$K,MATCH(67,Dados!$O:$O,0)) -> 53 | H76: =INDEX(Dados!$L:$L,MATCH(67,Dados!$O:$O,0)) -> Média | I76: =INDEX(Dados!$I:$I,MATCH(67,Dados!$O:$O,0)) -> Diminuindo | J76: =INDEX(Dados!$F:$F,MATCH(67,Dados!$O:$O,0)) -> 426900 | K76: =INDEX(Dados!$G:$G,MATCH(67,Dados!$O:$O,0)) -> 2000 | L76: =INDEX(Dados!$J:$J,MATCH(67,Dados!$O:$O,0)) -> 0.6425
A77: =IF(68<=12,"Onda 1 — testar agora",IF(68<=40,"Onda 2 — próximos passos","Onda 3 — depois de consolidar")) -> Onda 3 — depois de consolidar | B77: =INDEX(Dados!$B:$B,MATCH(68,Dados!$O:$O,0)) -> MAHOGANY | C77: =INDEX(Dados!$C:$C,MATCH(68,Dados!$O:$O,0)) -> Nacional/Massa | D77: =INDEX(Dados!$D:$D,MATCH(68,Dados!$O:$O,0)) -> Não | E77: =INDEX(Dados!$N:$N,MATCH(68,Dados!$O:$O,0)) -> 35.871505 | F77: =INDEX(Dados!$H:$H,MATCH(68,Dados!$O:$O,0)) -> 156.67568 | G77: =INDEX(Dados!$K:$K,MATCH(68,Dados!$O:$O,0)) -> 45 | H77: =INDEX(Dados!$L:$L,MATCH(68,Dados!$O:$O,0)) -> Média | I77: =INDEX(Dados!$I:$I,MATCH(68,Dados!$O:$O,0)) -> Diminuindo | J77: =INDEX(Dados!$F:$F,MATCH(68,Dados!$O:$O,0)) -> 579700 | K77: =INDEX(Dados!$G:$G,MATCH(68,Dados!$O:$O,0)) -> 3700 | L77: =INDEX(Dados!$J:$J,MATCH(68,Dados!$O:$O,0)) -> 0.6827
A78: =IF(69<=12,"Onda 1 — testar agora",IF(69<=40,"Onda 2 — próximos passos","Onda 3 — depois de consolidar")) -> Onda 3 — depois de consolidar | B78: =INDEX(Dados!$B:$B,MATCH(69,Dados!$O:$O,0)) -> CALVIN KLEIN | C78: =INDEX(Dados!$C:$C,MATCH(69,Dados!$O:$O,0)) -> Designer/Importado | D78: =INDEX(Dados!$D:$D,MATCH(69,Dados!$O:$O,0)) -> Não | E78: =INDEX(Dados!$N:$N,MATCH(69,Dados!$O:$O,0)) -> 35.723507 | F78: =INDEX(Dados!$H:$H,MATCH(69,Dados!$O:$O,0)) -> 282.05128 | G78: =INDEX(Dados!$K:$K,MATCH(69,Dados!$O:$O,0)) -> 106 | H78: =INDEX(Dados!$L:$L,MATCH(69,Dados!$O:$O,0)) -> Alta | I78: =INDEX(Dados!$I:$I,MATCH(69,Dados!$O:$O,0)) -> Estável | J78: =INDEX(Dados!$F:$F,MATCH(69,Dados!$O:$O,0)) -> 2200000 | K78: =INDEX(Dados!$G:$G,MATCH(69,Dados!$O:$O,0)) -> 7800 | L78: =INDEX(Dados!$J:$J,MATCH(69,Dados!$O:$O,0)) -> 0.7126
A79: =IF(70<=12,"Onda 1 — testar agora",IF(70<=40,"Onda 2 — próximos passos","Onda 3 — depois de consolidar")) -> Onda 3 — depois de consolidar | B79: =INDEX(Dados!$B:$B,MATCH(70,Dados!$O:$O,0)) -> TOUTI | C79: =INDEX(Dados!$C:$C,MATCH(70,Dados!$O:$O,0)) -> A verificar | D79: =INDEX(Dados!$D:$D,MATCH(70,Dados!$O:$O,0)) -> Não | E79: =INDEX(Dados!$N:$N,MATCH(70,Dados!$O:$O,0)) -> 35.64521 | F79: =INDEX(Dados!$H:$H,MATCH(70,Dados!$O:$O,0)) -> 73.226667 | G79: =INDEX(Dados!$K:$K,MATCH(70,Dados!$O:$O,0)) -> 14 | H79: =INDEX(Dados!$L:$L,MATCH(70,Dados!$O:$O,0)) -> Média | I79: =INDEX(Dados!$I:$I,MATCH(70,Dados!$O:$O,0)) -> Diminuindo | J79: =INDEX(Dados!$F:$F,MATCH(70,Dados!$O:$O,0)) -> 549200 | K79: =INDEX(Dados!$G:$G,MATCH(70,Dados!$O:$O,0)) -> 7500 | L79: =INDEX(Dados!$J:$J,MATCH(70,Dados!$O:$O,0)) -> 0.424
A80: =IF(71<=12,"Onda 1 — testar agora",IF(71<=40,"Onda 2 — próximos passos","Onda 3 — depois de consolidar")) -> Onda 3 — depois de consolidar | B80: =INDEX(Dados!$B:$B,MATCH(71,Dados!$O:$O,0)) -> MAISON ALHAMBRA | C80: =INDEX(Dados!$C:$C,MATCH(71,Dados!$O:$O,0)) -> Árabe/Import Acessível | D80: =INDEX(Dados!$D:$D,MATCH(71,Dados!$O:$O,0)) -> Não | E80: =INDEX(Dados!$N:$N,MATCH(71,Dados!$O:$O,0)) -> 34.885023 | F80: =INDEX(Dados!$H:$H,MATCH(71,Dados!$O:$O,0)) -> 159.42029 | G80: =INDEX(Dados!$K:$K,MATCH(71,Dados!$O:$O,0)) -> 371 | H80: =INDEX(Dados!$L:$L,MATCH(71,Dados!$O:$O,0)) -> Média | I80: =INDEX(Dados!$I:$I,MATCH(71,Dados!$O:$O,0)) -> Estável | J80: =INDEX(Dados!$F:$F,MATCH(71,Dados!$O:$O,0)) -> 4400000 | K80: =INDEX(Dados!$G:$G,MATCH(71,Dados!$O:$O,0)) -> 27600 | L80: =INDEX(Dados!$J:$J,MATCH(71,Dados!$O:$O,0)) -> 0.6829
A81: =IF(72<=12,"Onda 1 — testar agora",IF(72<=40,"Onda 2 — próximos passos","Onda 3 — depois de consolidar")) -> Onda 3 — depois de consolidar | B81: =INDEX(Dados!$B:$B,MATCH(72,Dados!$O:$O,0)) -> GUCCI | C81: =INDEX(Dados!$C:$C,MATCH(72,Dados!$O:$O,0)) -> Designer/Importado | D81: =INDEX(Dados!$D:$D,MATCH(72,Dados!$O:$O,0)) -> Não | E81: =INDEX(Dados!$N:$N,MATCH(72,Dados!$O:$O,0)) -> 33.974829 | F81: =INDEX(Dados!$H:$H,MATCH(72,Dados!$O:$O,0)) -> 658.25243 | G81: =INDEX(Dados!$K:$K,MATCH(72,Dados!$O:$O,0)) -> 32 | H81: =INDEX(Dados!$L:$L,MATCH(72,Dados!$O:$O,0)) -> Alta | I81: =INDEX(Dados!$I:$I,MATCH(72,Dados!$O:$O,0)) -> Diminuindo | J81: =INDEX(Dados!$F:$F,MATCH(72,Dados!$O:$O,0)) -> 271200 | K81: =INDEX(Dados!$G:$G,MATCH(72,Dados!$O:$O,0)) -> 412 | L81: =INDEX(Dados!$J:$J,MATCH(72,Dados!$O:$O,0)) -> 0.7015
A82: =IF(73<=12,"Onda 1 — testar agora",IF(73<=40,"Onda 2 — próximos passos","Onda 3 — depois de consolidar")) -> Onda 3 — depois de consolidar | B82: =INDEX(Dados!$B:$B,MATCH(73,Dados!$O:$O,0)) -> EUDORA | C82: =INDEX(Dados!$C:$C,MATCH(73,Dados!$O:$O,0)) -> Nacional/Massa | D82: =INDEX(Dados!$D:$D,MATCH(73,Dados!$O:$O,0)) -> Não | E82: =INDEX(Dados!$N:$N,MATCH(73,Dados!$O:$O,0)) -> 33.826316 | F82: =INDEX(Dados!$H:$H,MATCH(73,Dados!$O:$O,0)) -> 98.984772 | G82: =INDEX(Dados!$K:$K,MATCH(73,Dados!$O:$O,0)) -> 375 | H82: =INDEX(Dados!$L:$L,MATCH(73,Dados!$O:$O,0)) -> Alta | I82: =INDEX(Dados!$I:$I,MATCH(73,Dados!$O:$O,0)) -> Crescendo | J82: =INDEX(Dados!$F:$F,MATCH(73,Dados!$O:$O,0)) -> 3900000 | K82: =INDEX(Dados!$G:$G,MATCH(73,Dados!$O:$O,0)) -> 39400 | L82: =INDEX(Dados!$J:$J,MATCH(73,Dados!$O:$O,0)) -> 0.6278
A83: =IF(74<=12,"Onda 1 — testar agora",IF(74<=40,"Onda 2 — próximos passos","Onda 3 — depois de consolidar")) -> Onda 3 — depois de consolidar | B83: =INDEX(Dados!$B:$B,MATCH(74,Dados!$O:$O,0)) -> MUGLER | C83: =INDEX(Dados!$C:$C,MATCH(74,Dados!$O:$O,0)) -> Designer/Importado | D83: =INDEX(Dados!$D:$D,MATCH(74,Dados!$O:$O,0)) -> Não | E83: =INDEX(Dados!$N:$N,MATCH(74,Dados!$O:$O,0)) -> 33.550578 | F83: =INDEX(Dados!$H:$H,MATCH(74,Dados!$O:$O,0)) -> 568.48958 | G83: =INDEX(Dados!$K:$K,MATCH(74,Dados!$O:$O,0)) -> 4 | H83: =INDEX(Dados!$L:$L,MATCH(74,Dados!$O:$O,0)) -> Alta | I83: =INDEX(Dados!$I:$I,MATCH(74,Dados!$O:$O,0)) -> Diminuindo | J83: =INDEX(Dados!$F:$F,MATCH(74,Dados!$O:$O,0)) -> 436600 | K83: =INDEX(Dados!$G:$G,MATCH(74,Dados!$O:$O,0)) -> 768 | L83: =INDEX(Dados!$J:$J,MATCH(74,Dados!$O:$O,0)) -> 0.75
A84: =IF(75<=12,"Onda 1 — testar agora",IF(75<=40,"Onda 2 — próximos passos","Onda 3 — depois de consolidar")) -> Onda 3 — depois de consolidar | B84: =INDEX(Dados!$B:$B,MATCH(75,Dados!$O:$O,0)) -> GIORGIO ARMANI | C84: =INDEX(Dados!$C:$C,MATCH(75,Dados!$O:$O,0)) -> Designer/Importado | D84: =INDEX(Dados!$D:$D,MATCH(75,Dados!$O:$O,0)) -> Não | E84: =INDEX(Dados!$N:$N,MATCH(75,Dados!$O:$O,0)) -> 33.024123 | F84: =INDEX(Dados!$H:$H,MATCH(75,Dados!$O:$O,0)) -> 538.46154 | G84: =INDEX(Dados!$K:$K,MATCH(75,Dados!$O:$O,0)) -> 6 | H84: =INDEX(Dados!$L:$L,MATCH(75,Dados!$O:$O,0)) -> Alta | I84: =INDEX(Dados!$I:$I,MATCH(75,Dados!$O:$O,0)) -> Diminuindo | J84: =INDEX(Dados!$F:$F,MATCH(75,Dados!$O:$O,0)) -> 1400000 | K84: =INDEX(Dados!$G:$G,MATCH(75,Dados!$O:$O,0)) -> 2600 | L84: =INDEX(Dados!$J:$J,MATCH(75,Dados!$O:$O,0)) -> 0.8732
A85: =IF(76<=12,"Onda 1 — testar agora",IF(76<=40,"Onda 2 — próximos passos","Onda 3 — depois de consolidar")) -> Onda 3 — depois de consolidar | B85: =INDEX(Dados!$B:$B,MATCH(76,Dados!$O:$O,0)) -> LANCÔME | C85: =INDEX(Dados!$C:$C,MATCH(76,Dados!$O:$O,0)) -> Designer/Importado Premium | D85: =INDEX(Dados!$D:$D,MATCH(76,Dados!$O:$O,0)) -> Não | E85: =INDEX(Dados!$N:$N,MATCH(76,Dados!$O:$O,0)) -> 32.873013 | F85: =INDEX(Dados!$H:$H,MATCH(76,Dados!$O:$O,0)) -> 528.57143 | G85: =INDEX(Dados!$K:$K,MATCH(76,Dados!$O:$O,0)) -> 6 | H85: =INDEX(Dados!$L:$L,MATCH(76,Dados!$O:$O,0)) -> Alta | I85: =INDEX(Dados!$I:$I,MATCH(76,Dados!$O:$O,0)) -> Diminuindo | J85: =INDEX(Dados!$F:$F,MATCH(76,Dados!$O:$O,0)) -> 3700000 | K85: =INDEX(Dados!$G:$G,MATCH(76,Dados!$O:$O,0)) -> 7000 | L85: =INDEX(Dados!$J:$J,MATCH(76,Dados!$O:$O,0)) -> 0.5949
A86: =IF(77<=12,"Onda 1 — testar agora",IF(77<=40,"Onda 2 — próximos passos","Onda 3 — depois de consolidar")) -> Onda 3 — depois de consolidar | B86: =INDEX(Dados!$B:$B,MATCH(77,Dados!$O:$O,0)) -> RALPH LAUREN | C86: =INDEX(Dados!$C:$C,MATCH(77,Dados!$O:$O,0)) -> Designer/Importado | D86: =INDEX(Dados!$D:$D,MATCH(77,Dados!$O:$O,0)) -> Não | E86: =INDEX(Dados!$N:$N,MATCH(77,Dados!$O:$O,0)) -> 30.605126 | F86: =INDEX(Dados!$H:$H,MATCH(77,Dados!$O:$O,0)) -> 382.35294 | G86: =INDEX(Dados!$K:$K,MATCH(77,Dados!$O:$O,0)) -> 7 | H86: =INDEX(Dados!$L:$L,MATCH(77,Dados!$O:$O,0)) -> Alta | I86: =INDEX(Dados!$I:$I,MATCH(77,Dados!$O:$O,0)) -> Diminuindo | J86: =INDEX(Dados!$F:$F,MATCH(77,Dados!$O:$O,0)) -> 1300000 | K86: =INDEX(Dados!$G:$G,MATCH(77,Dados!$O:$O,0)) -> 3400 | L86: =INDEX(Dados!$J:$J,MATCH(77,Dados!$O:$O,0)) -> 0.6327
A87: =IF(78<=12,"Onda 1 — testar agora",IF(78<=40,"Onda 2 — próximos passos","Onda 3 — depois de consolidar")) -> Onda 3 — depois de consolidar | B87: =INDEX(Dados!$B:$B,MATCH(78,Dados!$O:$O,0)) -> O BOTICÁRIO | C87: =INDEX(Dados!$C:$C,MATCH(78,Dados!$O:$O,0)) -> Nacional/Massa | D87: =INDEX(Dados!$D:$D,MATCH(78,Dados!$O:$O,0)) -> Não | E87: =INDEX(Dados!$N:$N,MATCH(78,Dados!$O:$O,0)) -> 29.72783 | F87: =INDEX(Dados!$H:$H,MATCH(78,Dados!$O:$O,0)) -> 165.07385 | G87: =INDEX(Dados!$K:$K,MATCH(78,Dados!$O:$O,0)) -> 526 | H87: =INDEX(Dados!$L:$L,MATCH(78,Dados!$O:$O,0)) -> Média | I87: =INDEX(Dados!$I:$I,MATCH(78,Dados!$O:$O,0)) -> Estável | J87: =INDEX(Dados!$F:$F,MATCH(78,Dados!$O:$O,0)) -> 19000000 | K87: =INDEX(Dados!$G:$G,MATCH(78,Dados!$O:$O,0)) -> 115100 | L87: =INDEX(Dados!$J:$J,MATCH(78,Dados!$O:$O,0)) -> 0.632
A88: =IF(79<=12,"Onda 1 — testar agora",IF(79<=40,"Onda 2 — próximos passos","Onda 3 — depois de consolidar")) -> Onda 3 — depois de consolidar | B88: =INDEX(Dados!$B:$B,MATCH(79,Dados!$O:$O,0)) -> HUGO BOSS | C88: =INDEX(Dados!$C:$C,MATCH(79,Dados!$O:$O,0)) -> Designer/Importado | D88: =INDEX(Dados!$D:$D,MATCH(79,Dados!$O:$O,0)) -> Não | E88: =INDEX(Dados!$N:$N,MATCH(79,Dados!$O:$O,0)) -> 28.404582 | F88: =INDEX(Dados!$H:$H,MATCH(79,Dados!$O:$O,0)) -> 388.88889 | G88: =INDEX(Dados!$K:$K,MATCH(79,Dados!$O:$O,0)) -> 75 | H88: =INDEX(Dados!$L:$L,MATCH(79,Dados!$O:$O,0)) -> Alta | I88: =INDEX(Dados!$I:$I,MATCH(79,Dados!$O:$O,0)) -> Diminuindo | J88: =INDEX(Dados!$F:$F,MATCH(79,Dados!$O:$O,0)) -> 1400000 | K88: =INDEX(Dados!$G:$G,MATCH(79,Dados!$O:$O,0)) -> 3600 | L88: =INDEX(Dados!$J:$J,MATCH(79,Dados!$O:$O,0)) -> 0.7647
A89: =IF(80<=12,"Onda 1 — testar agora",IF(80<=40,"Onda 2 — próximos passos","Onda 3 — depois de consolidar")) -> Onda 3 — depois de consolidar | B89: =INDEX(Dados!$B:$B,MATCH(80,Dados!$O:$O,0)) -> MERCEDES-BENZ | C89: =INDEX(Dados!$C:$C,MATCH(80,Dados!$O:$O,0)) -> Designer/Importado | D89: =INDEX(Dados!$D:$D,MATCH(80,Dados!$O:$O,0)) -> Não | E89: =INDEX(Dados!$N:$N,MATCH(80,Dados!$O:$O,0)) -> 27.786196 | F89: =INDEX(Dados!$H:$H,MATCH(80,Dados!$O:$O,0)) -> 304.13306 | G89: =INDEX(Dados!$K:$K,MATCH(80,Dados!$O:$O,0)) -> 55 | H89: =INDEX(Dados!$L:$L,MATCH(80,Dados!$O:$O,0)) -> Alta | I89: =INDEX(Dados!$I:$I,MATCH(80,Dados!$O:$O,0)) -> Diminuindo | J89: =INDEX(Dados!$F:$F,MATCH(80,Dados!$O:$O,0)) -> 301700 | K89: =INDEX(Dados!$G:$G,MATCH(80,Dados!$O:$O,0)) -> 992 | L89: =INDEX(Dados!$J:$J,MATCH(80,Dados!$O:$O,0)) -> 0.6643
A90: =IF(81<=12,"Onda 1 — testar agora",IF(81<=40,"Onda 2 — próximos passos","Onda 3 — depois de consolidar")) -> Onda 3 — depois de consolidar | B90: =INDEX(Dados!$B:$B,MATCH(81,Dados!$O:$O,0)) -> FINKÈ | C90: =INDEX(Dados!$C:$C,MATCH(81,Dados!$O:$O,0)) -> A verificar | D90: =INDEX(Dados!$D:$D,MATCH(81,Dados!$O:$O,0)) -> Não | E90: =INDEX(Dados!$N:$N,MATCH(81,Dados!$O:$O,0)) -> 27.606163 | F90: =INDEX(Dados!$H:$H,MATCH(81,Dados!$O:$O,0)) -> 188.28571 | G90: =INDEX(Dados!$K:$K,MATCH(81,Dados!$O:$O,0)) -> 8 | H90: =INDEX(Dados!$L:$L,MATCH(81,Dados!$O:$O,0)) -> Alta | I90: =INDEX(Dados!$I:$I,MATCH(81,Dados!$O:$O,0)) -> Diminuindo | J90: =INDEX(Dados!$F:$F,MATCH(81,Dados!$O:$O,0)) -> 263600 | K90: =INDEX(Dados!$G:$G,MATCH(81,Dados!$O:$O,0)) -> 1400 | L90: =INDEX(Dados!$J:$J,MATCH(81,Dados!$O:$O,0)) -> 0.4231
A91: =IF(82<=12,"Onda 1 — testar agora",IF(82<=40,"Onda 2 — próximos passos","Onda 3 — depois de consolidar")) -> Onda 3 — depois de consolidar | B91: =INDEX(Dados!$B:$B,MATCH(82,Dados!$O:$O,0)) -> JACQUES BOGART | C91: =INDEX(Dados!$C:$C,MATCH(82,Dados!$O:$O,0)) -> Designer/Importado | D91: =INDEX(Dados!$D:$D,MATCH(82,Dados!$O:$O,0)) -> Não | E91: =INDEX(Dados!$N:$N,MATCH(82,Dados!$O:$O,0)) -> 27.230061 | F91: =INDEX(Dados!$H:$H,MATCH(82,Dados!$O:$O,0)) -> 265.52 | G91: =INDEX(Dados!$K:$K,MATCH(82,Dados!$O:$O,0)) -> 54 | H91: =INDEX(Dados!$L:$L,MATCH(82,Dados!$O:$O,0)) -> Alta | I91: =INDEX(Dados!$I:$I,MATCH(82,Dados!$O:$O,0)) -> Diminuindo | J91: =INDEX(Dados!$F:$F,MATCH(82,Dados!$O:$O,0)) -> 663800 | K91: =INDEX(Dados!$G:$G,MATCH(82,Dados!$O:$O,0)) -> 2500 | L91: =INDEX(Dados!$J:$J,MATCH(82,Dados!$O:$O,0)) -> 0.6284
A92: =IF(83<=12,"Onda 1 — testar agora",IF(83<=40,"Onda 2 — próximos passos","Onda 3 — depois de consolidar")) -> Onda 3 — depois de consolidar | B92: =INDEX(Dados!$B:$B,MATCH(83,Dados!$O:$O,0)) -> YEAR ONE PERFUMES | C92: =INDEX(Dados!$C:$C,MATCH(83,Dados!$O:$O,0)) -> A verificar | D92: =INDEX(Dados!$D:$D,MATCH(83,Dados!$O:$O,0)) -> Não | E92: =INDEX(Dados!$N:$N,MATCH(83,Dados!$O:$O,0)) -> 26.922418 | F92: =INDEX(Dados!$H:$H,MATCH(83,Dados!$O:$O,0)) -> 130.25 | G92: =INDEX(Dados!$K:$K,MATCH(83,Dados!$O:$O,0)) -> 2 | H92: =INDEX(Dados!$L:$L,MATCH(83,Dados!$O:$O,0)) -> Alta | I92: =INDEX(Dados!$I:$I,MATCH(83,Dados!$O:$O,0)) -> Diminuindo | J92: =INDEX(Dados!$F:$F,MATCH(83,Dados!$O:$O,0)) -> 364700 | K92: =INDEX(Dados!$G:$G,MATCH(83,Dados!$O:$O,0)) -> 2800 | L92: =INDEX(Dados!$J:$J,MATCH(83,Dados!$O:$O,0)) -> 0.1579
A93: =IF(84<=12,"Onda 1 — testar agora",IF(84<=40,"Onda 2 — próximos passos","Onda 3 — depois de consolidar")) -> Onda 3 — depois de consolidar | B93: =INDEX(Dados!$B:$B,MATCH(84,Dados!$O:$O,0)) -> HANNITY COSMETICOS | C93: =INDEX(Dados!$C:$C,MATCH(84,Dados!$O:$O,0)) -> A verificar | D93: =INDEX(Dados!$D:$D,MATCH(84,Dados!$O:$O,0)) -> Não | E93: =INDEX(Dados!$N:$N,MATCH(84,Dados!$O:$O,0)) -> 26.762561 | F93: =INDEX(Dados!$H:$H,MATCH(84,Dados!$O:$O,0)) -> 144.14286 | G93: =INDEX(Dados!$K:$K,MATCH(84,Dados!$O:$O,0)) -> 13 | H93: =INDEX(Dados!$L:$L,MATCH(84,Dados!$O:$O,0)) -> Alta | I93: =INDEX(Dados!$I:$I,MATCH(84,Dados!$O:$O,0)) -> Diminuindo | J93: =INDEX(Dados!$F:$F,MATCH(84,Dados!$O:$O,0)) -> 302700 | K93: =INDEX(Dados!$G:$G,MATCH(84,Dados!$O:$O,0)) -> 2100 | L93: =INDEX(Dados!$J:$J,MATCH(84,Dados!$O:$O,0)) -> 0.9375
A94: =IF(85<=12,"Onda 1 — testar agora",IF(85<=40,"Onda 2 — próximos passos","Onda 3 — depois de consolidar")) -> Onda 3 — depois de consolidar | B94: =INDEX(Dados!$B:$B,MATCH(85,Dados!$O:$O,0)) -> CACHAREL | C94: =INDEX(Dados!$C:$C,MATCH(85,Dados!$O:$O,0)) -> Designer/Importado | D94: =INDEX(Dados!$D:$D,MATCH(85,Dados!$O:$O,0)) -> Não | E94: =INDEX(Dados!$N:$N,MATCH(85,Dados!$O:$O,0)) -> 26.722515 | F94: =INDEX(Dados!$H:$H,MATCH(85,Dados!$O:$O,0)) -> 214.58824 | G94: =INDEX(Dados!$K:$K,MATCH(85,Dados!$O:$O,0)) -> 46 | H94: =INDEX(Dados!$L:$L,MATCH(85,Dados!$O:$O,0)) -> Alta | I94: =INDEX(Dados!$I:$I,MATCH(85,Dados!$O:$O,0)) -> Diminuindo | J94: =INDEX(Dados!$F:$F,MATCH(85,Dados!$O:$O,0)) -> 364800 | K94: =INDEX(Dados!$G:$G,MATCH(85,Dados!$O:$O,0)) -> 1700 | L94: =INDEX(Dados!$J:$J,MATCH(85,Dados!$O:$O,0)) -> 0.7025
A95: =IF(86<=12,"Onda 1 — testar agora",IF(86<=40,"Onda 2 — próximos passos","Onda 3 — depois de consolidar")) -> Onda 3 — depois de consolidar | B95: =INDEX(Dados!$B:$B,MATCH(86,Dados!$O:$O,0)) -> DAVIDOFF | C95: =INDEX(Dados!$C:$C,MATCH(86,Dados!$O:$O,0)) -> Designer/Importado | D95: =INDEX(Dados!$D:$D,MATCH(86,Dados!$O:$O,0)) -> Não | E95: =INDEX(Dados!$N:$N,MATCH(86,Dados!$O:$O,0)) -> 26.55006 | F95: =INDEX(Dados!$H:$H,MATCH(86,Dados!$O:$O,0)) -> 218.8 | G95: =INDEX(Dados!$K:$K,MATCH(86,Dados!$O:$O,0)) -> 53 | H95: =INDEX(Dados!$L:$L,MATCH(86,Dados!$O:$O,0)) -> Alta | I95: =INDEX(Dados!$I:$I,MATCH(86,Dados!$O:$O,0)) -> Diminuindo | J95: =INDEX(Dados!$F:$F,MATCH(86,Dados!$O:$O,0)) -> 218800 | K95: =INDEX(Dados!$G:$G,MATCH(86,Dados!$O:$O,0)) -> 1000 | L95: =INDEX(Dados!$J:$J,MATCH(86,Dados!$O:$O,0)) -> 0.6591
A96: =IF(87<=12,"Onda 1 — testar agora",IF(87<=40,"Onda 2 — próximos passos","Onda 3 — depois de consolidar")) -> Onda 3 — depois de consolidar | B96: =INDEX(Dados!$B:$B,MATCH(87,Dados!$O:$O,0)) -> BELARA - LATTAFA | C96: =INDEX(Dados!$C:$C,MATCH(87,Dados!$O:$O,0)) -> Árabe/Import Acessível | D96: =INDEX(Dados!$D:$D,MATCH(87,Dados!$O:$O,0)) -> Não | E96: =INDEX(Dados!$N:$N,MATCH(87,Dados!$O:$O,0)) -> 26.355306 | F96: =INDEX(Dados!$H:$H,MATCH(87,Dados!$O:$O,0)) -> 175.05556 | G96: =INDEX(Dados!$K:$K,MATCH(87,Dados!$O:$O,0)) -> 39 | H96: =INDEX(Dados!$L:$L,MATCH(87,Dados!$O:$O,0)) -> Alta | I96: =INDEX(Dados!$I:$I,MATCH(87,Dados!$O:$O,0)) -> Diminuindo | J96: =INDEX(Dados!$F:$F,MATCH(87,Dados!$O:$O,0)) -> 315100 | K96: =INDEX(Dados!$G:$G,MATCH(87,Dados!$O:$O,0)) -> 1800 | L96: =INDEX(Dados!$J:$J,MATCH(87,Dados!$O:$O,0)) -> 0.7222
A97: =IF(88<=12,"Onda 1 — testar agora",IF(88<=40,"Onda 2 — próximos passos","Onda 3 — depois de consolidar")) -> Onda 3 — depois de consolidar | B97: =INDEX(Dados!$B:$B,MATCH(88,Dados!$O:$O,0)) -> PRIMACIAL | C97: =INDEX(Dados!$C:$C,MATCH(88,Dados!$O:$O,0)) -> A verificar | D97: =INDEX(Dados!$D:$D,MATCH(88,Dados!$O:$O,0)) -> Não | E97: =INDEX(Dados!$N:$N,MATCH(88,Dados!$O:$O,0)) -> 26.086994 | F97: =INDEX(Dados!$H:$H,MATCH(88,Dados!$O:$O,0)) -> 80 | G97: =INDEX(Dados!$K:$K,MATCH(88,Dados!$O:$O,0)) -> 4 | H97: =INDEX(Dados!$L:$L,MATCH(88,Dados!$O:$O,0)) -> Alta | I97: =INDEX(Dados!$I:$I,MATCH(88,Dados!$O:$O,0)) -> Diminuindo | J97: =INDEX(Dados!$F:$F,MATCH(88,Dados!$O:$O,0)) -> 3400000 | K97: =INDEX(Dados!$G:$G,MATCH(88,Dados!$O:$O,0)) -> 42500 | L97: =INDEX(Dados!$J:$J,MATCH(88,Dados!$O:$O,0)) -> 0.7927
A98: =IF(89<=12,"Onda 1 — testar agora",IF(89<=40,"Onda 2 — próximos passos","Onda 3 — depois de consolidar")) -> Onda 3 — depois de consolidar | B98: =INDEX(Dados!$B:$B,MATCH(89,Dados!$O:$O,0)) -> ATTRACIONE | C98: =INDEX(Dados!$C:$C,MATCH(89,Dados!$O:$O,0)) -> A verificar | D98: =INDEX(Dados!$D:$D,MATCH(89,Dados!$O:$O,0)) -> Não | E98: =INDEX(Dados!$N:$N,MATCH(89,Dados!$O:$O,0)) -> 25.573589 | F98: =INDEX(Dados!$H:$H,MATCH(89,Dados!$O:$O,0)) -> 55.254335 | G98: =INDEX(Dados!$K:$K,MATCH(89,Dados!$O:$O,0)) -> 8 | H98: =INDEX(Dados!$L:$L,MATCH(89,Dados!$O:$O,0)) -> Alta | I98: =INDEX(Dados!$I:$I,MATCH(89,Dados!$O:$O,0)) -> Diminuindo | J98: =INDEX(Dados!$F:$F,MATCH(89,Dados!$O:$O,0)) -> 955900 | K98: =INDEX(Dados!$G:$G,MATCH(89,Dados!$O:$O,0)) -> 17300 | L98: =INDEX(Dados!$J:$J,MATCH(89,Dados!$O:$O,0)) -> 0.4545
A99: =IF(90<=12,"Onda 1 — testar agora",IF(90<=40,"Onda 2 — próximos passos","Onda 3 — depois de consolidar")) -> Onda 3 — depois de consolidar | B99: =INDEX(Dados!$B:$B,MATCH(90,Dados!$O:$O,0)) -> EZ COSMÉTICOS | C99: =INDEX(Dados!$C:$C,MATCH(90,Dados!$O:$O,0)) -> Nacional/Massa | D99: =INDEX(Dados!$D:$D,MATCH(90,Dados!$O:$O,0)) -> Não | E99: =INDEX(Dados!$N:$N,MATCH(90,Dados!$O:$O,0)) -> 25.475074 | F99: =INDEX(Dados!$H:$H,MATCH(90,Dados!$O:$O,0)) -> 37.735849 | G99: =INDEX(Dados!$K:$K,MATCH(90,Dados!$O:$O,0)) -> 3 | H99: =INDEX(Dados!$L:$L,MATCH(90,Dados!$O:$O,0)) -> Alta | I99: =INDEX(Dados!$I:$I,MATCH(90,Dados!$O:$O,0)) -> Diminuindo | J99: =INDEX(Dados!$F:$F,MATCH(90,Dados!$O:$O,0)) -> 1000000 | K99: =INDEX(Dados!$G:$G,MATCH(90,Dados!$O:$O,0)) -> 26500 | L99: =INDEX(Dados!$J:$J,MATCH(90,Dados!$O:$O,0)) -> 0.3871
A100: =IF(91<=12,"Onda 1 — testar agora",IF(91<=40,"Onda 2 — próximos passos","Onda 3 — depois de consolidar")) -> Onda 3 — depois de consolidar | B100: =INDEX(Dados!$B:$B,MATCH(91,Dados!$O:$O,0)) -> BANDERAS | C100: =INDEX(Dados!$C:$C,MATCH(91,Dados!$O:$O,0)) -> Designer/Importado | D100: =INDEX(Dados!$D:$D,MATCH(91,Dados!$O:$O,0)) -> Não | E100: =INDEX(Dados!$N:$N,MATCH(91,Dados!$O:$O,0)) -> 24.922258 | F100: =INDEX(Dados!$H:$H,MATCH(91,Dados!$O:$O,0)) -> 176.47059 | G100: =INDEX(Dados!$K:$K,MATCH(91,Dados!$O:$O,0)) -> 82 | H100: =INDEX(Dados!$L:$L,MATCH(91,Dados!$O:$O,0)) -> Alta | I100: =INDEX(Dados!$I:$I,MATCH(91,Dados!$O:$O,0)) -> Diminuindo | J100: =INDEX(Dados!$F:$F,MATCH(91,Dados!$O:$O,0)) -> 1200000 | K100: =INDEX(Dados!$G:$G,MATCH(91,Dados!$O:$O,0)) -> 6800 | L100: =INDEX(Dados!$J:$J,MATCH(91,Dados!$O:$O,0)) -> 0.726
A101: =IF(92<=12,"Onda 1 — testar agora",IF(92<=40,"Onda 2 — próximos passos","Onda 3 — depois de consolidar")) -> Onda 3 — depois de consolidar | B101: =INDEX(Dados!$B:$B,MATCH(92,Dados!$O:$O,0)) -> AMAKHA PARIS | C101: =INDEX(Dados!$C:$C,MATCH(92,Dados!$O:$O,0)) -> Nacional/Massa | D101: =INDEX(Dados!$D:$D,MATCH(92,Dados!$O:$O,0)) -> Não | E101: =INDEX(Dados!$N:$N,MATCH(92,Dados!$O:$O,0)) -> 24.901901 | F101: =INDEX(Dados!$H:$H,MATCH(92,Dados!$O:$O,0)) -> 44.504505 | G101: =INDEX(Dados!$K:$K,MATCH(92,Dados!$O:$O,0)) -> 23 | H101: =INDEX(Dados!$L:$L,MATCH(92,Dados!$O:$O,0)) -> Alta | I101: =INDEX(Dados!$I:$I,MATCH(92,Dados!$O:$O,0)) -> Diminuindo | J101: =INDEX(Dados!$F:$F,MATCH(92,Dados!$O:$O,0)) -> 494000 | K101: =INDEX(Dados!$G:$G,MATCH(92,Dados!$O:$O,0)) -> 11100 | L101: =INDEX(Dados!$J:$J,MATCH(92,Dados!$O:$O,0)) -> 0.5706
A102: =IF(93<=12,"Onda 1 — testar agora",IF(93<=40,"Onda 2 — próximos passos","Onda 3 — depois de consolidar")) -> Onda 3 — depois de consolidar | B102: =INDEX(Dados!$B:$B,MATCH(93,Dados!$O:$O,0)) -> BRITNEY SPEARS | C102: =INDEX(Dados!$C:$C,MATCH(93,Dados!$O:$O,0)) -> Designer/Importado | D102: =INDEX(Dados!$D:$D,MATCH(93,Dados!$O:$O,0)) -> Não | E102: =INDEX(Dados!$N:$N,MATCH(93,Dados!$O:$O,0)) -> 24.843057 | F102: =INDEX(Dados!$H:$H,MATCH(93,Dados!$O:$O,0)) -> 189 | G102: =INDEX(Dados!$K:$K,MATCH(93,Dados!$O:$O,0)) -> 90 | H102: =INDEX(Dados!$L:$L,MATCH(93,Dados!$O:$O,0)) -> Alta | I102: =INDEX(Dados!$I:$I,MATCH(93,Dados!$O:$O,0)) -> Diminuindo | J102: =INDEX(Dados!$F:$F,MATCH(93,Dados!$O:$O,0)) -> 302400 | K102: =INDEX(Dados!$G:$G,MATCH(93,Dados!$O:$O,0)) -> 1600 | L102: =INDEX(Dados!$J:$J,MATCH(93,Dados!$O:$O,0)) -> 0.719
...

Sheet Dados
A1: # | B1: Marca | C1: Posicionamento (classificação) | D1: Já no seu mix de nicho? | E1: Variação Ranking | F1: Vendas (R$) | G1: Unidades Vendidas | H1: Ticket Médio (R$) | I1: Tendência | J1: % Catálogo | K1: Nº Vendedores | L1: Saturação | M1: Ranking de Demanda (Nubmetrics) | N1: Pontuação (0-100) | O1: Rank Pontuação (auxiliar)
A2: 1 | B2: NATURA | C2: Nacional/Massa | D2: Não | E2: 1 | F2: 20900000 | G2: 161600 | H2: 129.33168 | I2: Estável | J2: 0.613 | K2: 549 | L2: Alta | M2: 23 | N2: =100*('Priorização de Entrada'!$B$3*(H2/MAX(H$2:H$101))+'Priorização de Entrada'!$B$4*(1-K2/MAX(K$2:K$101))+'Priorização de Entrada'!$B$5*(IF(L2="Baixa",1,IF(L2="Média",0.5,0)))+'Priorização de Entrada'!$B$6*(IF(I2="Crescendo",1,IF(I2="Estável",0.5,0)))) -> 18.403651 | O2: =SUMPRODUCT(($N$2:$N$101>N2)*1)+SUMPRODUCT(($N$2:N2=N2)*1) -> 98
A3: 2 | B3: LATTAFA | C3: Árabe/Import Acessível | D3: Não | E3: 1 | F3: 19000000 | G3: 99000 | H3: 191.91919 | I3: Estável | J3: 0.6514 | K3: 739 | L3: Média | M3: 0 | N3: =100*('Priorização de Entrada'!$B$3*(H3/MAX(H$2:H$101))+'Priorização de Entrada'!$B$4*(1-K3/MAX(K$2:K$101))+'Priorização de Entrada'!$B$5*(IF(L3="Baixa",1,IF(L3="Média",0.5,0)))+'Priorização de Entrada'!$B$6*(IF(I3="Crescendo",1,IF(I3="Estável",0.5,0)))) -> 22.932314 | O3: =SUMPRODUCT(($N$2:$N$101>N3)*1)+SUMPRODUCT(($N$2:N3=N3)*1) -> 96
A4: 3 | B4: O BOTICÁRIO | C4: Nacional/Massa | D4: Não | E4: -2 | F4: 19000000 | G4: 115100 | H4: 165.07385 | I4: Estável | J4: 0.632 | K4: 526 | L4: Média | M4: 17 | N4: =100*('Priorização de Entrada'!$B$3*(H4/MAX(H$2:H$101))+'Priorização de Entrada'!$B$4*(1-K4/MAX(K$2:K$101))+'Priorização de Entrada'!$B$5*(IF(L4="Baixa",1,IF(L4="Média",0.5,0)))+'Priorização de Entrada'!$B$6*(IF(I4="Crescendo",1,IF(I4="Estável",0.5,0)))) -> 29.72783 | O4: =SUMPRODUCT(($N$2:$N$101>N4)*1)+SUMPRODUCT(($N$2:N4=N4)*1) -> 78
A5: 4 | B5: CAROLINA HERRERA | C5: Designer/Importado | D5: Não | E5: 0 | F5: 10200000 | G5: 19500 | H5: 523.07692 | I5: Estável | J5: 0.6718 | K5: 29 | L5: Alta | M5: 0 | N5: =100*('Priorização de Entrada'!$B$3*(H5/MAX(H$2:H$101))+'Priorização de Entrada'!$B$4*(1-K5/MAX(K$2:K$101))+'Priorização de Entrada'!$B$5*(IF(L5="Baixa",1,IF(L5="Média",0.5,0)))+'Priorização de Entrada'!$B$6*(IF(I5="Crescendo",1,IF(I5="Estável",0.5,0)))) -> 42.010985 | O5: =SUMPRODUCT(($N$2:$N$101>N5)*1)+SUMPRODUCT(($N$2:N5=N5)*1) -> 56
A6: 5 | B6: ARMAF | C6: Árabe/Import Acessível | D6: Não | E6: 2 | F6: 8500000 | G6: 34800 | H6: 244.25287 | I6: Crescendo | J6: 0.6872 | K6: 264 | L6: Alta | M6: 0 | N6: =100*('Priorização de Entrada'!$B$3*(H6/MAX(H$2:H$101))+'Priorização de Entrada'!$B$4*(1-K6/MAX(K$2:K$101))+'Priorização de Entrada'!$B$5*(IF(L6="Baixa",1,IF(L6="Média",0.5,0)))+'Priorização de Entrada'!$B$6*(IF(I6="Crescendo",1,IF(I6="Estável",0.5,0)))) -> 39.800928 | O6: =SUMPRODUCT(($N$2:$N$101>N6)*1)+SUMPRODUCT(($N$2:N6=N6)*1) -> 60
A7: 6 | B7: AL WATANIAH | C7: Árabe/Import Acessível | D7: Não | E7: -1 | F7: 8300000 | G7: 61600 | H7: 134.74026 | I7: Diminuindo | J7: 0.6549 | K7: 431 | L7: Alta | M7: 0 | N7: =100*('Priorização de Entrada'!$B$3*(H7/MAX(H$2:H$101))+'Priorização de Entrada'!$B$4*(1-K7/MAX(K$2:K$101))+'Priorização de Entrada'!$B$5*(IF(L7="Baixa",1,IF(L7="Média",0.5,0)))+'Priorização de Entrada'!$B$6*(IF(I7="Crescendo",1,IF(I7="Estável",0.5,0)))) -> 12.478169 | O7: =SUMPRODUCT(($N$2:$N$101>N7)*1)+SUMPRODUCT(($N$2:N7=N7)*1) -> 100
A8: 7 | B8: RABANNE | C8: Designer/Importado | D8: Não | E8: -1 | F8: 8100000 | G8: 14100 | H8: 574.46809 | I8: Estável | J8: 0.6857 | K8: 32 | L8: Média | M8: 0 | N8: =100*('Priorização de Entrada'!$B$3*(H8/MAX(H$2:H$101))+'Priorização de Entrada'!$B$4*(1-K8/MAX(K$2:K$101))+'Priorização de Entrada'!$B$5*(IF(L8="Baixa",1,IF(L8="Média",0.5,0)))+'Priorização de Entrada'!$B$6*(IF(I8="Crescendo",1,IF(I8="Estável",0.5,0)))) -> 52.694697 | O8: =SUMPRODUCT(($N$2:$N$101>N8)*1)+SUMPRODUCT(($N$2:N8=N8)*1) -> 31
A9: 8 | B9: JEAN PAUL GAULTIER | C9: Designer/Importado | D9: Não | E9: 4 | F9: 4600000 | G9: 7200 | H9: 638.88889 | I9: Crescendo | J9: 0.7093 | K9: 27 | L9: Alta | M9: 46 | N9: =100*('Priorização de Entrada'!$B$3*(H9/MAX(H$2:H$101))+'Priorização de Entrada'!$B$4*(1-K9/MAX(K$2:K$101))+'Priorização de Entrada'!$B$5*(IF(L9="Baixa",1,IF(L9="Média",0.5,0)))+'Priorização de Entrada'!$B$6*(IF(I9="Crescendo",1,IF(I9="Estável",0.5,0)))) -> 53.848123 | O9: =SUMPRODUCT(($N$2:$N$101>N9)*1)+SUMPRODUCT(($N$2:N9=N9)*1) -> 27
A10: 9 | B10: MAISON ALHAMBRA | C10: Árabe/Import Acessível | D10: Não | E10: 0 | F10: 4400000 | G10: 27600 | H10: 159.42029 | I10: Estável | J10: 0.6829 | K10: 371 | L10: Média | M10: 0 | N10: =100*('Priorização de Entrada'!$B$3*(H10/MAX(H$2:H$101))+'Priorização de Entrada'!$B$4*(1-K10/MAX(K$2:K$101))+'Priorização de Entrada'!$B$5*(IF(L10="Baixa",1,IF(L10="Média",0.5,0)))+'Priorização de Entrada'!$B$6*(IF(I10="Crescendo",1,IF(I10="Estável",0.5,0)))) -> 34.885023 | O10: =SUMPRODUCT(($N$2:$N$101>N10)*1)+SUMPRODUCT(($N$2:N10=N10)*1) -> 71
A11: 10 | B11: LIPX | C11: A verificar | D11: Não | E11: 1 | F11: 4100000 | G11: 21000 | H11: 195.2381 | I11: Crescendo | J11: 0.8333 | K11: 36 | L11: Alta | M11: 0 | N11: =100*('Priorização de Entrada'!$B$3*(H11/MAX(H$2:H$101))+'Priorização de Entrada'!$B$4*(1-K11/MAX(K$2:K$101))+'Priorização de Entrada'!$B$5*(IF(L11="Baixa",1,IF(L11="Média",0.5,0)))+'Priorização de Entrada'!$B$6*(IF(I11="Crescendo",1,IF(I11="Estável",0.5,0)))) -> 46.765161 | O11: =SUMPRODUCT(($N$2:$N$101>N11)*1)+SUMPRODUCT(($N$2:N11=N11)*1) -> 38
A12: 11 | B12: EUDORA | C12: Nacional/Massa | D12: Não | E12: 2 | F12: 3900000 | G12: 39400 | H12: 98.984772 | I12: Crescendo | J12: 0.6278 | K12: 375 | L12: Alta | M12: 43 | N12: =100*('Priorização de Entrada'!$B$3*(H12/MAX(H$2:H$101))+'Priorização de Entrada'!$B$4*(1-K12/MAX(K$2:K$101))+'Priorização de Entrada'!$B$5*(IF(L12="Baixa",1,IF(L12="Média",0.5,0)))+'Priorização de Entrada'!$B$6*(IF(I12="Crescendo",1,IF(I12="Estável",0.5,0)))) -> 33.826316 | O12: =SUMPRODUCT(($N$2:$N$101>N12)*1)+SUMPRODUCT(($N$2:N12=N12)*1) -> 73
A13: 12 | B13: LANCÔME | C13: Designer/Importado Premium | D13: Não | E13: -4 | F13: 3700000 | G13: 7000 | H13: 528.57143 | I13: Diminuindo | J13: 0.5949 | K13: 6 | L13: Alta | M13: 0 | N13: =100*('Priorização de Entrada'!$B$3*(H13/MAX(H$2:H$101))+'Priorização de Entrada'!$B$4*(1-K13/MAX(K$2:K$101))+'Priorização de Entrada'!$B$5*(IF(L13="Baixa",1,IF(L13="Média",0.5,0)))+'Priorização de Entrada'!$B$6*(IF(I13="Crescendo",1,IF(I13="Estável",0.5,0)))) -> 32.873013 | O13: =SUMPRODUCT(($N$2:$N$101>N13)*1)+SUMPRODUCT(($N$2:N13=N13)*1) -> 76
... A101: 100 | B101: AL HARAMAIN | C101: Árabe/Import Acessível | D101: Não | E101: 7 | F101: 218100 | G101: 679 | H101: 321.20766 | I101: Crescendo | J101: 0.7247 | K101: 68 | L101: Baixa | M101: 0 | N101: =100*('Priorização de Entrada'!$B$3*(H101/MAX(H$2:H$101))+'Priorização de Entrada'!$B$4*(1-K101/MAX(K$2:K$101))+'Priorização de Entrada'!$B$5*(IF(L101="Baixa",1,IF(L101="Média",0.5,0)))+'Priorização de Entrada'!$B$6*(IF(I101="Crescendo",1,IF(I101="Estável",0.5,0)))) -> 67.607294 | O101: =SUMPRODUCT(($N$2:$N$101>N101)*1)+SUMPRODUCT(($N$2:N101=N101)*1) -> 8
